Workbook

Sheet Weekly_Cash_Flow_Summary
A1: 13-Week Rolling Cash Flow Forecast
A3: As of Date | B3: =Cash_Balance!E1 -> 46230 | F3: Week | G3: Week Start | H3: Week End | I3: Inflow(AR) | J3: Outflow(AP) | K3: Net Cash Flow | L3: Ending Bal | M3: Below Threshold?
A4: Beginning Cash | B4: =Cash_Balance!E2 -> 1938408 | F4: 1 | G4: =$B$3+(1-1)*7 -> 46230 | H4: =$B$3+(1-1)*7+6 -> 46236 | I4: =SUMPRODUCT((AR_detail!$L$2:$L$121>=G4)*(AR_detail!$L$2:$L$121<=H4)*(AR_detail!$J$2:$J$121<>"Collected")*AR_detail!$H$2:$H$121*AR_detail!$M$2:$M$121) -> 3161845 | J4: =SUMPRODUCT((AP_detail!$L$2:$L$101>=G4)*(AP_detail!$L$2:$L$101<=H4)*(AP_detail!$J$2:$J$101<>"Paid")*AP_detail!$H$2:$H$101) -> 1847500 | K4: =I4-J4 -> 1314345 | L4: =$B$4+K4 -> 3252753 | M4: =IF(L4<$B$5,"WARNING","OK") -> OK
A5: Min Cash Threshold | B5: =Cash_Balance!E3 -> 1500000 | F5: 2 | G5: =$B$3+(2-1)*7 -> 46237 | H5: =$B$3+(2-1)*7+6 -> 46243 | I5: =SUMPRODUCT((AR_detail!$L$2:$L$121>=G5)*(AR_detail!$L$2:$L$121<=H5)*(AR_detail!$J$2:$J$121<>"Collected")*AR_detail!$H$2:$H$121*AR_detail!$M$2:$M$121) -> 1260675 | J5: =SUMPRODUCT((AP_detail!$L$2:$L$101>=G5)*(AP_detail!$L$2:$L$101<=H5)*(AP_detail!$J$2:$J$101<>"Paid")*AP_detail!$H$2:$H$101) -> 1500500 | K5: =I5-J5 -> -239825 | L5: =L4+K5 -> 3012928 | M5: =IF(L5<$B$5,"WARNING","OK") -> OK
A6: Scenario | B6: Base | F6: 3 | G6: =$B$3+(3-1)*7 -> 46244 | H6: =$B$3+(3-1)*7+6 -> 46250 | I6: {=SUMPRODUCT((AR_detail!$L$2:$L$121>=G6)*(AR_detail!$L$2:$L$121<=H6)*(AR_detail!$J$2:$J$121<>"Collected")*AR_detail!$H$2:$H$121*AR_detail!$M$2:$M$121)} -> 1589265 | J6: =SUMPRODUCT((AP_detail!$L$2:$L$101>=G6)*(AP_detail!$L$2:$L$101<=H6)*(AP_detail!$J$2:$J$101<>"Paid")*AP_detail!$H$2:$H$101) -> 952500 | K6: =I6-J6 -> 636765 | L6: =L5+K6 -> 3649693 | M6: =IF(L6<$B$5,"WARNING","OK") -> OK
A7: Probability_Adjustment | B7: =INDEX($B$13:$B$15,MATCH($B$6,$A$13:$A$15,0)) -> 0 | F7: 4 | G7: =$B$3+(4-1)*7 -> 46251 | H7: =$B$3+(4-1)*7+6 -> 46257 | I7: =SUMPRODUCT((AR_detail!$L$2:$L$121>=G7)*(AR_detail!$L$2:$L$121<=H7)*(AR_detail!$J$2:$J$121<>"Collected")*AR_detail!$H$2:$H$121*AR_detail!$M$2:$M$121) -> 186915 | J7: =SUMPRODUCT((AP_detail!$L$2:$L$101>=G7)*(AP_detail!$L$2:$L$101<=H7)*(AP_detail!$J$2:$J$101<>"Paid")*AP_detail!$H$2:$H$101) -> 0 | K7: =I7-J7 -> 186915 | L7: =L6+K7 -> 3836608 | M7: =IF(L7<$B$5,"WARNING","OK") -> OK
A8: AR_Delay_Multiplier | B8: =INDEX($C$13:$C$15,MATCH($B$6,$A$13:$A$15,0)) -> 1 | F8: 5 | G8: =$B$3+(5-1)*7 -> 46258 | H8: =$B$3+(5-1)*7+6 -> 46264 | I8: {=SUMPRODUCT((AR_detail!$L$2:$L$121>=G8)*(AR_detail!$L$2:$L$121<=H8)*(AR_detail!$J$2:$J$121<>"Collected")*AR_detail!$H$2:$H$121*AR_detail!$M$2:$M$121)} -> 941010 | J8: {=SUMPRODUCT((AP_detail!$L$2:$L$101>=G8)*(AP_detail!$L$2:$L$101<=H8)*(AP_detail!$J$2:$J$101<>"Paid")*AP_detail!$H$2:$H$101)} -> 1485500 | K8: =I8-J8 -> -544490 | L8: =L7+K8 -> 3292118 | M8: =IF(L8<$B$5,"WARNING","OK") -> OK
A9: AP_Stretch_Multiplier | B9: =INDEX($D$13:$D$15,MATCH($B$6,$A$13:$A$15,0)) -> 1 | F9: 6 | G9: =$B$3+(6-1)*7 -> 46265 | H9: =$B$3+(6-1)*7+6 -> 46271 | I9: =SUMPRODUCT((AR_detail!$L$2:$L$121>=G9)*(AR_detail!$L$2:$L$121<=H9)*(AR_detail!$J$2:$J$121<>"Collected")*AR_detail!$H$2:$H$121*AR_detail!$M$2:$M$121) -> 50400 | J9: {=SUMPRODUCT((AP_detail!$L$2:$L$101>=G9)*(AP_detail!$L$2:$L$101<=H9)*(AP_detail!$J$2:$J$101<>"Paid")*AP_detail!$H$2:$H$101)} -> 132000 | K9: =I9-J9 -> -81600 | L9: =L8+K9 -> 3210518 | M9: =IF(L9<$B$5,"WARNING","OK") -> OK
F10: 7 | G10: =$B$3+(7-1)*7 -> 46272 | H10: =$B$3+(7-1)*7+6 -> 46278 | I10: =SUMPRODUCT((AR_detail!$L$2:$L$121>=G10)*(AR_detail!$L$2:$L$121<=H10)*(AR_detail!$J$2:$J$121<>"Collected")*AR_detail!$H$2:$H$121*AR_detail!$M$2:$M$121) -> 24750 | J10: =SUMPRODUCT((AP_detail!$L$2:$L$101>=G10)*(AP_detail!$L$2:$L$101<=H10)*(AP_detail!$J$2:$J$101<>"Paid")*AP_detail!$H$2:$H$101) -> 173000 | K10: =I10-J10 -> -148250 | L10: =L9+K10 -> 3062268 | M10: =IF(L10<$B$5,"WARNING","OK") -> OK
A11: Scenario assumption table (edit these to adjust the model) | F11: 8 | G11: =$B$3+(8-1)*7 -> 46279 | H11: =$B$3+(8-1)*7+6 -> 46285 | I11: =SUMPRODUCT((AR_detail!$L$2:$L$121>=G11)*(AR_detail!$L$2:$L$121<=H11)*(AR_detail!$J$2:$J$121<>"Collected")*AR_detail!$H$2:$H$121*AR_detail!$M$2:$M$121) -> 815475 | J11: =SUMPRODUCT((AP_detail!$L$2:$L$101>=G11)*(AP_detail!$L$2:$L$101<=H11)*(AP_detail!$J$2:$J$101<>"Paid")*AP_detail!$H$2:$H$101) -> 0 | K11: =I11-J11 -> 815475 | L11: =L10+K11 -> 3877743 | M11: =IF(L11<$B$5,"WARNING","OK") -> OK
A12: Scenario | B12: Prob Adj | C12: AR Delay Mult | D12: AP Stretch Mult | F12: 9 | G12: =$B$3+(9-1)*7 -> 46286 | H12: =$B$3+(9-1)*7+6 -> 46292 | I12: =SUMPRODUCT((AR_detail!$L$2:$L$121>=G12)*(AR_detail!$L$2:$L$121<=H12)*(AR_detail!$J$2:$J$121<>"Collected")*AR_detail!$H$2:$H$121*AR_detail!$M$2:$M$121) -> 0 | J12: =SUMPRODUCT((AP_detail!$L$2:$L$101>=G12)*(AP_detail!$L$2:$L$101<=H12)*(AP_detail!$J$2:$J$101<>"Paid")*AP_detail!$H$2:$H$101) -> 0 | K12: =I12-J12 -> 0 | L12: =L11+K12 -> 3877743 | M12: =IF(L12<$B$5,"WARNING","OK") -> OK
A13: Best | B13: 0.05 | C13: 0.5 | D13: 0.8 | F13: 10 | G13: =$B$3+(10-1)*7 -> 46293 | H13: =$B$3+(10-1)*7+6 -> 46299 | I13: =SUMPRODUCT((AR_detail!$L$2:$L$121>=G13)*(AR_detail!$L$2:$L$121<=H13)*(AR_detail!$J$2:$J$121<>"Collected")*AR_detail!$H$2:$H$121*AR_detail!$M$2:$M$121) -> 117450 | J13: =SUMPRODUCT((AP_detail!$L$2:$L$101>=G13)*(AP_detail!$L$2:$L$101<=H13)*(AP_detail!$J$2:$J$101<>"Paid")*AP_detail!$H$2:$H$101) -> 1033000 | K13: =I13-J13 -> -915550 | L13: =L12+K13 -> 2962193 | M13: =IF(L13<$B$5,"WARNING","OK") -> OK
A14: Base | B14: 0 | C14: 1 | D14: 1 | F14: 11 | G14: =$B$3+(11-1)*7 -> 46300 | H14: =$B$3+(11-1)*7+6 -> 46306 | I14: =SUMPRODUCT((AR_detail!$L$2:$L$121>=G14)*(AR_detail!$L$2:$L$121<=H14)*(AR_detail!$J$2:$J$121<>"Collected")*AR_detail!$H$2:$H$121*AR_detail!$M$2:$M$121) -> 0 | J14: =SUMPRODUCT((AP_detail!$L$2:$L$101>=G14)*(AP_detail!$L$2:$L$101<=H14)*(AP_detail!$J$2:$J$101<>"Paid")*AP_detail!$H$2:$H$101) -> 0 | K14: =I14-J14 -> 0 | L14: =L13+K14 -> 2962193 | M14: =IF(L14<$B$5,"WARNING","OK") -> OK
A15: Worst | B15: -0.15 | C15: 2 | D15: 1.8 | F15: 12 | G15: =$B$3+(12-1)*7 -> 46307 | H15: =$B$3+(12-1)*7+6 -> 46313 | I15: =SUMPRODUCT((AR_detail!$L$2:$L$121>=G15)*(AR_detail!$L$2:$L$121<=H15)*(AR_detail!$J$2:$J$121<>"Collected")*AR_detail!$H$2:$H$121*AR_detail!$M$2:$M$121) -> 0 | J15: =SUMPRODUCT((AP_detail!$L$2:$L$101>=G15)*(AP_detail!$L$2:$L$101<=H15)*(AP_detail!$J$2:$J$101<>"Paid")*AP_detail!$H$2:$H$101) -> 0 | K15: =I15-J15 -> 0 | L15: =L14+K15 -> 2962193 | M15: =IF(L15<$B$5,"WARNING","OK") -> OK
F16: 13 | G16: =$B$3+(13-1)*7 -> 46314 | H16: =$B$3+(13-1)*7+6 -> 46320 | I16: =SUMPRODUCT((AR_detail!$L$2:$L$121>=G16)*(AR_detail!$L$2:$L$121<=H16)*(AR_detail!$J$2:$J$121<>"Collected")*AR_detail!$H$2:$H$121*AR_detail!$M$2:$M$121) -> 0 | J16: =SUMPRODUCT((AP_detail!$L$2:$L$101>=G16)*(AP_detail!$L$2:$L$101<=H16)*(AP_detail!$J$2:$J$101<>"Paid")*AP_detail!$H$2:$H$101) -> 0 | K16: =I16-J16 -> 0 | L16: =L15+K16 -> 2962193 | M16: =IF(L16<$B$5,"WARNING","OK") -> OK

Sheet Cash_Balance
A1: Bank Account | B1: Ending Bal. | D1: As of Date | E1: 46230
A2: A bank (TWD) #58945 | B2: 589353 | D2: Beginning Cash | E2: =B7 -> 1938408
A3: B bank (TWD) #65084 | B3: 29472 | D3: Min Cash Threshold | E3: 1500000
A4: C bank (TWD) #20122 | B4: 60485
A5: D bank (TWD) #29060 | B5: 1038475
A6: E bank (TWD) #30582 | B6: 220623
B7: =SUM(B2:B6) -> 1938408
A10: <<<From TB>>>

Sheet AR_detail
A1: Invoice_ID | B1: Customer_Code | C1: Customer_Name | D1: Department | E1: Invoice_Date | F1: Due_Date | G1: Payment_Terms | H1: Amount | I1: Collection_Probability | J1: Status | K1: Autual_Collection_Date | L1: Expected_Collection_Date | M1: Scenario_Adjusted_Probability
A2: AR-260001 | B2: C00007 | C2: Ironstone Enterprises | D2: A | E2: 46154 | F2: {=_xlfn.IFS(G2="EM15",EOMONTH(E2,0)+15, G2="EM30",EOMONTH(E2,0)+30, G2="EM45",EOMONTH(E2,0)+45, G2="EM60",EOMONTH(E2,0)+60, G2="OA15",E2+15, G2="OA30",E2+30, G2="OA60",E2+60 )} -> 46203 | G2: EM30 | H2: 124000 | I2: =INDEX(Customer_list!$G$2:$G$21,MATCH(B2,Customer_list!$B$2:$B$21,0)) -> 0.97 | J2: Collected | K2: 46203 | L2: =IF(J2="Collected",K2,IF(J2="Open",F2,F2+INDEX(Customer_list!$H$2:$H$21,MATCH(B2,Customer_list!$B$2:$B$21,0))*Weekly_Cash_Flow_Summary!$B$8)) -> 46203 | M2: =MIN(1,MAX(0,I2+Weekly_Cash_Flow_Summary!$B$7)) -> 0.97
A3: AR-260002 | B3: C00009 | C3: Westfall Commercial Group | D3: A | E3: 46132 | F3: {=_xlfn.IFS(G3="EM15",EOMONTH(E3,0)+15, G3="EM30",EOMONTH(E3,0)+30, G3="EM45",EOMONTH(E3,0)+45, G3="EM60",EOMONTH(E3,0)+60, G3="OA15",E3+15, G3="OA30",E3+30, G3="OA60",E3+60 )} -> 46172 | G3: EM30 | H3: 305500 | I3: =INDEX(Customer_list!$G$2:$G$21,MATCH(B3,Customer_list!$B$2:$B$21,0)) -> 0.9 | J3: Collected | K3: 46178 | L3: =IF(J3="Collected",K3,IF(J3="Open",F3,F3+INDEX(Customer_list!$H$2:$H$21,MATCH(B3,Customer_list!$B$2:$B$21,0))*Weekly_Cash_Flow_Summary!$B$8)) -> 46178 | M3: =MIN(1,MAX(0,I3+Weekly_Cash_Flow_Summary!$B$7)) -> 0.9
A4: AR-260003 | B4: C00018 | C4: Lakeshore Retail Co. | D4: A | E4: 46163 | F4: {=_xlfn.IFS(G4="EM15",EOMONTH(E4,0)+15, G4="EM30",EOMONTH(E4,0)+30, G4="EM45",EOMONTH(E4,0)+45, G4="EM60",EOMONTH(E4,0)+60, G4="OA15",E4+15, G4="OA30",E4+30, G4="OA60",E4+60 )} -> 46193 | G4: OA30 | H4: 329000 | I4: =INDEX(Customer_list!$G$2:$G$21,MATCH(B4,Customer_list!$B$2:$B$21,0)) -> 0.97 | J4: Collected | K4: 46193 | L4: =IF(J4="Collected",K4,IF(J4="Open",F4,F4+INDEX(Customer_list!$H$2:$H$21,MATCH(B4,Customer_list!$B$2:$B$21,0))*Weekly_Cash_Flow_Summary!$B$8)) -> 46193 | M4: =MIN(1,MAX(0,I4+Weekly_Cash_Flow_Summary!$B$7)) -> 0.97
A5: AR-260004 | B5: C00009 | C5: Westfall Commercial Group | D5: A | E5: 46196 | F5: {=_xlfn.IFS(G5="EM15",EOMONTH(E5,0)+15, G5="EM30",EOMONTH(E5,0)+30, G5="EM45",EOMONTH(E5,0)+45, G5="EM60",EOMONTH(E5,0)+60, G5="OA15",E5+15, G5="OA30",E5+30, G5="OA60",E5+60 )} -> 46233 | G5: EM30 | H5: 103500 | I5: =INDEX(Customer_list!$G$2:$G$21,MATCH(B5,Customer_list!$B$2:$B$21,0)) -> 0.9 | J5: Open | L5: =IF(J5="Collected",K5,IF(J5="Open",F5,F5+INDEX(Customer_list!$H$2:$H$21,MATCH(B5,Customer_list!$B$2:$B$21,0))*Weekly_Cash_Flow_Summary!$B$8)) -> 46233 | M5: =MIN(1,MAX(0,I5+Weekly_Cash_Flow_Summary!$B$7)) -> 0.9
A6: AR-260005 | B6: C00011 | C6: Riverton Wholesale Ltd. | D6: B | E6: 46119 | F6: {=_xlfn.IFS(G6="EM15",EOMONTH(E6,0)+15, G6="EM30",EOMONTH(E6,0)+30, G6="EM45",EOMONTH(E6,0)+45, G6="EM60",EOMONTH(E6,0)+60, G6="OA15",E6+15, G6="OA30",E6+30, G6="OA60",E6+60 )} -> 46134 | G6: OA15 | H6: 165500 | I6: =INDEX(Customer_list!$G$2:$G$21,MATCH(B6,Customer_list!$B$2:$B$21,0)) -> 0.75 | J6: Collected | K6: 46162 | L6: =IF(J6="Collected",K6,IF(J6="Open",F6,F6+INDEX(Customer_list!$H$2:$H$21,MATCH(B6,Customer_list!$B$2:$B$21,0))*Weekly_Cash_Flow_Summary!$B$8)) -> 46162 | M6: =MIN(1,MAX(0,I6+Weekly_Cash_Flow_Summary!$B$7)) -> 0.75
A7: AR-260006 | B7: C00005 | C7: Crestwood Merchandise Inc. | D7: C | E7: 46122 | F7: {=_xlfn.IFS(G7="EM15",EOMONTH(E7,0)+15, G7="EM30",EOMONTH(E7,0)+30, G7="EM45",EOMONTH(E7,0)+45, G7="EM60",EOMONTH(E7,0)+60, G7="OA15",E7+15, G7="OA30",E7+30, G7="OA60",E7+60 )} -> 46152 | G7: OA30 | H7: 73500 | I7: =INDEX(Customer_list!$G$2:$G$21,MATCH(B7,Customer_list!$B$2:$B$21,0)) -> 0.75 | J7: Overdue | L7: =IF(J7="Collected",K7,IF(J7="Open",F7,F7+INDEX(Customer_list!$H$2:$H$21,MATCH(B7,Customer_list!$B$2:$B$21,0))*Weekly_Cash_Flow_Summary!$B$8)) -> 46177 | M7: =MIN(1,MAX(0,I7+Weekly_Cash_Flow_Summary!$B$7)) -> 0.75
A8: AR-260007 | B8: C00013 | C8: Pinehill Distribution Inc. | D8: B | E8: 46218 | F8: {=_xlfn.IFS(G8="EM15",EOMONTH(E8,0)+15, G8="EM30",EOMONTH(E8,0)+30, G8="EM45",EOMONTH(E8,0)+45, G8="EM60",EOMONTH(E8,0)+60, G8="OA15",E8+15, G8="OA30",E8+30, G8="OA60",E8+60 )} -> 46248 | G8: OA30 | H8: 208000 | I8: =INDEX(Customer_list!$G$2:$G$21,MATCH(B8,Customer_list!$B$2:$B$21,0)) -> 0.75 | J8: Open | L8: =IF(J8="Collected",K8,IF(J8="Open",F8,F8+INDEX(Customer_list!$H$2:$H$21,MATCH(B8,Customer_list!$B$2:$B$21,0))*Weekly_Cash_Flow_Summary!$B$8)) -> 46248 | M8: =MIN(1,MAX(0,I8+Weekly_Cash_Flow_Summary!$B$7)) -> 0.75
A9: AR-260008 | B9: C00009 | C9: Westfall Commercial Group | D9: A | E9: 46181 | F9: {=_xlfn.IFS(G9="EM15",EOMONTH(E9,0)+15, G9="EM30",EOMONTH(E9,0)+30, G9="EM45",EOMONTH(E9,0)+45, G9="EM60",EOMONTH(E9,0)+60, G9="OA15",E9+15, G9="OA30",E9+30, G9="OA60",E9+60 )} -> 46233 | G9: EM30 | H9: 336500 | I9: =INDEX(Customer_list!$G$2:$G$21,MATCH(B9,Customer_list!$B$2:$B$21,0)) -> 0.9 | J9: Open | L9: =IF(J9="Collected",K9,IF(J9="Open",F9,F9+INDEX(Customer_list!$H$2:$H$21,MATCH(B9,Customer_list!$B$2:$B$21,0))*Weekly_Cash_Flow_Summary!$B$8)) -> 46233 | M9: =MIN(1,MAX(0,I9+Weekly_Cash_Flow_Summary!$B$7)) -> 0.9
A10: AR-260009 | B10: C00020 | C10: Willowmere Commercial Ltd. | D10: C | E10: 46125 | F10: {=_xlfn.IFS(G10="EM15",EOMONTH(E10,0)+15, G10="EM30",EOMONTH(E10,0)+30, G10="EM45",EOMONTH(E10,0)+45, G10="EM60",EOMONTH(E10,0)+60, G10="OA15",E10+15, G10="OA30",E10+30, G10="OA60",E10+60 )} -> 46202 | G10: EM60 | H10: 261000 | I10: =INDEX(Customer_list!$G$2:$G$21,MATCH(B10,Customer_list!$B$2:$B$21,0)) -> 0.97 | J10: Collected | K10: 46208 | L10: =IF(J10="Collected",K10,IF(J10="Open",F10,F10+INDEX(Customer_list!$H$2:$H$21,MATCH(B10,Customer_list!$B$2:$B$21,0))*Weekly_Cash_Flow_Summary!$B$8)) -> 46208 | M10: =MIN(1,MAX(0,I10+Weekly_Cash_Flow_Summary!$B$7)) -> 0.97
A11: AR-260010 | B11: C00013 | C11: Pinehill Distribution Inc. | D11: B | E11: 46159 | F11: {=_xlfn.IFS(G11="EM15",EOMONTH(E11,0)+15, G11="EM30",EOMONTH(E11,0)+30, G11="EM45",EOMONTH(E11,0)+45, G11="EM60",EOMONTH(E11,0)+60, G11="OA15",E11+15, G11="OA30",E11+30, G11="OA60",E11+60 )} -> 46189 | G11: OA30 | H11: 301000 | I11: =INDEX(Customer_list!$G$2:$G$21,MATCH(B11,Customer_list!$B$2:$B$21,0)) -> 0.75 | J11: Overdue | L11: =IF(J11="Collected",K11,IF(J11="Open",F11,F11+INDEX(Customer_list!$H$2:$H$21,MATCH(B11,Customer_list!$B$2:$B$21,0))*Weekly_Cash_Flow_Summary!$B$8)) -> 46214 | M11: =MIN(1,MAX(0,I11+Weekly_Cash_Flow_Summary!$B$7)) -> 0.75
A12: AR-260011 | B12: C00008 | C12: Sunridge Retail Partners | D12: B | E12: 46187 | F12: {=_xlfn.IFS(G12="EM15",EOMONTH(E12,0)+15, G12="EM30",EOMONTH(E12,0)+30, G12="EM45",EOMONTH(E12,0)+45, G12="EM60",EOMONTH(E12,0)+60, G12="OA15",E12+15, G12="OA30",E12+30, G12="OA60",E12+60 )} -> 46217 | G12: OA30 | H12: 61500 | I12: =INDEX(Customer_list!$G$2:$G$21,MATCH(B12,Customer_list!$B$2:$B$21,0)) -> 0.9 | J12: Overdue | L12: =IF(J12="Collected",K12,IF(J12="Open",F12,F12+INDEX(Customer_list!$H$2:$H$21,MATCH(B12,Customer_list!$B$2:$B$21,0))*Weekly_Cash_Flow_Summary!$B$8)) -> 46227 | M12: =MIN(1,MAX(0,I12+Weekly_Cash_Flow_Summary!$B$7)) -> 0.9
A13: AR-260012 | B13: C00011 | C13: Riverton Wholesale Ltd. | D13: B | E13: 46120 | F13: {=_xlfn.IFS(G13="EM15",EOMONTH(E13,0)+15, G13="EM30",EOMONTH(E13,0)+30, G13="EM45",EOMONTH(E13,0)+45, G13="EM60",EOMONTH(E13,0)+60, G13="OA15",E13+15, G13="OA30",E13+30, G13="OA60",E13+60 )} -> 46135 | G13: OA15 | H13: 322500 | I13: =INDEX(Customer_list!$G$2:$G$21,MATCH(B13,Customer_list!$B$2:$B$21,0)) -> 0.75 | J13: Collected | K13: 46162 | L13: =IF(J13="Collected",K13,IF(J13="Open",F13,F13+INDEX(Customer_list!$H$2:$H$21,MATCH(B13,Customer_list!$B$2:$B$21,0))*Weekly_Cash_Flow_Summary!$B$8)) -> 46162 | M13: =MIN(1,MAX(0,I13+Weekly_Cash_Flow_Summary!$B$7)) -> 0.75
A14: AR-260013 | B14: C00011 | C14: Riverton Wholesale Ltd. | D14: B | E14: 46229 | F14: {=_xlfn.IFS(G14="EM15",EOMONTH(E14,0)+15, G14="EM30",EOMONTH(E14,0)+30, G14="EM45",EOMONTH(E14,0)+45, G14="EM60",EOMONTH(E14,0)+60, G14="OA15",E14+15, G14="OA30",E14+30, G14="OA60",E14+60 )} -> 46244 | G14: OA15 | H14: 44000 | I14: =INDEX(Customer_list!$G$2:$G$21,MATCH(B14,Customer_list!$B$2:$B$21,0)) -> 0.75 | J14: Open | L14: =IF(J14="Collected",K14,IF(J14="Open",F14,F14+INDEX(Customer_list!$H$2:$H$21,MATCH(B14,Customer_list!$B$2:$B$21,0))*Weekly_Cash_Flow_Summary!$B$8)) -> 46244 | M14: =MIN(1,MAX(0,I14+Weekly_Cash_Flow_Summary!$B$7)) -> 0.75
A15: AR-260014 | B15: C00002 | C15: Northgate Commerce Co. | D15: B | E15: 46177 | F15: {=_xlfn.IFS(G15="EM15",EOMONTH(E15,0)+15, G15="EM30",EOMONTH(E15,0)+30, G15="EM45",EOMONTH(E15,0)+45, G15="EM60",EOMONTH(E15,0)+60, G15="OA15",E15+15, G15="OA30",E15+30, G15="OA60",E15+60 )} -> 46237 | G15: OA60 | H15: 62000 | I15: =INDEX(Customer_list!$G$2:$G$21,MATCH(B15,Customer_list!$B$2:$B$21,0)) -> 0.9 | J15: Open | L15: =IF(J15="Collected",K15,IF(J15="Open",F15,F15+INDEX(Customer_list!$H$2:$H$21,MATCH(B15,Customer_list!$B$2:$B$21,0))*Weekly_Cash_Flow_Summary!$B$8)) -> 46237 | M15: =MIN(1,MAX(0,I15+Weekly_Cash_Flow_Summary!$B$7)) -> 0.9
A16: AR-260015 | B16: C00016 | C16: Fairview Merchants Ltd. | D16: B | E16: 46140 | F16: {=_xlfn.IFS(G16="EM15",EOMONTH(E16,0)+15, G16="EM30",EOMONTH(E16,0)+30, G16="EM45",EOMONTH(E16,0)+45, G16="EM60",EOMONTH(E16,0)+60, G16="OA15",E16+15, G16="OA30",E16+30, G16="OA60",E16+60 )} -> 46157 | G16: EM15 | H16: 219500 | I16: =INDEX(Customer_list!$G$2:$G$21,MATCH(B16,Customer_list!$B$2:$B$21,0)) -> 0.9 | J16: Collected | K16: 46167 | L16: =IF(J16="Collected",K16,IF(J16="Open",F16,F16+INDEX(Customer_list!$H$2:$H$21,MATCH(B16,Customer_list!$B$2:$B$21,0))*Weekly_Cash_Flow_Summary!$B$8)) -> 46167 | M16: =MIN(1,MAX(0,I16+Weekly_Cash_Flow_Summary!$B$7)) -> 0.9
A17: AR-260016 | B17: C00020 | C17: Willowmere Commercial Ltd. | D17: C | E17: 46117 | F17: {=_xlfn.IFS(G17="EM15",EOMONTH(E17,0)+15, G17="EM30",EOMONTH(E17,0)+30, G17="EM45",EOMONTH(E17,0)+45, G17="EM60",EOMONTH(E17,0)+60, G17="OA15",E17+15, G17="OA30",E17+30, G17="OA60",E17+60 )} -> 46202 | G17: EM60 | H17: 105500 | I17: =INDEX(Customer_list!$G$2:$G$21,MATCH(B17,Customer_list!$B$2:$B$21,0)) -> 0.97 | J17: Collected | K17: 46208 | L17: =IF(J17="Collected",K17,IF(J17="Open",F17,F17+INDEX(Customer_list!$H$2:$H$21,MATCH(B17,Customer_list!$B$2:$B$21,0))*Weekly_Cash_Flow_Summary!$B$8)) -> 46208 | M17: =MIN(1,MAX(0,I17+Weekly_Cash_Flow_Summary!$B$7)) -> 0.97
A18: AR-260017 | B18: C00003 | C18: BluePeak Distributors | D18: A | E18: 46124 | F18: {=_xlfn.IFS(G18="EM15",EOMONTH(E18,0)+15, G18="EM30",EOMONTH(E18,0)+30, G18="EM45",EOMONTH(E18,0)+45, G18="EM60",EOMONTH(E18,0)+60, G18="OA15",E18+15, G18="OA30",E18+30, G18="OA60",E18+60 )} -> 46202 | G18: EM60 | H18: 160000 | I18: =INDEX(Customer_list!$G$2:$G$21,MATCH(B18,Customer_list!$B$2:$B$21,0)) -> 0.97 | J18: Collected | K18: 46203 | L18: =IF(J18="Collected",K18,IF(J18="Open",F18,F18+INDEX(Customer_list!$H$2:$H$21,MATCH(B18,Customer_list!$B$2:$B$21,0))*Weekly_Cash_Flow_Summary!$B$8)) -> 46203 | M18: =MIN(1,MAX(0,I18+Weekly_Cash_Flow_Summary!$B$7)) -> 0.97
A19: AR-260018 | B19: C00002 | C19: Northgate Commerce Co. | D19: B | E19: 46168 | F19: {=_xlfn.IFS(G19="EM15",EOMONTH(E19,0)+15, G19="EM30",EOMONTH(E19,0)+30, G19="EM45",EOMONTH(E19,0)+45, G19="EM60",EOMONTH(E19,0)+60, G19="OA15",E19+15, G19="OA30",E19+30, G19="OA60",E19+60 )} -> 46228 | G19: OA60 | H19: 339500 | I19: =INDEX(Customer_list!$G$2:$G$21,MATCH(B19,Customer_list!$B$2:$B$21,0)) -> 0.9 | J19: Overdue | L19: =IF(J19="Collected",K19,IF(J19="Open",F19,F19+INDEX(Customer_list!$H$2:$H$21,MATCH(B19,Customer_list!$B$2:$B$21,0))*Weekly_Cash_Flow_Summary!$B$8)) -> 46238 | M19: =MIN(1,MAX(0,I19+Weekly_Cash_Flow_Summary!$B$7)) -> 0.9
A20: AR-260019 | B20: C00010 | C20: Oakhaven Trading Co. | D20: A | E20: 46166 | F20: {=_xlfn.IFS(G20="EM15",EOMONTH(E20,0)+15, G20="EM30",EOMONTH(E20,0)+30, G20="EM45",EOMONTH(E20,0)+45, G20="EM60",EOMONTH(E20,0)+60, G20="OA15",E20+15, G20="OA30",E20+30, G20="OA60",E20+60 )} -> 46196 | G20: OA30 | H20: 109500 | I20: =INDEX(Customer_list!$G$2:$G$21,MATCH(B20,Customer_list!$B$2:$B$21,0)) -> 0.97 | J20: Collected | K20: 46203 | L20: =IF(J20="Collected",K20,IF(J20="Open",F20,F20+INDEX(Customer_list!$H$2:$H$21,MATCH(B20,Customer_list!$B$2:$B$21,0))*Weekly_Cash_Flow_Summary!$B$8)) -> 46203 | M20: =MIN(1,MAX(0,I20+Weekly_Cash_Flow_Summary!$B$7)) -> 0.97
A21: AR-260020 | B21: C00012 | C21: Goldenbridge Retailers | D21: B | E21: 46121 | F21: {=_xlfn.IFS(G21="EM15",EOMONTH(E21,0)+15, G21="EM30",EOMONTH(E21,0)+30, G21="EM45",EOMONTH(E21,0)+45, G21="EM60",EOMONTH(E21,0)+60, G21="OA15",E21+15, G21="OA30",E21+30, G21="OA60",E21+60 )} -> 46151 | G21: OA30 | H21: 105500 | I21: =INDEX(Customer_list!$G$2:$G$21,MATCH(B21,Customer_list!$B$2:$B$21,0)) -> 0.9 | J21: Collected | K21: 46167 | L21: =IF(J21="Collected",K21,IF(J21="Open",F21,F21+INDEX(Customer_list!$H$2:$H$21,MATCH(B21,Customer_list!$B$2:$B$21,0))*Weekly_Cash_Flow_Summary!$B$8)) -> 46167 | M21: =MIN(1,MAX(0,I21+Weekly_Cash_Flow_Summary!$B$7)) -> 0.9
A22: AR-260021 | B22: C00018 | C22: Lakeshore Retail Co. | D22: A | E22: 46143 | F22: {=_xlfn.IFS(G22="EM15",EOMONTH(E22,0)+15, G22="EM30",EOMONTH(E22,0)+30, G22="EM45",EOMONTH(E22,0)+45, G22="EM60",EOMONTH(E22,0)+60, G22="OA15",E22+15, G22="OA30",E22+30, G22="OA60",E22+60 )} -> 46173 | G22: OA30 | H22: 262500 | I22: =INDEX(Customer_list!$G$2:$G$21,MATCH(B22,Customer_list!$B$2:$B$21,0)) -> 0.97 | J22: Collected | K22: 46178 | L22: =IF(J22="Collected",K22,IF(J22="Open",F22,F22+INDEX(Customer_list!$H$2:$H$21,MATCH(B22,Customer_list!$B$2:$B$21,0))*Weekly_Cash_Flow_Summary!$B$8)) -> 46178 | M22: =MIN(1,MAX(0,I22+Weekly_Cash_Flow_Summary!$B$7)) -> 0.97
A23: AR-260022 | B23: C00017 | C23: Cedarpoint Trading Inc. | D23: C | E23: 46124 | F23: {=_xlfn.IFS(G23="EM15",EOMONTH(E23,0)+15, G23="EM30",EOMONTH(E23,0)+30, G23="EM45",EOMONTH(E23,0)+45, G23="EM60",EOMONTH(E23,0)+60, G23="OA15",E23+15, G23="OA30",E23+30, G23="OA60",E23+60 )} -> 46187 | G23: EM45 | H23: 135000 | I23: =INDEX(Customer_list!$G$2:$G$21,MATCH(B23,Customer_list!$B$2:$B$21,0)) -> 0.75 | J23: Overdue | L23: =IF(J23="Collected",K23,IF(J23="Open",F23,F23+INDEX(Customer_list!$H$2:$H$21,MATCH(B23,Customer_list!$B$2:$B$21,0))*Weekly_Cash_Flow_Summary!$B$8)) -> 46212 | M23: =MIN(1,MAX(0,I23+Weekly_Cash_Flow_Summary!$B$7)) -> 0.75
A24: AR-260023 | B24: C00004 | C24: Harborview Trading Ltd. | D24: B | E24: 46183 | F24: {=_xlfn.IFS(G24="EM15",EOMONTH(E24,0)+15, G24="EM30",EOMONTH(E24,0)+30, G24="EM45",EOMONTH(E24,0)+45, G24="EM60",EOMONTH(E24,0)+60, G24="OA15",E24+15, G24="OA30",E24+30, G24="OA60",E24+60 )} -> 46263 | G24: EM60 | H24: 190000 | I24: =INDEX(Customer_list!$G$2:$G$21,MATCH(B24,Customer_list!$B$2:$B$21,0)) -> 0.9 | J24: Open | L24: =IF(J24="Collected",K24,IF(J24="Open",F24,F24+INDEX(Customer_list!$H$2:$H$21,MATCH(B24,Customer_list!$B$2:$B$21,0))*Weekly_Cash_Flow_Summary!$B$8)) -> 46263 | M24: =MIN(1,MAX(0,I24+Weekly_Cash_Flow_Summary!$B$7)) -> 0.9
A25: AR-260024 | B25: C00017 | C25: Cedarpoint Trading Inc. | D25: C | E25: 46167 | F25: {=_xlfn.IFS(G25="EM15",EOMONTH(E25,0)+15, G25="EM30",EOMONTH(E25,0)+30, G25="EM45",EOMONTH(E25,0)+45, G25="EM60",EOMONTH(E25,0)+60, G25="OA15",E25+15, G25="OA30",E25+30, G25="OA60",E25+60 )} -> 46218 | G25: EM45 | H25: 140000 | I25: =INDEX(Customer_list!$G$2:$G$21,MATCH(B25,Customer_list!$B$2:$B$21,0)) -> 0.75 | J25: Overdue | L25: =IF(J25="Collected",K25,IF(J25="Open",F25,F25+INDEX(Customer_list!$H$2:$H$21,MATCH(B25,Customer_list!$B$2:$B$21,0))*Weekly_Cash_Flow_Summary!$B$8)) -> 46243 | M25: =MIN(1,MAX(0,I25+Weekly_Cash_Flow_Summary!$B$7)) -> 0.75
A26: AR-260025 | B26: C00014 | C26: Clearwater Commerce Co. | D26: A | E26: 46120 | F26: {=_xlfn.IFS(G26="EM15",EOMONTH(E26,0)+15, G26="EM30",EOMONTH(E26,0)+30, G26="EM45",EOMONTH(E26,0)+45, G26="EM60",EOMONTH(E26,0)+60, G26="OA15",E26+15, G26="OA30",E26+30, G26="OA60",E26+60 )} -> 46187 | G26: EM45 | H26: 185500 | I26: =INDEX(Customer_list!$G$2:$G$21,MATCH(B26,Customer_list!$B$2:$B$21,0)) -> 0.97 | J26: Collected | K26: 46188 | L26: =IF(J26="Collected",K26,IF(J26="Open",F26,F26+INDEX(Customer_list!$H$2:$H$21,MATCH(B26,Customer_list!$B$2:$B$21,0))*Weekly_Cash_Flow_Summary!$B$8)) -> 46188 | M26: =MIN(1,MAX(0,I26+Weekly_Cash_Flow_Summary!$B$7)) -> 0.97
A27: AR-260026 | B27: C00006 | C27: Meadowbrook Supply Co. | D27: B | E27: 46218 | F27: {=_xlfn.IFS(G27="EM15",EOMONTH(E27,0)+15, G27="EM30",EOMONTH(E27,0)+30, G27="EM45",EOMONTH(E27,0)+45, G27="EM60",EOMONTH(E27,0)+60, G27="OA15",E27+15, G27="OA30",E27+30, G27="OA60",E27+60 )} -> 46294 | G27: EM60 | H27: 130500 | I27: =INDEX(Customer_list!$G$2:$G$21,MATCH(B27,Customer_list!$B$2:$B$21,0)) -> 0.9 | J27: Open | L27: =IF(J27="Collected",K27,IF(J27="Open",F27,F27+INDEX(Customer_list!$H$2:$H$21,MATCH(B27,Customer_list!$B$2:$B$21,0))*Weekly_Cash_Flow_Summary!$B$8)) -> 46294 | M27: =MIN(1,MAX(0,I27+Weekly_Cash_Flow_Summary!$B$7)) -> 0.9
A28: AR-260027 | B28: C00008 | C28: Sunridge Retail Partners | D28: B | E28: 46185 | F28: {=_xlfn.IFS(G28="EM15",EOMONTH(E28,0)+15, G28="EM30",EOMONTH(E28,0)+30, G28="EM45",EOMONTH(E28,0)+45, G28="EM60",EOMONTH(E28,0)+60, G28="OA15",E28+15, G28="OA30",E28+30, G28="OA60",E28+60 )} -> 46215 | G28: OA30 | H28: 317500 | I28: =INDEX(Customer_list!$G$2:$G$21,MATCH(B28,Customer_list!$B$2:$B$21,0)) -> 0.9 | J28: Overdue | L28: =IF(J28="Collected",K28,IF(J28="Open",F28,F28+INDEX(Customer_list!$H$2:$H$21,MATCH(B28,Customer_list!$B$2:$B$21,0))*Weekly_Cash_Flow_Summary!$B$8)) -> 46225 | M28: =MIN(1,MAX(0,I28+Weekly_Cash_Flow_Summary!$B$7)) -> 0.9
A29: AR-260028 | B29: C00018 | C29: Lakeshore Retail Co. | D29: A | E29: 46128 | F29: {=_xlfn.IFS(G29="EM15",EOMONTH(E29,0)+15, G29="EM30",EOMONTH(E29,0)+30, G29="EM45",EOMONTH(E29,0)+45, G29="EM60",EOMONTH(E29,0)+60, G29="OA15",E29+15, G29="OA30",E29+30, G29="OA60",E29+60 )} -> 46158 | G29: OA30 | H29: 131500 | I29: =INDEX(Customer_list!$G$2:$G$21,MATCH(B29,Customer_list!$B$2:$B$21,0)) -> 0.97 | J29: Collected | K29: 46162 | L29: =IF(J29="Collected",K29,IF(J29="Open",F29,F29+INDEX(Customer_list!$H$2:$H$21,MATCH(B29,Customer_list!$B$2:$B$21,0))*Weekly_Cash_Flow_Summary!$B$8)) -> 46162 | M29: =MIN(1,MAX(0,I29+Weekly_Cash_Flow_Summary!$B$7)) -> 0.97
A30: AR-260029 | B30: C00006 | C30: Meadowbrook Supply Co. | D30: B | E30: 46141 | F30: {=_xlfn.IFS(G30="EM15",EOMONTH(E30,0)+15, G30="EM30",EOMONTH(E30,0)+30, G30="EM45",EOMONTH(E30,0)+45, G30="EM60",EOMONTH(E30,0)+60, G30="OA15",E30+15, G30="OA30",E30+30, G30="OA60",E30+60 )} -> 46202 | G30: EM60 | H30: 281500 | I30: =INDEX(Customer_list!$G$2:$G$21,MATCH(B30,Customer_list!$B$2:$B$21,0)) -> 0.9 | J30: Collected | K30: 46208 | L30: =IF(J30="Collected",K30,IF(J30="Open",F30,F30+INDEX(Customer_list!$H$2:$H$21,MATCH(B30,Customer_list!$B$2:$B$21,0))*Weekly_Cash_Flow_Summary!$B$8)) -> 46208 | M30: =MIN(1,MAX(0,I30+Weekly_Cash_Flow_Summary!$B$7)) -> 0.9
A31: AR-260030 | B31: C00001 | C31: Silverline Retail Group | D31: C | E31: 46193 | F31: {=_xlfn.IFS(G31="EM15",EOMONTH(E31,0)+15, G31="EM30",EOMONTH(E31,0)+30, G31="EM45",EOMONTH(E31,0)+45, G31="EM60",EOMONTH(E31,0)+60, G31="OA15",E31+15, G31="OA30",E31+30, G31="OA60",E31+60 )} -> 46218 | G31: EM15 | H31: 95000 | I31: =INDEX(Customer_list!$G$2:$G$21,MATCH(B31,Customer_list!$B$2:$B$21,0)) -> 0.97 | J31: Collected | K31: 46218 | L31: =IF(J31="Collected",K31,IF(J31="Open",F31,F31+INDEX(Customer_list!$H$2:$H$21,MATCH(B31,Customer_list!$B$2:$B$21,0))*Weekly_Cash_Flow_Summary!$B$8)) -> 46218 | M31: =MIN(1,MAX(0,I31+Weekly_Cash_Flow_Summary!$B$7)) -> 0.97
A32: AR-260031 | B32: C00007 | C32: Ironstone Enterprises | D32: A | E32: 46193 | F32: {=_xlfn.IFS(G32="EM15",EOMONTH(E32,0)+15, G32="EM30",EOMONTH(E32,0)+30, G32="EM45",EOMONTH(E32,0)+45, G32="EM60",EOMONTH(E32,0)+60, G32="OA15",E32+15, G32="OA30",E32+30, G32="OA60",E32+60 )} -> 46233 | G32: EM30 | H32: 314500 | I32: =INDEX(Customer_list!$G$2:$G$21,MATCH(B32,Customer_list!$B$2:$B$21,0)) -> 0.97 | J32: Open | L32: =IF(J32="Collected",K32,IF(J32="Open",F32,F32+INDEX(Customer_list!$H$2:$H$21,MATCH(B32,Customer_list!$B$2:$B$21,0))*Weekly_Cash_Flow_Summary!$B$8)) -> 46233 | M32: =MIN(1,MAX(0,I32+Weekly_Cash_Flow_Summary!$B$7)) -> 0.97
A33: AR-260032 | B33: C00016 | C33: Fairview Merchants Ltd. | D33: B | E33: 46187 | F33: {=_xlfn.IFS(G33="EM15",EOMONTH(E33,0)+15, G33="EM30",EOMONTH(E33,0)+30, G33="EM45",EOMONTH(E33,0)+45, G33="EM60",EOMONTH(E33,0)+60, G33="OA15",E33+15, G33="OA30",E33+30, G33="OA60",E33+60 )} -> 46218 | G33: EM15 | H33: 302500 | I33: =INDEX(Customer_list!$G$2:$G$21,MATCH(B33,Customer_list!$B$2:$B$21,0)) -> 0.9 | J33: Collected | K33: 46228 | L33: =IF(J33="Collected",K33,IF(J33="Open",F33,F33+INDEX(Customer_list!$H$2:$H$21,MATCH(B33,Customer_list!$B$2:$B$21,0))*Weekly_Cash_Flow_Summary!$B$8)) -> 46228 | M33: =MIN(1,MAX(0,I33+Weekly_Cash_Flow_Summary!$B$7)) -> 0.9
A34: AR-260033 | B34: C00010 | C34: Oakhaven Trading Co. | D34: A | E34: 46120 | F34: {=_xlfn.IFS(G34="EM15",EOMONTH(E34,0)+15, G34="EM30",EOMONTH(E34,0)+30, G34="EM45",EOMONTH(E34,0)+45, G34="EM60",EOMONTH(E34,0)+60, G34="OA15",E34+15, G34="OA30",E34+30, G34="OA60",E34+60 )} -> 46150 | G34: OA30 | H34: 326000 | I34: =INDEX(Customer_list!$G$2:$G$21,MATCH(B34,Customer_list!$B$2:$B$21,0)) -> 0.97 | J34: Collected | K34: 46157 | L34: =IF(J34="Collected",K34,IF(J34="Open",F34,F34+INDEX(Customer_list!$H$2:$H$21,MATCH(B34,Customer_list!$B$2:$B$21,0))*Weekly_Cash_Flow_Summary!$B$8)) -> 46157 | M34: =MIN(1,MAX(0,I34+Weekly_Cash_Flow_Summary!$B$7)) -> 0.97
A35: AR-260034 | B35: C00006 | C35: Meadowbrook Supply Co. | D35: B | E35: 46186 | F35: {=_xlfn.IFS(G35="EM15",EOMONTH(E35,0)+15, G35="EM30",EOMONTH(E35,0)+30, G35="EM45",EOMONTH(E35,0)+45, G35="EM60",EOMONTH(E35,0)+60, G35="OA15",E35+15, G35="OA30",E35+30, G35="OA60",E35+60 )} -> 46263 | G35: EM60 | H35: 92500 | I35: =INDEX(Customer_list!$G$2:$G$21,MATCH(B35,Customer_list!$B$2:$B$21,0)) -> 0.9 | J35: Open | L35: =IF(J35="Collected",K35,IF(J35="Open",F35,F35+INDEX(Customer_list!$H$2:$H$21,MATCH(B35,Customer_list!$B$2:$B$21,0))*Weekly_Cash_Flow_Summary!$B$8)) -> 46263 | M35: =MIN(1,MAX(0,I35+Weekly_Cash_Flow_Summary!$B$7)) -> 0.9
A36: AR-260035 | B36: C00009 | C36: Westfall Commercial Group | D36: A | E36: 46187 | F36: {=_xlfn.IFS(G36="EM15",EOMONTH(E36,0)+15, G36="EM30",EOMONTH(E36,0)+30, G36="EM45",EOMONTH(E36,0)+45, G36="EM60",EOMONTH(E36,0)+60, G36="OA15",E36+15, G36="OA30",E36+30, G36="OA60",E36+60 )} -> 46233 | G36: EM30 | H36: 44500 | I36: =INDEX(Customer_list!$G$2:$G$21,MATCH(B36,Customer_list!$B$2:$B$21,0)) -> 0.9 | J36: Open | L36: =IF(J36="Collected",K36,IF(J36="Open",F36,F36+INDEX(Customer_list!$H$2:$H$21,MATCH(B36,Customer_list!$B$2:$B$21,0))*Weekly_Cash_Flow_Summary!$B$8)) -> 46233 | M36: =MIN(1,MAX(0,I36+Weekly_Cash_Flow_Summary!$B$7)) -> 0.9
A37: AR-260036 | B37: C00005 | C37: Crestwood Merchandise Inc. | D37: C | E37: 46163 | F37: {=_xlfn.IFS(G37="EM15",EOMONTH(E37,0)+15, G37="EM30",EOMONTH(E37,0)+30, G37="EM45",EOMONTH(E37,0)+45, G37="EM60",EOMONTH(E37,0)+60, G37="OA15",E37+15, G37="OA30",E37+30, G37="OA60",E37+60 )} -> 46193 | G37: OA30 | H37: 349000 | I37: =INDEX(Customer_list!$G$2:$G$21,MATCH(B37,Customer_list!$B$2:$B$21,0)) -> 0.75 | J37: Collected | K37: 46213 | L37: =IF(J37="Collected",K37,IF(J37="Open",F37,F37+INDEX(Customer_list!$H$2:$H$21,MATCH(B37,Customer_list!$B$2:$B$21,0))*Weekly_Cash_Flow_Summary!$B$8)) -> 46213 | M37: =MIN(1,MAX(0,I37+Weekly_Cash_Flow_Summary!$B$7)) -> 0.75
A38: AR-260037 | B38: C00016 | C38: Fairview Merchants Ltd. | D38: B | E38: 46119 | F38: {=_xlfn.IFS(G38="EM15",EOMONTH(E38,0)+15, G38="EM30",EOMONTH(E38,0)+30, G38="EM45",EOMONTH(E38,0)+45, G38="EM60",EOMONTH(E38,0)+60, G38="OA15",E38+15, G38="OA30",E38+30, G38="OA60",E38+60 )} -> 46157 | G38: EM15 | H38: 332500 | I38: =INDEX(Customer_list!$G$2:$G$21,MATCH(B38,Customer_list!$B$2:$B$21,0)) -> 0.9 | J38: Collected | K38: 46167 | L38: =IF(J38="Collected",K38,IF(J38="Open",F38,F38+INDEX(Customer_list!$H$2:$H$21,MATCH(B38,Customer_list!$B$2:$B$21,0))*Weekly_Cash_Flow_Summary!$B$8)) -> 46167 | M38: =MIN(1,MAX(0,I38+Weekly_Cash_Flow_Summary!$B$7)) -> 0.9
A39: AR-260038 | B39: C00018 | C39: Lakeshore Retail Co. | D39: A | E39: 46141 | F39: {=_xlfn.IFS(G39="EM15",EOMONTH(E39,0)+15, G39="EM30",EOMONTH(E39,0)+30, G39="EM45",EOMONTH(E39,0)+45, G39="EM60",EOMONTH(E39,0)+60, G39="OA15",E39+15, G39="OA30",E39+30, G39="OA60",E39+60 )} -> 46171 | G39: OA30 | H39: 332500 | I39: =INDEX(Customer_list!$G$2:$G$21,MATCH(B39,Customer_list!$B$2:$B$21,0)) -> 0.97 | J39: Collected | K39: 46178 | L39: =IF(J39="Collected",K39,IF(J39="Open",F39,F39+INDEX(Customer_list!$H$2:$H$21,MATCH(B39,Customer_list!$B$2:$B$21,0))*Weekly_Cash_Flow_Summary!$B$8)) -> 46178 | M39: =MIN(1,MAX(0,I39+Weekly_Cash_Flow_Summary!$B$7)) -> 0.97
A40: AR-260039 | B40: C00014 | C40: Clearwater Commerce Co. | D40: A | E40: 46118 | F40: {=_xlfn.IFS(G40="EM15",EOMONTH(E40,0)+15, G40="EM30",EOMONTH(E40,0)+30, G40="EM45",EOMONTH(E40,0)+45, G40="EM60",EOMONTH(E40,0)+60, G40="OA15",E40+15, G40="OA30",E40+30, G40="OA60",E40+60 )} -> 46187 | G40: EM45 | H40: 297500 | I40: =INDEX(Customer_list!$G$2:$G$21,MATCH(B40,Customer_list!$B$2:$B$21,0)) -> 0.97 | J40: Collected | K40: 46188 | L40: =IF(J40="Collected",K40,IF(J40="Open",F40,F40+INDEX(Customer_list!$H$2:$H$21,MATCH(B40,Customer_list!$B$2:$B$21,0))*Weekly_Cash_Flow_Summary!$B$8)) -> 46188 | M40: =MIN(1,MAX(0,I40+Weekly_Cash_Flow_Summary!$B$7)) -> 0.97
A41: AR-260040 | B41: C00016 | C41: Fairview Merchants Ltd. | D41: B | E41: 46184 | F41: {=_xlfn.IFS(G41="EM15",EOMONTH(E41,0)+15, G41="EM30",EOMONTH(E41,0)+30, G41="EM45",EOMONTH(E41,0)+45, G41="EM60",EOMONTH(E41,0)+60, G41="OA15",E41+15, G41="OA30",E41+30, G41="OA60",E41+60 )} -> 46218 | G41: EM15 | H41: 26000 | I41: =INDEX(Customer_list!$G$2:$G$21,MATCH(B41,Customer_list!$B$2:$B$21,0)) -> 0.9 | J41: Overdue | L41: =IF(J41="Collected",K41,IF(J41="Open",F41,F41+INDEX(Customer_list!$H$2:$H$21,MATCH(B41,Customer_list!$B$2:$B$21,0))*Weekly_Cash_Flow_Summary!$B$8)) -> 46228 | M41: =MIN(1,MAX(0,I41+Weekly_Cash_Flow_Summary!$B$7)) -> 0.9
A42: AR-260041 | B42: C00002 | C42: Northgate Commerce Co. | D42: B | E42: 46222 | F42: {=_xlfn.IFS(G42="EM15",EOMONTH(E42,0)+15, G42="EM30",EOMONTH(E42,0)+30, G42="EM45",EOMONTH(E42,0)+45, G42="EM60",EOMONTH(E42,0)+60, G42="OA15",E42+15, G42="OA30",E42+30, G42="OA60",E42+60 )} -> 46282 | G42: OA60 | H42: 301500 | I42: =INDEX(Customer_list!$G$2:$G$21,MATCH(B42,Customer_list!$B$2:$B$21,0)) -> 0.9 | J42: Open | L42: =IF(J42="Collected",K42,IF(J42="Open",F42,F42+INDEX(Customer_list!$H$2:$H$21,MATCH(B42,Customer_list!$B$2:$B$21,0))*Weekly_Cash_Flow_Summary!$B$8)) -> 46282 | M42: =MIN(1,MAX(0,I42+Weekly_Cash_Flow_Summary!$B$7)) -> 0.9
A43: AR-260042 | B43: C00013 | C43: Pinehill Distribution Inc. | D43: B | E43: 46130 | F43: {=_xlfn.IFS(G43="EM15",EOMONTH(E43,0)+15, G43="EM30",EOMONTH(E43,0)+30, G43="EM45",EOMONTH(E43,0)+45, G43="EM60",EOMONTH(E43,0)+60, G43="OA15",E43+15, G43="OA30",E43+30, G43="OA60",E43+60 )} -> 46160 | G43: OA30 | H43: 78500 | I43: =INDEX(Customer_list!$G$2:$G$21,MATCH(B43,Customer_list!$B$2:$B$21,0)) -> 0.75 | J43: Collected | K43: 46183 | L43: =IF(J43="Collected",K43,IF(J43="Open",F43,F43+INDEX(Customer_list!$H$2:$H$21,MATCH(B43,Customer_list!$B$2:$B$21,0))*Weekly_Cash_Flow_Summary!$B$8)) -> 46183 | M43: =MIN(1,MAX(0,I43+Weekly_Cash_Flow_Summary!$B$7)) -> 0.75
A44: AR-260043 | B44: C00010 | C44: Oakhaven Trading Co. | D44: A | E44: 46150 | F44: {=_xlfn.IFS(G44="EM15",EOMONTH(E44,0)+15, G44="EM30",EOMONTH(E44,0)+30, G44="EM45",EOMONTH(E44,0)+45, G44="EM60",EOMONTH(E44,0)+60, G44="OA15",E44+15, G44="OA30",E44+30, G44="OA60",E44+60 )} -> 46180 | G44: OA30 | H44: 258000 | I44: =INDEX(Customer_list!$G$2:$G$21,MATCH(B44,Customer_list!$B$2:$B$21,0)) -> 0.97 | J44: Collected | K44: 46188 | L44: =IF(J44="Collected",K44,IF(J44="Open",F44,F44+INDEX(Customer_list!$H$2:$H$21,MATCH(B44,Customer_list!$B$2:$B$21,0))*Weekly_Cash_Flow_Summary!$B$8)) -> 46188 | M44: =MIN(1,MAX(0,I44+Weekly_Cash_Flow_Summary!$B$7)) -> 0.97
A45: AR-260044 | B45: C00014 | C45: Clearwater Commerce Co. | D45: A | E45: 46166 | F45: {=_xlfn.IFS(G45="EM15",EOMONTH(E45,0)+15, G45="EM30",EOMONTH(E45,0)+30, G45="EM45",EOMONTH(E45,0)+45, G45="EM60",EOMONTH(E45,0)+60, G45="OA15",E45+15, G45="OA30",E45+30, G45="OA60",E45+60 )} -> 46218 | G45: EM45 | H45: 282500 | I45: =INDEX(Customer_list!$G$2:$G$21,MATCH(B45,Customer_list!$B$2:$B$21,0)) -> 0.97 | J45: Collected | K45: 46218 | L45: =IF(J45="Collected",K45,IF(J45="Open",F45,F45+INDEX(Customer_list!$H$2:$H$21,MATCH(B45,Customer_list!$B$2:$B$21,0))*Weekly_Cash_Flow_Summary!$B$8)) -> 46218 | M45: =MIN(1,MAX(0,I45+Weekly_Cash_Flow_Summary!$B$7)) -> 0.97
A46: AR-260045 | B46: C00020 | C46: Willowmere Commercial Ltd. | D46: C | E46: 46131 | F46: {=_xlfn.IFS(G46="EM15",EOMONTH(E46,0)+15, G46="EM30",EOMONTH(E46,0)+30, G46="EM45",EOMONTH(E46,0)+45, G46="EM60",EOMONTH(E46,0)+60, G46="OA15",E46+15, G46="OA30",E46+30, G46="OA60",E46+60 )} -> 46202 | G46: EM60 | H46: 76000 | I46: =INDEX(Customer_list!$G$2:$G$21,MATCH(B46,Customer_list!$B$2:$B$21,0)) -> 0.97 | J46: Collected | K46: 46208 | L46: =IF(J46="Collected",K46,IF(J46="Open",F46,F46+INDEX(Customer_list!$H$2:$H$21,MATCH(B46,Customer_list!$B$2:$B$21,0))*Weekly_Cash_Flow_Summary!$B$8)) -> 46208 | M46: =MIN(1,MAX(0,I46+Weekly_Cash_Flow_Summary!$B$7)) -> 0.97
A47: AR-260046 | B47: C00020 | C47: Willowmere Commercial Ltd. | D47: C | E47: 46182 | F47: {=_xlfn.IFS(G47="EM15",EOMONTH(E47,0)+15, G47="EM30",EOMONTH(E47,0)+30, G47="EM45",EOMONTH(E47,0)+45, G47="EM60",EOMONTH(E47,0)+60, G47="OA15",E47+15, G47="OA30",E47+30, G47="OA60",E47+60 )} -> 46263 | G47: EM60 | H47: 348000 | I47: =INDEX(Customer_list!$G$2:$G$21,MATCH(B47,Customer_list!$B$2:$B$21,0)) -> 0.97 | J47: Open | L47: =IF(J47="Collected",K47,IF(J47="Open",F47,F47+INDEX(Customer_list!$H$2:$H$21,MATCH(B47,Customer_list!$B$2:$B$21,0))*Weekly_Cash_Flow_Summary!$B$8)) -> 46263 | M47: =MIN(1,MAX(0,I47+Weekly_Cash_Flow_Summary!$B$7)) -> 0.97
A48: AR-260047 | B48: C00001 | C48: Silverline Retail Group | D48: C | E48: 46128 | F48: {=_xlfn.IFS(G48="EM15",EOMONTH(E48,0)+15, G48="EM30",EOMONTH(E48,0)+30, G48="EM45",EOMONTH(E48,0)+45, G48="EM60",EOMONTH(E48,0)+60, G48="OA15",E48+15, G48="OA30",E48+30, G48="OA60",E48+60 )} -> 46157 | G48: EM15 | H48: 176500 | I48: =INDEX(Customer_list!$G$2:$G$21,MATCH(B48,Customer_list!$B$2:$B$21,0)) -> 0.97 | J48: Overdue | L48: =IF(J48="Collected",K48,IF(J48="Open",F48,F48+INDEX(Customer_list!$H$2:$H$21,MATCH(B48,Customer_list!$B$2:$B$21,0))*Weekly_Cash_Flow_Summary!$B$8)) -> 46160 | M48: =MIN(1,MAX(0,I48+Weekly_Cash_Flow_Summary!$B$7)) -> 0.97
A49: AR-260048 | B49: C00018 | C49: Lakeshore Retail Co. | D49: A | E49: 46186 | F49: {=_xlfn.IFS(G49="EM15",EOMONTH(E49,0)+15, G49="EM30",EOMONTH(E49,0)+30, G49="EM45",EOMONTH(E49,0)+45, G49="EM60",EOMONTH(E49,0)+60, G49="OA15",E49+15, G49="OA30",E49+30, G49="OA60",E49+60 )} -> 46216 | G49: OA30 | H49: 339500 | I49: =INDEX(Customer_list!$G$2:$G$21,MATCH(B49,Customer_list!$B$2:$B$21,0)) -> 0.97 | J49: Collected | K49: 46223 | L49: =IF(J49="Collected",K49,IF(J49="Open",F49,F49+INDEX(Customer_list!$H$2:$H$21,MATCH(B49,Customer_list!$B$2:$B$21,0))*Weekly_Cash_Flow_Summary!$B$8)) -> 46223 | M49: =MIN(1,MAX(0,I49+Weekly_Cash_Flow_Summary!$B$7)) -> 0.97
A50: AR-260049 | B50: C00005 | C50: Crestwood Merchandise Inc. | D50: C | E50: 46152 | F50: {=_xlfn.IFS(G50="EM15",EOMONTH(E50,0)+15, G50="EM30",EOMONTH(E50,0)+30, G50="EM45",EOMONTH(E50,0)+45, G50="EM60",EOMONTH(E50,0)+60, G50="OA15",E50+15, G50="OA30",E50+30, G50="OA60",E50+60 )} -> 46182 | G50: OA30 | H50: 104500 | I50: =INDEX(Customer_list!$G$2:$G$21,MATCH(B50,Customer_list!$B$2:$B$21,0)) -> 0.75 | J50: Overdue | L50: =IF(J50="Collected",K50,IF(J50="Open",F50,F50+INDEX(Customer_list!$H$2:$H$21,MATCH(B50,Customer_list!$B$2:$B$21,0))*Weekly_Cash_Flow_Summary!$B$8)) -> 46207 | M50: =MIN(1,MAX(0,I50+Weekly_Cash_Flow_Summary!$B$7)) -> 0.75
A51: AR-260050 | B51: C00014 | C51: Clearwater Commerce Co. | D51: A | E51: 46184 | F51: {=_xlfn.IFS(G51="EM15",EOMONTH(E51,0)+15, G51="EM30",EOMONTH(E51,0)+30, G51="EM45",EOMONTH(E51,0)+45, G51="EM60",EOMONTH(E51,0)+60, G51="OA15",E51+15, G51="OA30",E51+30, G51="OA60",E51+60 )} -> 46248 | G51: EM45 | H51: 20500 | I51: =INDEX(Customer_list!$G$2:$G$21,MATCH(B51,Customer_list!$B$2:$B$21,0)) -> 0.97 | J51: Open | L51: =IF(J51="Collected",K51,IF(J51="Open",F51,F51+INDEX(Customer_list!$H$2:$H$21,MATCH(B51,Customer_list!$B$2:$B$21,0))*Weekly_Cash_Flow_Summary!$B$8)) -> 46248 | M51: =MIN(1,MAX(0,I51+Weekly_Cash_Flow_Summary!$B$7)) -> 0.97
A52: AR-260051 | B52: C00011 | C52: Riverton Wholesale Ltd. | D52: B | E52: 46217 | F52: {=_xlfn.IFS(G52="EM15",EOMONTH(E52,0)+15, G52="EM30",EOMONTH(E52,0)+30, G52="EM45",EOMONTH(E52,0)+45, G52="EM60",EOMONTH(E52,0)+60, G52="OA15",E52+15, G52="OA30",E52+30, G52="OA60",E52+60 )} -> 46232 | G52: OA15 | H52: 30000 | I52: =INDEX(Customer_list!$G$2:$G$21,MATCH(B52,Customer_list!$B$2:$B$21,0)) -> 0.75 | J52: Overdue | L52: =IF(J52="Collected",K52,IF(J52="Open",F52,F52+INDEX(Customer_list!$H$2:$H$21,MATCH(B52,Customer_list!$B$2:$B$21,0))*Weekly_Cash_Flow_Summary!$B$8)) -> 46257 | M52: =MIN(1,MAX(0,I52+Weekly_Cash_Flow_Summary!$B$7)) -> 0.75
A53: AR-260052 | B53: C00018 | C53: Lakeshore Retail Co. | D53: A | E53: 46200 | F53: {=_xlfn.IFS(G53="EM15",EOMONTH(E53,0)+15, G53="EM30",EOMONTH(E53,0)+30, G53="EM45",EOMONTH(E53,0)+45, G53="EM60",EOMONTH(E53,0)+60, G53="OA15",E53+15, G53="OA30",E53+30, G53="OA60",E53+60 )} -> 46230 | G53: OA30 | H53: 181000 | I53: =INDEX(Customer_list!$G$2:$G$21,MATCH(B53,Customer_list!$B$2:$B$21,0)) -> 0.97 | J53: Overdue | L53: =IF(J53="Collected",K53,IF(J53="Open",F53,F53+INDEX(Customer_list!$H$2:$H$21,MATCH(B53,Customer_list!$B$2:$B$21,0))*Weekly_Cash_Flow_Summary!$B$8)) -> 46233 | M53: =MIN(1,MAX(0,I53+Weekly_Cash_Flow_Summary!$B$7)) -> 0.97
A54: AR-260053 | B54: C00008 | C54: Sunridge Retail Partners | D54: B | E54: 46136 | F54: {=_xlfn.IFS(G54="EM15",EOMONTH(E54,0)+15, G54="EM30",EOMONTH(E54,0)+30, G54="EM45",EOMONTH(E54,0)+45, G54="EM60",EOMONTH(E54,0)+60, G54="OA15",E54+15, G54="OA30",E54+30, G54="OA60",E54+60 )} -> 46166 | G54: OA30 | H54: 317500 | I54: =INDEX(Customer_list!$G$2:$G$21,MATCH(B54,Customer_list!$B$2:$B$21,0)) -> 0.9 | J54: Collected | K54: 46172 | L54: =IF(J54="Collected",K54,IF(J54="Open",F54,F54+INDEX(Customer_list!$H$2:$H$21,MATCH(B54,Customer_list!$B$2:$B$21,0))*Weekly_Cash_Flow_Summary!$B$8)) -> 46172 | M54: =MIN(1,MAX(0,I54+Weekly_Cash_Flow_Summary!$B$7)) -> 0.9
A55: AR-260054 | B55: C00012 | C55: Goldenbridge Retailers | D55: B | E55: 46126 | F55: {=_xlfn.IFS(G55="EM15",EOMONTH(E55,0)+15, G55="EM30",EOMONTH(E55,0)+30, G55="EM45",EOMONTH(E55,0)+45, G55="EM60",EOMONTH(E55,0)+60, G55="OA15",E55+15, G55="OA30",E55+30, G55="OA60",E55+60 )} -> 46156 | G55: OA30 | H55: 65000 | I55: =INDEX(Customer_list!$G$2:$G$21,MATCH(B55,Customer_list!$B$2:$B$21,0)) -> 0.9 | J55: Collected | K55: 46167 | L55: =IF(J55="Collected",K55,IF(J55="Open",F55,F55+INDEX(Customer_list!$H$2:$H$21,MATCH(B55,Customer_list!$B$2:$B$21,0))*Weekly_Cash_Flow_Summary!$B$8)) -> 46167 | M55: =MIN(1,MAX(0,I55+Weekly_Cash_Flow_Summary!$B$7)) -> 0.9
A56: AR-260055 | B56: C00004 | C56: Harborview Trading Ltd. | D56: B | E56: 46187 | F56: {=_xlfn.IFS(G56="EM15",EOMONTH(E56,0)+15, G56="EM30",EOMONTH(E56,0)+30, G56="EM45",EOMONTH(E56,0)+45, G56="EM60",EOMONTH(E56,0)+60, G56="OA15",E56+15, G56="OA30",E56+30, G56="OA60",E56+60 )} -> 46263 | G56: EM60 | H56: 299500 | I56: =INDEX(Customer_list!$G$2:$G$21,MATCH(B56,Customer_list!$B$2:$B$21,0)) -> 0.9 | J56: Open | L56: =IF(J56="Collected",K56,IF(J56="Open",F56,F56+INDEX(Customer_list!$H$2:$H$21,MATCH(B56,Customer_list!$B$2:$B$21,0))*Weekly_Cash_Flow_Summary!$B$8)) -> 46263 | M56: =MIN(1,MAX(0,I56+Weekly_Cash_Flow_Summary!$B$7)) -> 0.9
A57: AR-260056 | B57: C00013 | C57: Pinehill Distribution Inc. | D57: B | E57: 46186 | F57: {=_xlfn.IFS(G57="EM15",EOMONTH(E57,0)+15, G57="EM30",EOMONTH(E57,0)+30, G57="EM45",EOMONTH(E57,0)+45, G57="EM60",EOMONTH(E57,0)+60, G57="OA15",E57+15, G57="OA30",E57+30, G57="OA60",E57+60 )} -> 46216 | G57: OA30 | H57: 269000 | I57: =INDEX(Customer_list!$G$2:$G$21,MATCH(B57,Customer_list!$B$2:$B$21,0)) -> 0.75 | J57: Overdue | L57: =IF(J57="Collected",K57,IF(J57="Open",F57,F57+INDEX(Customer_list!$H$2:$H$21,MATCH(B57,Customer_list!$B$2:$B$21,0))*Weekly_Cash_Flow_Summary!$B$8)) -> 46241 | M57: =MIN(1,MAX(0,I57+Weekly_Cash_Flow_Summary!$B$7)) -> 0.75
A58: AR-260057 | B58: C00018 | C58: Lakeshore Retail Co. | D58: A | E58: 46194 | F58: {=_xlfn.IFS(G58="EM15",EOMONTH(E58,0)+15, G58="EM30",EOMONTH(E58,0)+30, G58="EM45",EOMONTH(E58,0)+45, G58="EM60",EOMONTH(E58,0)+60, G58="OA15",E58+15, G58="OA30",E58+30, G58="OA60",E58+60 )} -> 46224 | G58: OA30 | H58: 106500 | I58: =INDEX(Customer_list!$G$2:$G$21,MATCH(B58,Customer_list!$B$2:$B$21,0)) -> 0.97 | J58: Overdue | L58: =IF(J58="Collected",K58,IF(J58="Open",F58,F58+INDEX(Customer_list!$H$2:$H$21,MATCH(B58,Customer_list!$B$2:$B$21,0))*Weekly_Cash_Flow_Summary!$B$8)) -> 46227 | M58: =MIN(1,MAX(0,I58+Weekly_Cash_Flow_Summary!$B$7)) -> 0.97
A59: AR-260058 | B59: C00004 | C59: Harborview Trading Ltd. | D59: B | E59: 46137 | F59: {=_xlfn.IFS(G59="EM15",EOMONTH(E59,0)+15, G59="EM30",EOMONTH(E59,0)+30, G59="EM45",EOMONTH(E59,0)+45, G59="EM60",EOMONTH(E59,0)+60, G59="OA15",E59+15, G59="OA30",E59+30, G59="OA60",E59+60 )} -> 46202 | G59: EM60 | H59: 131000 | I59: =INDEX(Customer_list!$G$2:$G$21,MATCH(B59,Customer_list!$B$2:$B$21,0)) -> 0.9 | J59: Collected | K59: 46213 | L59: =IF(J59="Collected",K59,IF(J59="Open",F59,F59+INDEX(Customer_list!$H$2:$H$21,MATCH(B59,Customer_list!$B$2:$B$21,0))*Weekly_Cash_Flow_Summary!$B$8)) -> 46213 | M59: =MIN(1,MAX(0,I59+Weekly_Cash_Flow_Summary!$B$7)) -> 0.9
A60: AR-260059 | B60: C00014 | C60: Clearwater Commerce Co. | D60: A | E60: 46160 | F60: {=_xlfn.IFS(G60="EM15",EOMONTH(E60,0)+15, G60="EM30",EOMONTH(E60,0)+30, G60="EM45",EOMONTH(E60,0)+45, G60="EM60",EOMONTH(E60,0)+60, G60="OA15",E60+15, G60="OA30",E60+30, G60="OA60",E60+60 )} -> 46218 | G60: EM45 | H60: 125500 | I60: =INDEX(Customer_list!$G$2:$G$21,MATCH(B60,Customer_list!$B$2:$B$21,0)) -> 0.97 | J60: Collected | K60: 46218 | L60: =IF(J60="Collected",K60,IF(J60="Open",F60,F60+INDEX(Customer_list!$H$2:$H$21,MATCH(B60,Customer_list!$B$2:$B$21,0))*Weekly_Cash_Flow_Summary!$B$8)) -> 46218 | M60: =MIN(1,MAX(0,I60+Weekly_Cash_Flow_Summary!$B$7)) -> 0.97
A61: AR-260060 | B61: C00008 | C61: Sunridge Retail Partners | D61: B | E61: 46125 | F61: {=_xlfn.IFS(G61="EM15",EOMONTH(E61,0)+15, G61="EM30",EOMONTH(E61,0)+30, G61="EM45",EOMONTH(E61,0)+45, G61="EM60",EOMONTH(E61,0)+60, G61="OA15",E61+15, G61="OA30",E61+30, G61="OA60",E61+60 )} -> 46155 | G61: OA30 | H61: 216000 | I61: =INDEX(Customer_list!$G$2:$G$21,MATCH(B61,Customer_list!$B$2:$B$21,0)) -> 0.9 | J61: Overdue | L61: =IF(J61="Collected",K61,IF(J61="Open",F61,F61+INDEX(Customer_list!$H$2:$H$21,MATCH(B61,Customer_list!$B$2:$B$21,0))*Weekly_Cash_Flow_Summary!$B$8)) -> 46165 | M61: =MIN(1,MAX(0,I61+Weekly_Cash_Flow_Summary!$B$7)) -> 0.9
A62: AR-260061 | B62: C00010 | C62: Oakhaven Trading Co. | D62: A | E62: 46183 | F62: {=_xlfn.IFS(G62="EM15",EOMONTH(E62,0)+15, G62="EM30",EOMONTH(E62,0)+30, G62="EM45",EOMONTH(E62,0)+45, G62="EM60",EOMONTH(E62,0)+60, G62="OA15",E62+15, G62="OA30",E62+30, G62="OA60",E62+60 )} -> 46213 | G62: OA30 | H62: 83500 | I62: =INDEX(Customer_list!$G$2:$G$21,MATCH(B62,Customer_list!$B$2:$B$21,0)) -> 0.97 | J62: Collected | K62: 46218 | L62: =IF(J62="Collected",K62,IF(J62="Open",F62,F62+INDEX(Customer_list!$H$2:$H$21,MATCH(B62,Customer_list!$B$2:$B$21,0))*Weekly_Cash_Flow_Summary!$B$8)) -> 46218 | M62: =MIN(1,MAX(0,I62+Weekly_Cash_Flow_Summary!$B$7)) -> 0.97
A63: AR-260062 | B63: C00016 | C63: Fairview Merchants Ltd. | D63: B | E63: 46204 | F63: {=_xlfn.IFS(G63="EM15",EOMONTH(E63,0)+15, G63="EM30",EOMONTH(E63,0)+30, G63="EM45",EOMONTH(E63,0)+45, G63="EM60",EOMONTH(E63,0)+60, G63="OA15",E63+15, G63="OA30",E63+30, G63="OA60",E63+60 )} -> 46249 | G63: EM15 | H63: 197500 | I63: =INDEX(Customer_list!$G$2:$G$21,MATCH(B63,Customer_list!$B$2:$B$21,0)) -> 0.9 | J63: Open | L63: =IF(J63="Collected",K63,IF(J63="Open",F63,F63+INDEX(Customer_list!$H$2:$H$21,MATCH(B63,Customer_list!$B$2:$B$21,0))*Weekly_Cash_Flow_Summary!$B$8)) -> 46249 | M63: =MIN(1,MAX(0,I63+Weekly_Cash_Flow_Summary!$B$7)) -> 0.9
A64: AR-260063 | B64: C00012 | C64: Goldenbridge Retailers | D64: B | E64: 46121 | F64: {=_xlfn.IFS(G64="EM15",EOMONTH(E64,0)+15, G64="EM30",EOMONTH(E64,0)+30, G64="EM45",EOMONTH(E64,0)+45, G64="EM60",EOMONTH(E64,0)+60, G64="OA15",E64+15, G64="OA30",E64+30, G64="OA60",E64+60 )} -> 46151 | G64: OA30 | H64: 328500 | I64: =INDEX(Customer_list!$G$2:$G$21,MATCH(B64,Customer_list!$B$2:$B$21,0)) -> 0.9 | J64: Collected | K64: 46167 | L64: =IF(J64="Collected",K64,IF(J64="Open",F64,F64+INDEX(Customer_list!$H$2:$H$21,MATCH(B64,Customer_list!$B$2:$B$21,0))*Weekly_Cash_Flow_Summary!$B$8)) -> 46167 | M64: =MIN(1,MAX(0,I64+Weekly_Cash_Flow_Summary!$B$7)) -> 0.9
A65: AR-260064 | B65: C00018 | C65: Lakeshore Retail Co. | D65: A | E65: 46185 | F65: {=_xlfn.IFS(G65="EM15",EOMONTH(E65,0)+15, G65="EM30",EOMONTH(E65,0)+30, G65="EM45",EOMONTH(E65,0)+45, G65="EM60",EOMONTH(E65,0)+60, G65="OA15",E65+15, G65="OA30",E65+30, G65="OA60",E65+60 )} -> 46215 | G65: OA30 | H65: 51000 | I65: =INDEX(Customer_list!$G$2:$G$21,MATCH(B65,Customer_list!$B$2:$B$21,0)) -> 0.97 | J65: Collected | K65: 46223 | L65: =IF(J65="Collected",K65,IF(J65="Open",F65,F65+INDEX(Customer_list!$H$2:$H$21,MATCH(B65,Customer_list!$B$2:$B$21,0))*Weekly_Cash_Flow_Summary!$B$8)) -> 46223 | M65: =MIN(1,MAX(0,I65+Weekly_Cash_Flow_Summary!$B$7)) -> 0.97
A66: AR-260065 | B66: C00015 | C66: Brightstone Supply Group | D66: B | E66: 46120 | F66: {=_xlfn.IFS(G66="EM15",EOMONTH(E66,0)+15, G66="EM30",EOMONTH(E66,0)+30, G66="EM45",EOMONTH(E66,0)+45, G66="EM60",EOMONTH(E66,0)+60, G66="OA15",E66+15, G66="OA30",E66+30, G66="OA60",E66+60 )} -> 46187 | G66: EM45 | H66: 193000 | I66: =INDEX(Customer_list!$G$2:$G$21,MATCH(B66,Customer_list!$B$2:$B$21,0)) -> 0.75 | J66: Collected | K66: 46208 | L66: =IF(J66="Collected",K66,IF(J66="Open",F66,F66+INDEX(Customer_list!$H$2:$H$21,MATCH(B66,Customer_list!$B$2:$B$21,0))*Weekly_Cash_Flow_Summary!$B$8)) -> 46208 | M66: =MIN(1,MAX(0,I66+Weekly_Cash_Flow_Summary!$B$7)) -> 0.75
A67: AR-260066 | B67: C00015 | C67: Brightstone Supply Group | D67: B | E67: 46192 | F67: {=_xlfn.IFS(G67="EM15",EOMONTH(E67,0)+15, G67="EM30",EOMONTH(E67,0)+30, G67="EM45",EOMONTH(E67,0)+45, G67="EM60",EOMONTH(E67,0)+60, G67="OA15",E67+15, G67="OA30",E67+30, G67="OA60",E67+60 )} -> 46248 | G67: EM45 | H67: 166000 | I67: =INDEX(Customer_list!$G$2:$G$21,MATCH(B67,Customer_list!$B$2:$B$21,0)) -> 0.75 | J67: Open | L67: =IF(J67="Collected",K67,IF(J67="Open",F67,F67+INDEX(Customer_list!$H$2:$H$21,MATCH(B67,Customer_list!$B$2:$B$21,0))*Weekly_Cash_Flow_Summary!$B$8)) -> 46248 | M67: =MIN(1,MAX(0,I67+Weekly_Cash_Flow_Summary!$B$7)) -> 0.75
A68: AR-260067 | B68: C00012 | C68: Goldenbridge Retailers | D68: B | E68: 46139 | F68: {=_xlfn.IFS(G68="EM15",EOMONTH(E68,0)+15, G68="EM30",EOMONTH(E68,0)+30, G68="EM45",EOMONTH(E68,0)+45, G68="EM60",EOMONTH(E68,0)+60, G68="OA15",E68+15, G68="OA30",E68+30, G68="OA60",E68+60 )} -> 46169 | G68: OA30 | H68: 274500 | I68: =INDEX(Customer_list!$G$2:$G$21,MATCH(B68,Customer_list!$B$2:$B$21,0)) -> 0.9 | J68: Collected | K68: 46183 | L68: =IF(J68="Collected",K68,IF(J68="Open",F68,F68+INDEX(Customer_list!$H$2:$H$21,MATCH(B68,Customer_list!$B$2:$B$21,0))*Weekly_Cash_Flow_Summary!$B$8)) -> 46183 | M68: =MIN(1,MAX(0,I68+Weekly_Cash_Flow_Summary!$B$7)) -> 0.9
A69: AR-260068 | B69: C00012 | C69: Goldenbridge Retailers | D69: B | E69: 46176 | F69: {=_xlfn.IFS(G69="EM15",EOMONTH(E69,0)+15, G69="EM30",EOMONTH(E69,0)+30, G69="EM45",EOMONTH(E69,0)+45, G69="EM60",EOMONTH(E69,0)+60, G69="OA15",E69+15, G69="OA30",E69+30, G69="OA60",E69+60 )} -> 46206 | G69: OA30 | H69: 319500 | I69: =INDEX(Customer_list!$G$2:$G$21,MATCH(B69,Customer_list!$B$2:$B$21,0)) -> 0.9 | J69: Collected | K69: 46213 | L69: =IF(J69="Collected",K69,IF(J69="Open",F69,F69+INDEX(Customer_list!$H$2:$H$21,MATCH(B69,Customer_list!$B$2:$B$21,0))*Weekly_Cash_Flow_Summary!$B$8)) -> 46213 | M69: =MIN(1,MAX(0,I69+Weekly_Cash_Flow_Summary!$B$7)) -> 0.9
A70: AR-260069 | B70: C00010 | C70: Oakhaven Trading Co. | D70: A | E70: 46200 | F70: {=_xlfn.IFS(G70="EM15",EOMONTH(E70,0)+15, G70="EM30",EOMONTH(E70,0)+30, G70="EM45",EOMONTH(E70,0)+45, G70="EM60",EOMONTH(E70,0)+60, G70="OA15",E70+15, G70="OA30",E70+30, G70="OA60",E70+60 )} -> 46230 | G70: OA30 | H70: 268000 | I70: =INDEX(Customer_list!$G$2:$G$21,MATCH(B70,Customer_list!$B$2:$B$21,0)) -> 0.97 | J70: Overdue | L70: =IF(J70="Collected",K70,IF(J70="Open",F70,F70+INDEX(Customer_list!$H$2:$H$21,MATCH(B70,Customer_list!$B$2:$B$21,0))*Weekly_Cash_Flow_Summary!$B$8)) -> 46233 | M70: =MIN(1,MAX(0,I70+Weekly_Cash_Flow_Summary!$B$7)) -> 0.97
A71: AR-260070 | B71: C00013 | C71: Pinehill Distribution Inc. | D71: B | E71: 46181 | F71: {=_xlfn.IFS(G71="EM15",EOMONTH(E71,0)+15, G71="EM30",EOMONTH(E71,0)+30, G71="EM45",EOMONTH(E71,0)+45, G71="EM60",EOMONTH(E71,0)+60, G71="OA15",E71+15, G71="OA30",E71+30, G71="OA60",E71+60 )} -> 46211 | G71: OA30 | H71: 69500 | I71: =INDEX(Customer_list!$G$2:$G$21,MATCH(B71,Customer_list!$B$2:$B$21,0)) -> 0.75 | J71: Overdue | L71: =IF(J71="Collected",K71,IF(J71="Open",F71,F71+INDEX(Customer_list!$H$2:$H$21,MATCH(B71,Customer_list!$B$2:$B$21,0))*Weekly_Cash_Flow_Summary!$B$8)) -> 46236 | M71: =MIN(1,MAX(0,I71+Weekly_Cash_Flow_Summary!$B$7)) -> 0.75
A72: AR-260071 | B72: C00002 | C72: Northgate Commerce Co. | D72: B | E72: 46167 | F72: {=_xlfn.IFS(G72="EM15",EOMONTH(E72,0)+15, G72="EM30",EOMONTH(E72,0)+30, G72="EM45",EOMONTH(E72,0)+45, G72="EM60",EOMONTH(E72,0)+60, G72="OA15",E72+15, G72="OA30",E72+30, G72="OA60",E72+60 )} -> 46227 | G72: OA60 | H72: 206000 | I72: =INDEX(Customer_list!$G$2:$G$21,MATCH(B72,Customer_list!$B$2:$B$21,0)) -> 0.9 | J72: Overdue | L72: =IF(J72="Collected",K72,IF(J72="Open",F72,F72+INDEX(Customer_list!$H$2:$H$21,MATCH(B72,Customer_list!$B$2:$B$21,0))*Weekly_Cash_Flow_Summary!$B$8)) -> 46237 | M72: =MIN(1,MAX(0,I72+Weekly_Cash_Flow_Summary!$B$7)) -> 0.9
A73: AR-260072 | B73: C00008 | C73: Sunridge Retail Partners | D73: B | E73: 46212 | F73: {=_xlfn.IFS(G73="EM15",EOMONTH(E73,0)+15, G73="EM30",EOMONTH(E73,0)+30, G73="EM45",EOMONTH(E73,0)+45, G73="EM60",EOMONTH(E73,0)+60, G73="OA15",E73+15, G73="OA30",E73+30, G73="OA60",E73+60 )} -> 46242 | G73: OA30 | H73: 242000 | I73: =INDEX(Customer_list!$G$2:$G$21,MATCH(B73,Customer_list!$B$2:$B$21,0)) -> 0.9 | J73: Open | L73: =IF(J73="Collected",K73,IF(J73="Open",F73,F73+INDEX(Customer_list!$H$2:$H$21,MATCH(B73,Customer_list!$B$2:$B$21,0))*Weekly_Cash_Flow_Summary!$B$8)) -> 46242 | M73: =MIN(1,MAX(0,I73+Weekly_Cash_Flow_Summary!$B$7)) -> 0.9
A74: AR-260073 | B74: C00009 | C74: Westfall Commercial Group | D74: A | E74: 46153 | F74: {=_xlfn.IFS(G74="EM15",EOMONTH(E74,0)+15, G74="EM30",EOMONTH(E74,0)+30, G74="EM45",EOMONTH(E74,0)+45, G74="EM60",EOMONTH(E74,0)+60, G74="OA15",E74+15, G74="OA30",E74+30, G74="OA60",E74+60 )} -> 46203 | G74: EM30 | H74: 71500 | I74: =INDEX(Customer_list!$G$2:$G$21,MATCH(B74,Customer_list!$B$2:$B$21,0)) -> 0.9 | J74: Collected | K74: 46208 | L74: =IF(J74="Collected",K74,IF(J74="Open",F74,F74+INDEX(Customer_list!$H$2:$H$21,MATCH(B74,Customer_list!$B$2:$B$21,0))*Weekly_Cash_Flow_Summary!$B$8)) -> 46208 | M74: =MIN(1,MAX(0,I74+Weekly_Cash_Flow_Summary!$B$7)) -> 0.9
A75: AR-260074 | B75: C00004 | C75: Harborview Trading Ltd. | D75: B | E75: 46172 | F75: {=_xlfn.IFS(G75="EM15",EOMONTH(E75,0)+15, G75="EM30",EOMONTH(E75,0)+30, G75="EM45",EOMONTH(E75,0)+45, G75="EM60",EOMONTH(E75,0)+60, G75="OA15",E75+15, G75="OA30",E75+30, G75="OA60",E75+60 )} -> 46233 | G75: EM60 | H75: 77500 | I75: =INDEX(Customer_list!$G$2:$G$21,MATCH(B75,Customer_list!$B$2:$B$21,0)) -> 0.9 | J75: Open | L75: =IF(J75="Collected",K75,IF(J75="Open",F75,F75+INDEX(Customer_list!$H$2:$H$21,MATCH(B75,Customer_list!$B$2:$B$21,0))*Weekly_Cash_Flow_Summary!$B$8)) -> 46233 | M75: =MIN(1,MAX(0,I75+Weekly_Cash_Flow_Summary!$B$7)) -> 0.9
A76: AR-260075 | B76: C00002 | C76: Northgate Commerce Co. | D76: B | E76: 46187 | F76: {=_xlfn.IFS(G76="EM15",EOMONTH(E76,0)+15, G76="EM30",EOMONTH(E76,0)+30, G76="EM45",EOMONTH(E76,0)+45, G76="EM60",EOMONTH(E76,0)+60, G76="OA15",E76+15, G76="OA30",E76+30, G76="OA60",E76+60 )} -> 46247 | G76: OA60 | H76: 150500 | I76: =INDEX(Customer_list!$G$2:$G$21,MATCH(B76,Customer_list!$B$2:$B$21,0)) -> 0.9 | J76: Open | L76: =IF(J76="Collected",K76,IF(J76="Open",F76,F76+INDEX(Customer_list!$H$2:$H$21,MATCH(B76,Customer_list!$B$2:$B$21,0))*Weekly_Cash_Flow_Summary!$B$8)) -> 46247 | M76: =MIN(1,MAX(0,I76+Weekly_Cash_Flow_Summary!$B$7)) -> 0.9
A77: AR-260076 | B77: C00001 | C77: Silverline Retail Group | D77: C | E77: 46231 | F77: {=_xlfn.IFS(G77="EM15",EOMONTH(E77,0)+15, G77="EM30",EOMONTH(E77,0)+30, G77="EM45",EOMONTH(E77,0)+45, G77="EM60",EOMONTH(E77,0)+60, G77="OA15",E77+15, G77="OA30",E77+30, G77="OA60",E77+60 )} -> 46249 | G77: EM15 | H77: 120500 | I77: =INDEX(Customer_list!$G$2:$G$21,MATCH(B77,Customer_list!$B$2:$B$21,0)) -> 0.97 | J77: Open | L77: =IF(J77="Collected",K77,IF(J77="Open",F77,F77+INDEX(Customer_list!$H$2:$H$21,MATCH(B77,Customer_list!$B$2:$B$21,0))*Weekly_Cash_Flow_Summary!$B$8)) -> 46249 | M77: =MIN(1,MAX(0,I77+Weekly_Cash_Flow_Summary!$B$7)) -> 0.97
A78: AR-260077 | B78: C00012 | C78: Goldenbridge Retailers | D78: B | E78: 46171 | F78: {=_xlfn.IFS(G78="EM15",EOMONTH(E78,0)+15, G78="EM30",EOMONTH(E78,0)+30, G78="EM45",EOMONTH(E78,0)+45, G78="EM60",EOMONTH(E78,0)+60, G78="OA15",E78+15, G78="OA30",E78+30, G78="OA60",E78+60 )} -> 46201 | G78: OA30 | H78: 93500 | I78: =INDEX(Customer_list!$G$2:$G$21,MATCH(B78,Customer_list!$B$2:$B$21,0)) -> 0.9 | J78: Collected | K78: 46213 | L78: =IF(J78="Collected",K78,IF(J78="Open",F78,F78+INDEX(Customer_list!$H$2:$H$21,MATCH(B78,Customer_list!$B$2:$B$21,0))*Weekly_Cash_Flow_Summary!$B$8)) -> 46213 | M78: =MIN(1,MAX(0,I78+Weekly_Cash_Flow_Summary!$B$7)) -> 0.9
A79: AR-260078 | B79: C00018 | C79: Lakeshore Retail Co. | D79: A | E79: 46159 | F79: {=_xlfn.IFS(G79="EM15",EOMONTH(E79,0)+15, G79="EM30",EOMONTH(E79,0)+30, G79="EM45",EOMONTH(E79,0)+45, G79="EM60",EOMONTH(E79,0)+60, G79="OA15",E79+15, G79="OA30",E79+30, G79="OA60",E79+60 )} -> 46189 | G79: OA30 | H79: 241000 | I79: =INDEX(Customer_list!$G$2:$G$21,MATCH(B79,Customer_list!$B$2:$B$21,0)) -> 0.97 | J79: Collected | K79: 46193 | L79: =IF(J79="Collected",K79,IF(J79="Open",F79,F79+INDEX(Customer_list!$H$2:$H$21,MATCH(B79,Customer_list!$B$2:$B$21,0))*Weekly_Cash_Flow_Summary!$B$8)) -> 46193 | M79: =MIN(1,MAX(0,I79+Weekly_Cash_Flow_Summary!$B$7)) -> 0.97
A80: AR-260079 | B80: C00010 | C80: Oakhaven Trading Co. | D80: A | E80: 46151 | F80: {=_xlfn.IFS(G80="EM15",EOMONTH(E80,0)+15, G80="EM30",EOMONTH(E80,0)+30, G80="EM45",EOMONTH(E80,0)+45, G80="EM60",EOMONTH(E80,0)+60, G80="OA15",E80+15, G80="OA30",E80+30, G80="OA60",E80+60 )} -> 46181 | G80: OA30 | H80: 151000 | I80: =INDEX(Customer_list!$G$2:$G$21,MATCH(B80,Customer_list!$B$2:$B$21,0)) -> 0.97 | J80: Collected | K80: 46188 | L80: =IF(J80="Collected",K80,IF(J80="Open",F80,F80+INDEX(Customer_list!$H$2:$H$21,MATCH(B80,Customer_list!$B$2:$B$21,0))*Weekly_Cash_Flow_Summary!$B$8)) -> 46188 | M80: =MIN(1,MAX(0,I80+Weekly_Cash_Flow_Summary!$B$7)) -> 0.97
A81: AR-260080 | B81: C00017 | C81: Cedarpoint Trading Inc. | D81: C | E81: 46144 | F81: {=_xlfn.IFS(G81="EM15",EOMONTH(E81,0)+15, G81="EM30",EOMONTH(E81,0)+30, G81="EM45",EOMONTH(E81,0)+45, G81="EM60",EOMONTH(E81,0)+60, G81="OA15",E81+15, G81="OA30",E81+30, G81="OA60",E81+60 )} -> 46218 | G81: EM45 | H81: 252500 | I81: =INDEX(Customer_list!$G$2:$G$21,MATCH(B81,Customer_list!$B$2:$B$21,0)) -> 0.75 | J81: Overdue | L81: =IF(J81="Collected",K81,IF(J81="Open",F81,F81+INDEX(Customer_list!$H$2:$H$21,MATCH(B81,Customer_list!$B$2:$B$21,0))*Weekly_Cash_Flow_Summary!$B$8)) -> 46243 | M81: =MIN(1,MAX(0,I81+Weekly_Cash_Flow_Summary!$B$7)) -> 0.75
A82: AR-260081 | B82: C00015 | C82: Brightstone Supply Group | D82: B | E82: 46214 | F82: {=_xlfn.IFS(G82="EM15",EOMONTH(E82,0)+15, G82="EM30",EOMONTH(E82,0)+30, G82="EM45",EOMONTH(E82,0)+45, G82="EM60",EOMONTH(E82,0)+60, G82="OA15",E82+15, G82="OA30",E82+30, G82="OA60",E82+60 )} -> 46279 | G82: EM45 | H82: 308500 | I82: =INDEX(Customer_list!$G$2:$G$21,MATCH(B82,Customer_list!$B$2:$B$21,0)) -> 0.75 | J82: Open | L82: =IF(J82="Collected",K82,IF(J82="Open",F82,F82+INDEX(Customer_list!$H$2:$H$21,MATCH(B82,Customer_list!$B$2:$B$21,0))*Weekly_Cash_Flow_Summary!$B$8)) -> 46279 | M82: =MIN(1,MAX(0,I82+Weekly_Cash_Flow_Summary!$B$7)) -> 0.75
A83: AR-260082 | B83: C00002 | C83: Northgate Commerce Co. | D83: B | E83: 46136 | F83: {=_xlfn.IFS(G83="EM15",EOMONTH(E83,0)+15, G83="EM30",EOMONTH(E83,0)+30, G83="EM45",EOMONTH(E83,0)+45, G83="EM60",EOMONTH(E83,0)+60, G83="OA15",E83+15, G83="OA30",E83+30, G83="OA60",E83+60 )} -> 46196 | G83: OA60 | H83: 71500 | I83: =INDEX(Customer_list!$G$2:$G$21,MATCH(B83,Customer_list!$B$2:$B$21,0)) -> 0.9 | J83: Overdue | L83: =IF(J83="Collected",K83,IF(J83="Open",F83,F83+INDEX(Customer_list!$H$2:$H$21,MATCH(B83,Customer_list!$B$2:$B$21,0))*Weekly_Cash_Flow_Summary!$B$8)) -> 46206 | M83: =MIN(1,MAX(0,I83+Weekly_Cash_Flow_Summary!$B$7)) -> 0.9
A84: AR-260083 | B84: C00007 | C84: Ironstone Enterprises | D84: A | E84: 46202 | F84: {=_xlfn.IFS(G84="EM15",EOMONTH(E84,0)+15, G84="EM30",EOMONTH(E84,0)+30, G84="EM45",EOMONTH(E84,0)+45, G84="EM60",EOMONTH(E84,0)+60, G84="OA15",E84+15, G84="OA30",E84+30, G84="OA60",E84+60 )} -> 46233 | G84: EM30 | H84: 46500 | I84: =INDEX(Customer_list!$G$2:$G$21,MATCH(B84,Customer_list!$B$2:$B$21,0)) -> 0.97 | J84: Open | L84: =IF(J84="Collected",K84,IF(J84="Open",F84,F84+INDEX(Customer_list!$H$2:$H$21,MATCH(B84,Customer_list!$B$2:$B$21,0))*Weekly_Cash_Flow_Summary!$B$8)) -> 46233 | M84: =MIN(1,MAX(0,I84+Weekly_Cash_Flow_Summary!$B$7)) -> 0.97
A85: AR-260084 | B85: C00002 | C85: Northgate Commerce Co. | D85: B | E85: 46212 | F85: {=_xlfn.IFS(G85="EM15",EOMONTH(E85,0)+15, G85="EM30",EOMONTH(E85,0)+30, G85="EM45",EOMONTH(E85,0)+45, G85="EM60",EOMONTH(E85,0)+60, G85="OA15",E85+15, G85="OA30",E85+30, G85="OA60",E85+60 )} -> 46272 | G85: OA60 | H85: 27500 | I85: =INDEX(Customer_list!$G$2:$G$21,MATCH(B85,Customer_list!$B$2:$B$21,0)) -> 0.9 | J85: Open | L85: =IF(J85="Collected",K85,IF(J85="Open",F85,F85+INDEX(Customer_list!$H$2:$H$21,MATCH(B85,Customer_list!$B$2:$B$21,0))*Weekly_Cash_Flow_Summary!$B$8)) -> 46272 | M85: =MIN(1,MAX(0,I85+Weekly_Cash_Flow_Summary!$B$7)) -> 0.9
A86: AR-260085 | B86: C00004 | C86: Harborview Trading Ltd. | D86: B | E86: 46144 | F86: {=_xlfn.IFS(G86="EM15",EOMONTH(E86,0)+15, G86="EM30",EOMONTH(E86,0)+30, G86="EM45",EOMONTH(E86,0)+45, G86="EM60",EOMONTH(E86,0)+60, G86="OA15",E86+15, G86="OA30",E86+30, G86="OA60",E86+60 )} -> 46233 | G86: EM60 | H86: 144000 | I86: =INDEX(Customer_list!$G$2:$G$21,MATCH(B86,Customer_list!$B$2:$B$21,0)) -> 0.9 | J86: Open | L86: =IF(J86="Collected",K86,IF(J86="Open",F86,F86+INDEX(Customer_list!$H$2:$H$21,MATCH(B86,Customer_list!$B$2:$B$21,0))*Weekly_Cash_Flow_Summary!$B$8)) -> 46233 | M86: =MIN(1,MAX(0,I86+Weekly_Cash_Flow_Summary!$B$7)) -> 0.9
A87: AR-260086 | B87: C00011 | C87: Riverton Wholesale Ltd. | D87: B | E87: 46123 | F87: {=_xlfn.IFS(G87="EM15",EOMONTH(E87,0)+15, G87="EM30",EOMONTH(E87,0)+30, G87="EM45",EOMONTH(E87,0)+45, G87="EM60",EOMONTH(E87,0)+60, G87="OA15",E87+15, G87="OA30",E87+30, G87="OA60",E87+60 )} -> 46138 | G87: OA15 | H87: 272500 | I87: =INDEX(Customer_list!$G$2:$G$21,MATCH(B87,Customer_list!$B$2:$B$21,0)) -> 0.75 | J87: Collected | K87: 46162 | L87: =IF(J87="Collected",K87,IF(J87="Open",F87,F87+INDEX(Customer_list!$H$2:$H$21,MATCH(B87,Customer_list!$B$2:$B$21,0))*Weekly_Cash_Flow_Summary!$B$8)) -> 46162 | M87: =MIN(1,MAX(0,I87+Weekly_Cash_Flow_Summary!$B$7)) -> 0.75
A88: AR-260087 | B88: C00019 | C88: Stonebridge Wholesale Group | D88: C | E88: 46186 | F88: {=_xlfn.IFS(G88="EM15",EOMONTH(E88,0)+15, G88="EM30",EOMONTH(E88,0)+30, G88="EM45",EOMONTH(E88,0)+45, G88="EM60",EOMONTH(E88,0)+60, G88="OA15",E88+15, G88="OA30",E88+30, G88="OA60",E88+60 )} -> 46216 | G88: OA30 | H88: 50500 | I88: =INDEX(Customer_list!$G$2:$G$21,MATCH(B88,Customer_list!$B$2:$B$21,0)) -> 0.9 | J88: Overdue | L88: =IF(J88="Collected",K88,IF(J88="Open",F88,F88+INDEX(Customer_list!$H$2:$H$21,MATCH(B88,Customer_list!$B$2:$B$21,0))*Weekly_Cash_Flow_Summary!$B$8)) -> 46226 | M88: =MIN(1,MAX(0,I88+Weekly_Cash_Flow_Summary!$B$7)) -> 0.9
A89: AR-260088 | B89: C00016 | C89: Fairview Merchants Ltd. | D89: B | E89: 46151 | F89: {=_xlfn.IFS(G89="EM15",EOMONTH(E89,0)+15, G89="EM30",EOMONTH(E89,0)+30, G89="EM45",EOMONTH(E89,0)+45, G89="EM60",EOMONTH(E89,0)+60, G89="OA15",E89+15, G89="OA30",E89+30, G89="OA60",E89+60 )} -> 46188 | G89: EM15 | H89: 106500 | I89: =INDEX(Customer_list!$G$2:$G$21,MATCH(B89,Customer_list!$B$2:$B$21,0)) -> 0.9 | J89: Overdue | L89: =IF(J89="Collected",K89,IF(J89="Open",F89,F89+INDEX(Customer_list!$H$2:$H$21,MATCH(B89,Customer_list!$B$2:$B$21,0))*Weekly_Cash_Flow_Summary!$B$8)) -> 46198 | M89: =MIN(1,MAX(0,I89+Weekly_Cash_Flow_Summary!$B$7)) -> 0.9
A90: AR-260089 | B90: C00001 | C90: Silverline Retail Group | D90: C | E90: 46180 | F90: {=_xlfn.IFS(G90="EM15",EOMONTH(E90,0)+15, G90="EM30",EOMONTH(E90,0)+30, G90="EM45",EOMONTH(E90,0)+45, G90="EM60",EOMONTH(E90,0)+60, G90="OA15",E90+15, G90="OA30",E90+30, G90="OA60",E90+60 )} -> 46218 | G90: EM15 | H90: 159000 | I90: =INDEX(Customer_list!$G$2:$G$21,MATCH(B90,Customer_list!$B$2:$B$21,0)) -> 0.97 | J90: Collected | K90: 46218 | L90: =IF(J90="Collected",K90,IF(J90="Open",F90,F90+INDEX(Customer_list!$H$2:$H$21,MATCH(B90,Customer_list!$B$2:$B$21,0))*Weekly_Cash_Flow_Summary!$B$8)) -> 46218 | M90: =MIN(1,MAX(0,I90+Weekly_Cash_Flow_Summary!$B$7)) -> 0.97
A91: AR-260090 | B91: C00002 | C91: Northgate Commerce Co. | D91: B | E91: 46176 | F91: {=_xlfn.IFS(G91="EM15",EOMONTH(E91,0)+15, G91="EM30",EOMONTH(E91,0)+30, G91="EM45",EOMONTH(E91,0)+45, G91="EM60",EOMONTH(E91,0)+60, G91="OA15",E91+15, G91="OA30",E91+30, G91="OA60",E91+60 )} -> 46236 | G91: OA60 | H91: 258500 | I91: =INDEX(Customer_list!$G$2:$G$21,MATCH(B91,Customer_list!$B$2:$B$21,0)) -> 0.9 | J91: Open | L91: =IF(J91="Collected",K91,IF(J91="Open",F91,F91+INDEX(Customer_list!$H$2:$H$21,MATCH(B91,Customer_list!$B$2:$B$21,0))*Weekly_Cash_Flow_Summary!$B$8)) -> 46236 | M91: =MIN(1,MAX(0,I91+Weekly_Cash_Flow_Summary!$B$7)) -> 0.9
A92: AR-260091 | B92: C00018 | C92: Lakeshore Retail Co. | D92: A | E92: 46225 | F92: {=_xlfn.IFS(G92="EM15",EOMONTH(E92,0)+15, G92="EM30",EOMONTH(E92,0)+30, G92="EM45",EOMONTH(E92,0)+45, G92="EM60",EOMONTH(E92,0)+60, G92="OA15",E92+15, G92="OA30",E92+30, G92="OA60",E92+60 )} -> 46255 | G92: OA30 | H92: 169500 | I92: =INDEX(Customer_list!$G$2:$G$21,MATCH(B92,Customer_list!$B$2:$B$21,0)) -> 0.97 | J92: Open | L92: =IF(J92="Collected",K92,IF(J92="Open",F92,F92+INDEX(Customer_list!$H$2:$H$21,MATCH(B92,Customer_list!$B$2:$B$21,0))*Weekly_Cash_Flow_Summary!$B$8)) -> 46255 | M92: =MIN(1,MAX(0,I92+Weekly_Cash_Flow_Summary!$B$7)) -> 0.97
A93: AR-260092 | B93: C00011 | C93: Riverton Wholesale Ltd. | D93: B | E93: 46156 | F93: {=_xlfn.IFS(G93="EM15",EOMONTH(E93,0)+15, G93="EM30",EOMONTH(E93,0)+30, G93="EM45",EOMONTH(E93,0)+45, G93="EM60",EOMONTH(E93,0)+60, G93="OA15",E93+15, G93="OA30",E93+30, G93="OA60",E93+60 )} -> 46171 | G93: OA15 | H93: 275000 | I93: =INDEX(Customer_list!$G$2:$G$21,MATCH(B93,Customer_list!$B$2:$B$21,0)) -> 0.75 | J93: Collected | K93: 46193 | L93: =IF(J93="Collected",K93,IF(J93="Open",F93,F93+INDEX(Customer_list!$H$2:$H$21,MATCH(B93,Customer_list!$B$2:$B$21,0))*Weekly_Cash_Flow_Summary!$B$8)) -> 46193 | M93: =MIN(1,MAX(0,I93+Weekly_Cash_Flow_Summary!$B$7)) -> 0.75
A94: AR-260093 | B94: C00016 | C94: Fairview Merchants Ltd. | D94: B | E94: 46206 | F94: {=_xlfn.IFS(G94="EM15",EOMONTH(E94,0)+15, G94="EM30",EOMONTH(E94,0)+30, G94="EM45",EOMONTH(E94,0)+45, G94="EM60",EOMONTH(E94,0)+60, G94="OA15",E94+15, G94="OA30",E94+30, G94="OA60",E94+60 )} -> 46249 | G94: EM15 | H94: 134000 | I94: =INDEX(Customer_list!$G$2:$G$21,MATCH(B94,Customer_list!$B$2:$B$21,0)) -> 0.9 | J94: Open | L94: =IF(J94="Collected",K94,IF(J94="Open",F94,F94+INDEX(Customer_list!$H$2:$H$21,MATCH(B94,Customer_list!$B$2:$B$21,0))*Weekly_Cash_Flow_Summary!$B$8)) -> 46249 | M94: =MIN(1,MAX(0,I94+Weekly_Cash_Flow_Summary!$B$7)) -> 0.9
A95: AR-260094 | B95: C00003 | C95: BluePeak Distributors | D95: A | E95: 46170 | F95: {=_xlfn.IFS(G95="EM15",EOMONTH(E95,0)+15, G95="EM30",EOMONTH(E95,0)+30, G95="EM45",EOMONTH(E95,0)+45, G95="EM60",EOMONTH(E95,0)+60, G95="OA15",E95+15, G95="OA30",E95+30, G95="OA60",E95+60 )} -> 46233 | G95: EM60 | H95: 323500 | I95: =INDEX(Customer_list!$G$2:$G$21,MATCH(B95,Customer_list!$B$2:$B$21,0)) -> 0.97 | J95: Open | L95: =IF(J95="Collected",K95,IF(J95="Open",F95,F95+INDEX(Customer_list!$H$2:$H$21,MATCH(B95,Customer_list!$B$2:$B$21,0))*Weekly_Cash_Flow_Summary!$B$8)) -> 46233 | M95: =MIN(1,MAX(0,I95+Weekly_Cash_Flow_Summary!$B$7)) -> 0.97
A96: AR-260095 | B96: C00016 | C96: Fairview Merchants Ltd. | D96: B | E96: 46149 | F96: {=_xlfn.IFS(G96="EM15",EOMONTH(E96,0)+15, G96="EM30",EOMONTH(E96,0)+30, G96="EM45",EOMONTH(E96,0)+45, G96="EM60",EOMONTH(E96,0)+60, G96="OA15",E96+15, G96="OA30",E96+30, G96="OA60",E96+60 )} -> 46188 | G96: EM15 | H96: 184500 | I96: =INDEX(Customer_list!$G$2:$G$21,MATCH(B96,Customer_list!$B$2:$B$21,0)) -> 0.9 | J96: Collected | K96: 46198 | L96: =IF(J96="Collected",K96,IF(J96="Open",F96,F96+INDEX(Customer_list!$H$2:$H$21,MATCH(B96,Customer_list!$B$2:$B$21,0))*Weekly_Cash_Flow_Summary!$B$8)) -> 46198 | M96: =MIN(1,MAX(0,I96+Weekly_Cash_Flow_Summary!$B$7)) -> 0.9
A97: AR-260096 | B97: C00005 | C97: Crestwood Merchandise Inc. | D97: C | E97: 46190 | F97: {=_xlfn.IFS(G97="EM15",EOMONTH(E97,0)+15, G97="EM30",EOMONTH(E97,0)+30, G97="EM45",EOMONTH(E97,0)+45, G97="EM60",EOMONTH(E97,0)+60, G97="OA15",E97+15, G97="OA30",E97+30, G97="OA60",E97+60 )} -> 46220 | G97: OA30 | H97: 283500 | I97: =INDEX(Customer_list!$G$2:$G$21,MATCH(B97,Customer_list!$B$2:$B$21,0)) -> 0.75 | J97: Overdue | L97: =IF(J97="Collected",K97,IF(J97="Open",F97,F97+INDEX(Customer_list!$H$2:$H$21,MATCH(B97,Customer_list!$B$2:$B$21,0))*Weekly_Cash_Flow_Summary!$B$8)) -> 46245 | M97: =MIN(1,MAX(0,I97+Weekly_Cash_Flow_Summary!$B$7)) -> 0.75
A98: AR-260097 | B98: C00007 | C98: Ironstone Enterprises | D98: A | E98: 46122 | F98: {=_xlfn.IFS(G98="EM15",EOMONTH(E98,0)+15, G98="EM30",EOMONTH(E98,0)+30, G98="EM45",EOMONTH(E98,0)+45, G98="EM60",EOMONTH(E98,0)+60, G98="OA15",E98+15, G98="OA30",E98+30, G98="OA60",E98+60 )} -> 46172 | G98: EM30 | H98: 298500 | I98: =INDEX(Customer_list!$G$2:$G$21,MATCH(B98,Customer_list!$B$2:$B$21,0)) -> 0.97 | J98: Collected | K98: 46172 | L98: =IF(J98="Collected",K98,IF(J98="Open",F98,F98+INDEX(Customer_list!$H$2:$H$21,MATCH(B98,Customer_list!$B$2:$B$21,0))*Weekly_Cash_Flow_Summary!$B$8)) -> 46172 | M98: =MIN(1,MAX(0,I98+Weekly_Cash_Flow_Summary!$B$7)) -> 0.97
A99: AR-260098 | B99: C00014 | C99: Clearwater Commerce Co. | D99: A | E99: 46128 | F99: {=_xlfn.IFS(G99="EM15",EOMONTH(E99,0)+15, G99="EM30",EOMONTH(E99,0)+30, G99="EM45",EOMONTH(E99,0)+45, G99="EM60",EOMONTH(E99,0)+60, G99="OA15",E99+15, G99="OA30",E99+30, G99="OA60",E99+60 )} -> 46187 | G99: EM45 | H99: 62000 | I99: =INDEX(Customer_list!$G$2:$G$21,MATCH(B99,Customer_list!$B$2:$B$21,0)) -> 0.97 | J99: Collected | K99: 46188 | L99: =IF(J99="Collected",K99,IF(J99="Open",F99,F99+INDEX(Customer_list!$H$2:$H$21,MATCH(B99,Customer_list!$B$2:$B$21,0))*Weekly_Cash_Flow_Summary!$B$8)) -> 46188 | M99: =MIN(1,MAX(0,I99+Weekly_Cash_Flow_Summary!$B$7)) -> 0.97
A100: AR-260099 | B100: C00017 | C100: Cedarpoint Trading Inc. | D100: C | E100: 46178 | F100: {=_xlfn.IFS(G100="EM15",EOMONTH(E100,0)+15, G100="EM30",EOMONTH(E100,0)+30, G100="EM45",EOMONTH(E100,0)+45, G100="EM60",EOMONTH(E100,0)+60, G100="OA15",E100+15, G100="OA30",E100+30, G100="OA60",E100+60 )} -> 46248 | G100: EM45 | H100: 332000 | I100: =INDEX(Customer_list!$G$2:$G$21,MATCH(B100,Customer_list!$B$2:$B$21,0)) -> 0.75 | J100: Open | L100: =IF(J100="Collected",K100,IF(J100="Open",F100,F100+INDEX(Customer_list!$H$2:$H$21,MATCH(B100,Customer_list!$B$2:$B$21,0))*Weekly_Cash_Flow_Summary!$B$8)) -> 46248 | M100: =MIN(1,MAX(0,I100+Weekly_Cash_Flow_Summary!$B$7)) -> 0.75
...

Sheet AP_detail
A1: Bill_ID | B1: Vendor_Code | C1: Vendor_Name | D1: Department | E1: Bill_Date | F1: Due_Date | G1: Payment_Terms | H1: Amount | I1: Priority | J1: Status | K1: Actual_Payment_Date | L1: Expected_Payment_Date
A2: AP-260001 | B2: =VLOOKUP(C2,Vendor_list!A:D,2,0) -> V00002 | C2: Coastal Line Logistics | D2: =VLOOKUP(C2,Vendor_list!A:D,4,0) -> C | E2: 46124 | F2: {=_xlfn.IFS(G2="EM15",EOMONTH(E2,0)+15, G2="EM30",EOMONTH(E2,0)+30, G2="EM45",EOMONTH(E2,0)+45, G2="EM60",EOMONTH(E2,0)+60, G2="EM90",EOMONTH(E2,0)+90, G2="OA15",E2+15, G2="OA30",E2+30, G2="OA60",E2+60)} -> 46232 | G2: =VLOOKUP(C2,Vendor_list!A:D,3,0) -> EM90 | H2: 223500 | I2: High | J2: Overdue | L2: =IF(J2="Paid",K2,IF(J2="Open",F2,F2+INDEX(Vendor_list!$F$2:$F$16,MATCH(B2,Vendor_list!$B$2:$B$16,0))*Weekly_Cash_Flow_Summary!$B$9)) -> 46234
A3: AP-260002 | B3: =VLOOKUP(C3,Vendor_list!A:D,2,0) -> V00011 | C3: Highcastle Equipment Co. | D3: =VLOOKUP(C3,Vendor_list!A:D,4,0) -> C | E3: 46138 | F3: {=_xlfn.IFS(G3="EM15",EOMONTH(E3,0)+15, G3="EM30",EOMONTH(E3,0)+30, G3="EM45",EOMONTH(E3,0)+45, G3="EM60",EOMONTH(E3,0)+60, G3="EM90",EOMONTH(E3,0)+90, G3="OA15",E3+15, G3="OA30",E3+30, G3="OA60",E3+60)} -> 46232 | G3: =VLOOKUP(C3,Vendor_list!A:D,3,0) -> EM90 | H3: 189500 | I3: High | J3: Overdue | L3: =IF(J3="Paid",K3,IF(J3="Open",F3,F3+INDEX(Vendor_list!$F$2:$F$16,MATCH(B3,Vendor_list!$B$2:$B$16,0))*Weekly_Cash_Flow_Summary!$B$9)) -> 46234
A4: AP-260003 | B4: =VLOOKUP(C4,Vendor_list!A:D,2,0) -> V00003 | C4: Amberfield Textiles | D4: =VLOOKUP(C4,Vendor_list!A:D,4,0) -> C | E4: 46132 | F4: {=_xlfn.IFS(G4="EM15",EOMONTH(E4,0)+15, G4="EM30",EOMONTH(E4,0)+30, G4="EM45",EOMONTH(E4,0)+45, G4="EM60",EOMONTH(E4,0)+60, G4="EM90",EOMONTH(E4,0)+90, G4="OA15",E4+15, G4="OA30",E4+30, G4="OA60",E4+60)} -> 46162 | G4: =VLOOKUP(C4,Vendor_list!A:D,3,0) -> OA30 | H4: 22500 | I4: Medium | J4: Paid | K4: 46167 | L4: =IF(J4="Paid",K4,IF(J4="Open",F4,F4+INDEX(Vendor_list!$F$2:$F$16,MATCH(B4,Vendor_list!$B$2:$B$16,0))*Weekly_Cash_Flow_Summary!$B$9)) -> 46167
A5: AP-260004 | B5: =VLOOKUP(C5,Vendor_list!A:D,2,0) -> V00007 | C5: Northline Freight Services | D5: =VLOOKUP(C5,Vendor_list!A:D,4,0) -> A | E5: 46207 | F5: {=_xlfn.IFS(G5="EM15",EOMONTH(E5,0)+15, G5="EM30",EOMONTH(E5,0)+30, G5="EM45",EOMONTH(E5,0)+45, G5="EM60",EOMONTH(E5,0)+60, G5="EM90",EOMONTH(E5,0)+90, G5="OA15",E5+15, G5="OA30",E5+30, G5="OA60",E5+60)} -> 46222 | G5: =VLOOKUP(C5,Vendor_list!A:D,3,0) -> OA15 | H5: 19000 | I5: High | J5: Paid | K5: 46228 | L5: =IF(J5="Paid",K5,IF(J5="Open",F5,F5+INDEX(Vendor_list!$F$2:$F$16,MATCH(B5,Vendor_list!$B$2:$B$16,0))*Weekly_Cash_Flow_Summary!$B$9)) -> 46228
A6: AP-260005 | B6: =VLOOKUP(C6,Vendor_list!A:D,2,0) -> V00003 | C6: Amberfield Textiles | D6: =VLOOKUP(C6,Vendor_list!A:D,4,0) -> C | E6: 46151 | F6: {=_xlfn.IFS(G6="EM15",EOMONTH(E6,0)+15, G6="EM30",EOMONTH(E6,0)+30, G6="EM45",EOMONTH(E6,0)+45, G6="EM60",EOMONTH(E6,0)+60, G6="EM90",EOMONTH(E6,0)+90, G6="OA15",E6+15, G6="OA30",E6+30, G6="OA60",E6+60)} -> 46181 | G6: =VLOOKUP(C6,Vendor_list!A:D,3,0) -> OA30 | H6: 258500 | I6: Medium | J6: Paid | K6: 46198 | L6: =IF(J6="Paid",K6,IF(J6="Open",F6,F6+INDEX(Vendor_list!$F$2:$F$16,MATCH(B6,Vendor_list!$B$2:$B$16,0))*Weekly_Cash_Flow_Summary!$B$9)) -> 46198
A7: AP-260006 | B7: =VLOOKUP(C7,Vendor_list!A:D,2,0) -> V00012 | C7: Starling Print & Packaging | D7: =VLOOKUP(C7,Vendor_list!A:D,4,0) -> B | E7: 46220 | F7: {=_xlfn.IFS(G7="EM15",EOMONTH(E7,0)+15, G7="EM30",EOMONTH(E7,0)+30, G7="EM45",EOMONTH(E7,0)+45, G7="EM60",EOMONTH(E7,0)+60, G7="EM90",EOMONTH(E7,0)+90, G7="OA15",E7+15, G7="OA30",E7+30, G7="OA60",E7+60)} -> 46235 | G7: =VLOOKUP(C7,Vendor_list!A:D,3,0) -> OA15 | H7: 79000 | I7: Low | J7: Open | L7: =IF(J7="Paid",K7,IF(J7="Open",F7,F7+INDEX(Vendor_list!$F$2:$F$16,MATCH(B7,Vendor_list!$B$2:$B$16,0))*Weekly_Cash_Flow_Summary!$B$9)) -> 46235
A8: AP-260007 | B8: =VLOOKUP(C8,Vendor_list!A:D,2,0) -> V00014 | C8: Kestrel Logistics Group | D8: =VLOOKUP(C8,Vendor_list!A:D,4,0) -> C | E8: 46123 | F8: {=_xlfn.IFS(G8="EM15",EOMONTH(E8,0)+15, G8="EM30",EOMONTH(E8,0)+30, G8="EM45",EOMONTH(E8,0)+45, G8="EM60",EOMONTH(E8,0)+60, G8="EM90",EOMONTH(E8,0)+90, G8="OA15",E8+15, G8="OA30",E8+30, G8="OA60",E8+60)} -> 46138 | G8: =VLOOKUP(C8,Vendor_list!A:D,3,0) -> OA15 | H8: 88500 | I8: Low | J8: Paid | K8: 46167 | L8: =IF(J8="Paid",K8,IF(J8="Open",F8,F8+INDEX(Vendor_list!$F$2:$F$16,MATCH(B8,Vendor_list!$B$2:$B$16,0))*Weekly_Cash_Flow_Summary!$B$9)) -> 46167
A9: AP-260008 | B9: =VLOOKUP(C9,Vendor_list!A:D,2,0) -> V00011 | C9: Highcastle Equipment Co. | D9: =VLOOKUP(C9,Vendor_list!A:D,4,0) -> C | E9: 46208 | F9: {=_xlfn.IFS(G9="EM15",EOMONTH(E9,0)+15, G9="EM30",EOMONTH(E9,0)+30, G9="EM45",EOMONTH(E9,0)+45, G9="EM60",EOMONTH(E9,0)+60, G9="EM90",EOMONTH(E9,0)+90, G9="OA15",E9+15, G9="OA30",E9+30, G9="OA60",E9+60)} -> 46324 | G9: =VLOOKUP(C9,Vendor_list!A:D,3,0) -> EM90 | H9: 246500 | I9: High | J9: Open | L9: =IF(J9="Paid",K9,IF(J9="Open",F9,F9+INDEX(Vendor_list!$F$2:$F$16,MATCH(B9,Vendor_list!$B$2:$B$16,0))*Weekly_Cash_Flow_Summary!$B$9)) -> 46324
A10: AP-260009 | B10: =VLOOKUP(C10,Vendor_list!A:D,2,0) -> V00003 | C10: Amberfield Textiles | D10: =VLOOKUP(C10,Vendor_list!A:D,4,0) -> C | E10: 46136 | F10: {=_xlfn.IFS(G10="EM15",EOMONTH(E10,0)+15, G10="EM30",EOMONTH(E10,0)+30, G10="EM45",EOMONTH(E10,0)+45, G10="EM60",EOMONTH(E10,0)+60, G10="EM90",EOMONTH(E10,0)+90, G10="OA15",E10+15, G10="OA30",E10+30, G10="OA60",E10+60)} -> 46166 | G10: =VLOOKUP(C10,Vendor_list!A:D,3,0) -> OA30 | H10: 230000 | I10: Medium | J10: Paid | K10: 46183 | L10: =IF(J10="Paid",K10,IF(J10="Open",F10,F10+INDEX(Vendor_list!$F$2:$F$16,MATCH(B10,Vendor_list!$B$2:$B$16,0))*Weekly_Cash_Flow_Summary!$B$9)) -> 46183
A11: AP-260010 | B11: =VLOOKUP(C11,Vendor_list!A:D,2,0) -> V00001 | C11: Granite Peak Manufacturing | D11: =VLOOKUP(C11,Vendor_list!A:D,4,0) -> A | E11: 46151 | F11: {=_xlfn.IFS(G11="EM15",EOMONTH(E11,0)+15, G11="EM30",EOMONTH(E11,0)+30, G11="EM45",EOMONTH(E11,0)+45, G11="EM60",EOMONTH(E11,0)+60, G11="EM90",EOMONTH(E11,0)+90, G11="OA15",E11+15, G11="OA30",E11+30, G11="OA60",E11+60)} -> 46181 | G11: =VLOOKUP(C11,Vendor_list!A:D,3,0) -> OA30 | H11: 243500 | I11: High | J11: Paid | K11: 46183 | L11: =IF(J11="Paid",K11,IF(J11="Open",F11,F11+INDEX(Vendor_list!$F$2:$F$16,MATCH(B11,Vendor_list!$B$2:$B$16,0))*Weekly_Cash_Flow_Summary!$B$9)) -> 46183
A12: AP-260011 | B12: =VLOOKUP(C12,Vendor_list!A:D,2,0) -> V00009 | C12: Bayridge Fabrication Inc. | D12: =VLOOKUP(C12,Vendor_list!A:D,4,0) -> B | E12: 46124 | F12: {=_xlfn.IFS(G12="EM15",EOMONTH(E12,0)+15, G12="EM30",EOMONTH(E12,0)+30, G12="EM45",EOMONTH(E12,0)+45, G12="EM60",EOMONTH(E12,0)+60, G12="EM90",EOMONTH(E12,0)+90, G12="OA15",E12+15, G12="OA30",E12+30, G12="OA60",E12+60)} -> 46184 | G12: =VLOOKUP(C12,Vendor_list!A:D,3,0) -> OA60 | H12: 101000 | I12: Medium | J12: Paid | K12: 46198 | L12: =IF(J12="Paid",K12,IF(J12="Open",F12,F12+INDEX(Vendor_list!$F$2:$F$16,MATCH(B12,Vendor_list!$B$2:$B$16,0))*Weekly_Cash_Flow_Summary!$B$9)) -> 46198
A13: AP-260012 | B13: =VLOOKUP(C13,Vendor_list!A:D,2,0) -> V00004 | C13: Redwood Packaging Co. | D13: =VLOOKUP(C13,Vendor_list!A:D,4,0) -> B | E13: 46158 | F13: {=_xlfn.IFS(G13="EM15",EOMONTH(E13,0)+15, G13="EM30",EOMONTH(E13,0)+30, G13="EM45",EOMONTH(E13,0)+45, G13="EM60",EOMONTH(E13,0)+60, G13="EM90",EOMONTH(E13,0)+90, G13="OA15",E13+15, G13="OA30",E13+30, G13="OA60",E13+60)} -> 46263 | G13: =VLOOKUP(C13,Vendor_list!A:D,3,0) -> EM90 | H13: 192000 | I13: Medium | J13: Open | L13: =IF(J13="Paid",K13,IF(J13="Open",F13,F13+INDEX(Vendor_list!$F$2:$F$16,MATCH(B13,Vendor_list!$B$2:$B$16,0))*Weekly_Cash_Flow_Summary!$B$9)) -> 46263
A14: AP-260013 | B14: =VLOOKUP(C14,Vendor_list!A:D,2,0) -> V00006 | C14: Vantage Point Materials | D14: =VLOOKUP(C14,Vendor_list!A:D,4,0) -> B | E14: 46230 | F14: {=_xlfn.IFS(G14="EM15",EOMONTH(E14,0)+15, G14="EM30",EOMONTH(E14,0)+30, G14="EM45",EOMONTH(E14,0)+45, G14="EM60",EOMONTH(E14,0)+60, G14="EM90",EOMONTH(E14,0)+90, G14="OA15",E14+15, G14="OA30",E14+30, G14="OA60",E14+60)} -> 46245 | G14: =VLOOKUP(C14,Vendor_list!A:D,3,0) -> OA15 | H14: 46500 | I14: Medium | J14: Open | L14: =IF(J14="Paid",K14,IF(J14="Open",F14,F14+INDEX(Vendor_list!$F$2:$F$16,MATCH(B14,Vendor_list!$B$2:$B$16,0))*Weekly_Cash_Flow_Summary!$B$9)) -> 46245
A15: AP-260014 | B15: =VLOOKUP(C15,Vendor_list!A:D,2,0) -> V00002 | C15: Coastal Line Logistics | D15: =VLOOKUP(C15,Vendor_list!A:D,4,0) -> C | E15: 46205 | F15: {=_xlfn.IFS(G15="EM15",EOMONTH(E15,0)+15, G15="EM30",EOMONTH(E15,0)+30, G15="EM45",EOMONTH(E15,0)+45, G15="EM60",EOMONTH(E15,0)+60, G15="EM90",EOMONTH(E15,0)+90, G15="OA15",E15+15, G15="OA30",E15+30, G15="OA60",E15+60)} -> 46324 | G15: =VLOOKUP(C15,Vendor_list!A:D,3,0) -> EM90 | H15: 95000 | I15: High | J15: Open | L15: =IF(J15="Paid",K15,IF(J15="Open",F15,F15+INDEX(Vendor_list!$F$2:$F$16,MATCH(B15,Vendor_list!$B$2:$B$16,0))*Weekly_Cash_Flow_Summary!$B$9)) -> 46324
A16: AP-260015 | B16: =VLOOKUP(C16,Vendor_list!A:D,2,0) -> V00005 | C16: Summit Ridge Components | D16: =VLOOKUP(C16,Vendor_list!A:D,4,0) -> A | E16: 46231 | F16: {=_xlfn.IFS(G16="EM15",EOMONTH(E16,0)+15, G16="EM30",EOMONTH(E16,0)+30, G16="EM45",EOMONTH(E16,0)+45, G16="EM60",EOMONTH(E16,0)+60, G16="EM90",EOMONTH(E16,0)+90, G16="OA15",E16+15, G16="OA30",E16+30, G16="OA60",E16+60)} -> 46249 | G16: =VLOOKUP(C16,Vendor_list!A:D,3,0) -> EM15 | H16: 144500 | I16: High | J16: Open | L16: =IF(J16="Paid",K16,IF(J16="Open",F16,F16+INDEX(Vendor_list!$F$2:$F$16,MATCH(B16,Vendor_list!$B$2:$B$16,0))*Weekly_Cash_Flow_Summary!$B$9)) -> 46249
A17: AP-260016 | B17: =VLOOKUP(C17,Vendor_list!A:D,2,0) -> V00010 | C17: Timberline Wholesale Goods | D17: =VLOOKUP(C17,Vendor_list!A:D,4,0) -> C | E17: 46223 | F17: {=_xlfn.IFS(G17="EM15",EOMONTH(E17,0)+15, G17="EM30",EOMONTH(E17,0)+30, G17="EM45",EOMONTH(E17,0)+45, G17="EM60",EOMONTH(E17,0)+60, G17="EM90",EOMONTH(E17,0)+90, G17="OA15",E17+15, G17="OA30",E17+30, G17="OA60",E17+60)} -> 46238 | G17: =VLOOKUP(C17,Vendor_list!A:D,3,0) -> OA15 | H17: 247500 | I17: Low | J17: Open | L17: =IF(J17="Paid",K17,IF(J17="Open",F17,F17+INDEX(Vendor_list!$F$2:$F$16,MATCH(B17,Vendor_list!$B$2:$B$16,0))*Weekly_Cash_Flow_Summary!$B$9)) -> 46238
A18: AP-260017 | B18: =VLOOKUP(C18,Vendor_list!A:D,2,0) -> V00004 | C18: Redwood Packaging Co. | D18: =VLOOKUP(C18,Vendor_list!A:D,4,0) -> B | E18: 46197 | F18: {=_xlfn.IFS(G18="EM15",EOMONTH(E18,0)+15, G18="EM30",EOMONTH(E18,0)+30, G18="EM45",EOMONTH(E18,0)+45, G18="EM60",EOMONTH(E18,0)+60, G18="EM90",EOMONTH(E18,0)+90, G18="OA15",E18+15, G18="OA30",E18+30, G18="OA60",E18+60)} -> 46293 | G18: =VLOOKUP(C18,Vendor_list!A:D,3,0) -> EM90 | H18: 119500 | I18: Medium | J18: Open | L18: =IF(J18="Paid",K18,IF(J18="Open",F18,F18+INDEX(Vendor_list!$F$2:$F$16,MATCH(B18,Vendor_list!$B$2:$B$16,0))*Weekly_Cash_Flow_Summary!$B$9)) -> 46293
A19: AP-260018 | B19: =VLOOKUP(C19,Vendor_list!A:D,2,0) -> V00008 | C19: Copperfield Industrial Supply | D19: =VLOOKUP(C19,Vendor_list!A:D,4,0) -> C | E19: 46173 | F19: {=_xlfn.IFS(G19="EM15",EOMONTH(E19,0)+15, G19="EM30",EOMONTH(E19,0)+30, G19="EM45",EOMONTH(E19,0)+45, G19="EM60",EOMONTH(E19,0)+60, G19="EM90",EOMONTH(E19,0)+90, G19="OA15",E19+15, G19="OA30",E19+30, G19="OA60",E19+60)} -> 46233 | G19: =VLOOKUP(C19,Vendor_list!A:D,3,0) -> EM60 | H19: 130000 | I19: Medium | J19: Open | L19: =IF(J19="Paid",K19,IF(J19="Open",F19,F19+INDEX(Vendor_list!$F$2:$F$16,MATCH(B19,Vendor_list!$B$2:$B$16,0))*Weekly_Cash_Flow_Summary!$B$9)) -> 46233
A20: AP-260019 | B20: =VLOOKUP(C20,Vendor_list!A:D,2,0) -> V00009 | C20: Bayridge Fabrication Inc. | D20: =VLOOKUP(C20,Vendor_list!A:D,4,0) -> B | E20: 46182 | F20: {=_xlfn.IFS(G20="EM15",EOMONTH(E20,0)+15, G20="EM30",EOMONTH(E20,0)+30, G20="EM45",EOMONTH(E20,0)+45, G20="EM60",EOMONTH(E20,0)+60, G20="EM90",EOMONTH(E20,0)+90, G20="OA15",E20+15, G20="OA30",E20+30, G20="OA60",E20+60)} -> 46242 | G20: =VLOOKUP(C20,Vendor_list!A:D,3,0) -> OA60 | H20: 107500 | I20: Medium | J20: Open | L20: =IF(J20="Paid",K20,IF(J20="Open",F20,F20+INDEX(Vendor_list!$F$2:$F$16,MATCH(B20,Vendor_list!$B$2:$B$16,0))*Weekly_Cash_Flow_Summary!$B$9)) -> 46242
A21: AP-260020 | B21: =VLOOKUP(C21,Vendor_list!A:D,2,0) -> V00002 | C21: Coastal Line Logistics | D21: =VLOOKUP(C21,Vendor_list!A:D,4,0) -> C | E21: 46162 | F21: {=_xlfn.IFS(G21="EM15",EOMONTH(E21,0)+15, G21="EM30",EOMONTH(E21,0)+30, G21="EM45",EOMONTH(E21,0)+45, G21="EM60",EOMONTH(E21,0)+60, G21="EM90",EOMONTH(E21,0)+90, G21="OA15",E21+15, G21="OA30",E21+30, G21="OA60",E21+60)} -> 46263 | G21: =VLOOKUP(C21,Vendor_list!A:D,3,0) -> EM90 | H21: 23000 | I21: High | J21: Open | L21: =IF(J21="Paid",K21,IF(J21="Open",F21,F21+INDEX(Vendor_list!$F$2:$F$16,MATCH(B21,Vendor_list!$B$2:$B$16,0))*Weekly_Cash_Flow_Summary!$B$9)) -> 46263
A22: AP-260021 | B22: =VLOOKUP(C22,Vendor_list!A:D,2,0) -> V00009 | C22: Bayridge Fabrication Inc. | D22: =VLOOKUP(C22,Vendor_list!A:D,4,0) -> B | E22: 46162 | F22: {=_xlfn.IFS(G22="EM15",EOMONTH(E22,0)+15, G22="EM30",EOMONTH(E22,0)+30, G22="EM45",EOMONTH(E22,0)+45, G22="EM60",EOMONTH(E22,0)+60, G22="EM90",EOMONTH(E22,0)+90, G22="OA15",E22+15, G22="OA30",E22+30, G22="OA60",E22+60)} -> 46222 | G22: =VLOOKUP(C22,Vendor_list!A:D,3,0) -> OA60 | H22: 138500 | I22: Medium | J22: Overdue | L22: =IF(J22="Paid",K22,IF(J22="Open",F22,F22+INDEX(Vendor_list!$F$2:$F$16,MATCH(B22,Vendor_list!$B$2:$B$16,0))*Weekly_Cash_Flow_Summary!$B$9)) -> 46229
A23: AP-260022 | B23: =VLOOKUP(C23,Vendor_list!A:D,2,0) -> V00003 | C23: Amberfield Textiles | D23: =VLOOKUP(C23,Vendor_list!A:D,4,0) -> C | E23: 46177 | F23: {=_xlfn.IFS(G23="EM15",EOMONTH(E23,0)+15, G23="EM30",EOMONTH(E23,0)+30, G23="EM45",EOMONTH(E23,0)+45, G23="EM60",EOMONTH(E23,0)+60, G23="EM90",EOMONTH(E23,0)+90, G23="OA15",E23+15, G23="OA30",E23+30, G23="OA60",E23+60)} -> 46207 | G23: =VLOOKUP(C23,Vendor_list!A:D,3,0) -> OA30 | H23: 289500 | I23: Medium | J23: Overdue | L23: =IF(J23="Paid",K23,IF(J23="Open",F23,F23+INDEX(Vendor_list!$F$2:$F$16,MATCH(B23,Vendor_list!$B$2:$B$16,0))*Weekly_Cash_Flow_Summary!$B$9)) -> 46214
A24: AP-260023 | B24: =VLOOKUP(C24,Vendor_list!A:D,2,0) -> V00010 | C24: Timberline Wholesale Goods | D24: =VLOOKUP(C24,Vendor_list!A:D,4,0) -> C | E24: 46164 | F24: {=_xlfn.IFS(G24="EM15",EOMONTH(E24,0)+15, G24="EM30",EOMONTH(E24,0)+30, G24="EM45",EOMONTH(E24,0)+45, G24="EM60",EOMONTH(E24,0)+60, G24="EM90",EOMONTH(E24,0)+90, G24="OA15",E24+15, G24="OA30",E24+30, G24="OA60",E24+60)} -> 46179 | G24: =VLOOKUP(C24,Vendor_list!A:D,3,0) -> OA15 | H24: 291500 | I24: Low | J24: Paid | K24: 46198 | L24: =IF(J24="Paid",K24,IF(J24="Open",F24,F24+INDEX(Vendor_list!$F$2:$F$16,MATCH(B24,Vendor_list!$B$2:$B$16,0))*Weekly_Cash_Flow_Summary!$B$9)) -> 46198
A25: AP-260024 | B25: =VLOOKUP(C25,Vendor_list!A:D,2,0) -> V00002 | C25: Coastal Line Logistics | D25: =VLOOKUP(C25,Vendor_list!A:D,4,0) -> C | E25: 46153 | F25: {=_xlfn.IFS(G25="EM15",EOMONTH(E25,0)+15, G25="EM30",EOMONTH(E25,0)+30, G25="EM45",EOMONTH(E25,0)+45, G25="EM60",EOMONTH(E25,0)+60, G25="EM90",EOMONTH(E25,0)+90, G25="OA15",E25+15, G25="OA30",E25+30, G25="OA60",E25+60)} -> 46263 | G25: =VLOOKUP(C25,Vendor_list!A:D,3,0) -> EM90 | H25: 276000 | I25: High | J25: Open | L25: =IF(J25="Paid",K25,IF(J25="Open",F25,F25+INDEX(Vendor_list!$F$2:$F$16,MATCH(B25,Vendor_list!$B$2:$B$16,0))*Weekly_Cash_Flow_Summary!$B$9)) -> 46263
A26: AP-260025 | B26: =VLOOKUP(C26,Vendor_list!A:D,2,0) -> V00005 | C26: Summit Ridge Components | D26: =VLOOKUP(C26,Vendor_list!A:D,4,0) -> A | E26: 46205 | F26: {=_xlfn.IFS(G26="EM15",EOMONTH(E26,0)+15, G26="EM30",EOMONTH(E26,0)+30, G26="EM45",EOMONTH(E26,0)+45, G26="EM60",EOMONTH(E26,0)+60, G26="EM90",EOMONTH(E26,0)+90, G26="OA15",E26+15, G26="OA30",E26+30, G26="OA60",E26+60)} -> 46249 | G26: =VLOOKUP(C26,Vendor_list!A:D,3,0) -> EM15 | H26: 213000 | I26: High | J26: Open | L26: =IF(J26="Paid",K26,IF(J26="Open",F26,F26+INDEX(Vendor_list!$F$2:$F$16,MATCH(B26,Vendor_list!$B$2:$B$16,0))*Weekly_Cash_Flow_Summary!$B$9)) -> 46249
A27: AP-260026 | B27: =VLOOKUP(C27,Vendor_list!A:D,2,0) -> V00015 | C27: Marbleton Supply Chain Co. | D27: =VLOOKUP(C27,Vendor_list!A:D,4,0) -> C | E27: 46167 | F27: {=_xlfn.IFS(G27="EM15",EOMONTH(E27,0)+15, G27="EM30",EOMONTH(E27,0)+30, G27="EM45",EOMONTH(E27,0)+45, G27="EM60",EOMONTH(E27,0)+60, G27="EM90",EOMONTH(E27,0)+90, G27="OA15",E27+15, G27="OA30",E27+30, G27="OA60",E27+60)} -> 46227 | G27: =VLOOKUP(C27,Vendor_list!A:D,3,0) -> OA60 | H27: 283500 | I27: Low | J27: Overdue | L27: =IF(J27="Paid",K27,IF(J27="Open",F27,F27+INDEX(Vendor_list!$F$2:$F$16,MATCH(B27,Vendor_list!$B$2:$B$16,0))*Weekly_Cash_Flow_Summary!$B$9)) -> 46242
A28: AP-260027 | B28: =VLOOKUP(C28,Vendor_list!A:D,2,0) -> V00009 | C28: Bayridge Fabrication Inc. | D28: =VLOOKUP(C28,Vendor_list!A:D,4,0) -> B | E28: 46181 | F28: {=_xlfn.IFS(G28="EM15",EOMONTH(E28,0)+15, G28="EM30",EOMONTH(E28,0)+30, G28="EM45",EOMONTH(E28,0)+45, G28="EM60",EOMONTH(E28,0)+60, G28="EM90",EOMONTH(E28,0)+90, G28="OA15",E28+15, G28="OA30",E28+30, G28="OA60",E28+60)} -> 46241 | G28: =VLOOKUP(C28,Vendor_list!A:D,3,0) -> OA60 | H28: 278000 | I28: Medium | J28: Open | L28: =IF(J28="Paid",K28,IF(J28="Open",F28,F28+INDEX(Vendor_list!$F$2:$F$16,MATCH(B28,Vendor_list!$B$2:$B$16,0))*Weekly_Cash_Flow_Summary!$B$9)) -> 46241
A29: AP-260028 | B29: =VLOOKUP(C29,Vendor_list!A:D,2,0) -> V00001 | C29: Granite Peak Manufacturing | D29: =VLOOKUP(C29,Vendor_list!A:D,4,0) -> A | E29: 46211 | F29: {=_xlfn.IFS(G29="EM15",EOMONTH(E29,0)+15, G29="EM30",EOMONTH(E29,0)+30, G29="EM45",EOMONTH(E29,0)+45, G29="EM60",EOMONTH(E29,0)+60, G29="EM90",EOMONTH(E29,0)+90, G29="OA15",E29+15, G29="OA30",E29+30, G29="OA60",E29+60)} -> 46241 | G29: =VLOOKUP(C29,Vendor_list!A:D,3,0) -> OA30 | H29: 50500 | I29: High | J29: Open | L29: =IF(J29="Paid",K29,IF(J29="Open",F29,F29+INDEX(Vendor_list!$F$2:$F$16,MATCH(B29,Vendor_list!$B$2:$B$16,0))*Weekly_Cash_Flow_Summary!$B$9)) -> 46241
A30: AP-260029 | B30: =VLOOKUP(C30,Vendor_list!A:D,2,0) -> V00004 | C30: Redwood Packaging Co. | D30: =VLOOKUP(C30,Vendor_list!A:D,4,0) -> B | E30: 46193 | F30: {=_xlfn.IFS(G30="EM15",EOMONTH(E30,0)+15, G30="EM30",EOMONTH(E30,0)+30, G30="EM45",EOMONTH(E30,0)+45, G30="EM60",EOMONTH(E30,0)+60, G30="EM90",EOMONTH(E30,0)+90, G30="OA15",E30+15, G30="OA30",E30+30, G30="OA60",E30+60)} -> 46293 | G30: =VLOOKUP(C30,Vendor_list!A:D,3,0) -> EM90 | H30: 272500 | I30: Medium | J30: Open | L30: =IF(J30="Paid",K30,IF(J30="Open",F30,F30+INDEX(Vendor_list!$F$2:$F$16,MATCH(B30,Vendor_list!$B$2:$B$16,0))*Weekly_Cash_Flow_Summary!$B$9)) -> 46293
A31: AP-260030 | B31: =VLOOKUP(C31,Vendor_list!A:D,2,0) -> V00014 | C31: Kestrel Logistics Group | D31: =VLOOKUP(C31,Vendor_list!A:D,4,0) -> C | E31: 46118 | F31: {=_xlfn.IFS(G31="EM15",EOMONTH(E31,0)+15, G31="EM30",EOMONTH(E31,0)+30, G31="EM45",EOMONTH(E31,0)+45, G31="EM60",EOMONTH(E31,0)+60, G31="EM90",EOMONTH(E31,0)+90, G31="OA15",E31+15, G31="OA30",E31+30, G31="OA60",E31+60)} -> 46133 | G31: =VLOOKUP(C31,Vendor_list!A:D,3,0) -> OA15 | H31: 92000 | I31: Low | J31: Paid | K31: 46152 | L31: =IF(J31="Paid",K31,IF(J31="Open",F31,F31+INDEX(Vendor_list!$F$2:$F$16,MATCH(B31,Vendor_list!$B$2:$B$16,0))*Weekly_Cash_Flow_Summary!$B$9)) -> 46152
A32: AP-260031 | B32: =VLOOKUP(C32,Vendor_list!A:D,2,0) -> V00006 | C32: Vantage Point Materials | D32: =VLOOKUP(C32,Vendor_list!A:D,4,0) -> B | E32: 46193 | F32: {=_xlfn.IFS(G32="EM15",EOMONTH(E32,0)+15, G32="EM30",EOMONTH(E32,0)+30, G32="EM45",EOMONTH(E32,0)+45, G32="EM60",EOMONTH(E32,0)+60, G32="EM90",EOMONTH(E32,0)+90, G32="OA15",E32+15, G32="OA30",E32+30, G32="OA60",E32+60)} -> 46208 | G32: =VLOOKUP(C32,Vendor_list!A:D,3,0) -> OA15 | H32: 87500 | I32: Medium | J32: Paid | K32: 46213 | L32: =IF(J32="Paid",K32,IF(J32="Open",F32,F32+INDEX(Vendor_list!$F$2:$F$16,MATCH(B32,Vendor_list!$B$2:$B$16,0))*Weekly_Cash_Flow_Summary!$B$9)) -> 46213
A33: AP-260032 | B33: =VLOOKUP(C33,Vendor_list!A:D,2,0) -> V00012 | C33: Starling Print & Packaging | D33: =VLOOKUP(C33,Vendor_list!A:D,4,0) -> B | E33: 46145 | F33: {=_xlfn.IFS(G33="EM15",EOMONTH(E33,0)+15, G33="EM30",EOMONTH(E33,0)+30, G33="EM45",EOMONTH(E33,0)+45, G33="EM60",EOMONTH(E33,0)+60, G33="EM90",EOMONTH(E33,0)+90, G33="OA15",E33+15, G33="OA30",E33+30, G33="OA60",E33+60)} -> 46160 | G33: =VLOOKUP(C33,Vendor_list!A:D,3,0) -> OA15 | H33: 178000 | I33: Low | J33: Paid | K33: 46183 | L33: =IF(J33="Paid",K33,IF(J33="Open",F33,F33+INDEX(Vendor_list!$F$2:$F$16,MATCH(B33,Vendor_list!$B$2:$B$16,0))*Weekly_Cash_Flow_Summary!$B$9)) -> 46183
A34: AP-260033 | B34: =VLOOKUP(C34,Vendor_list!A:D,2,0) -> V00006 | C34: Vantage Point Materials | D34: =VLOOKUP(C34,Vendor_list!A:D,4,0) -> B | E34: 46118 | F34: {=_xlfn.IFS(G34="EM15",EOMONTH(E34,0)+15, G34="EM30",EOMONTH(E34,0)+30, G34="EM45",EOMONTH(E34,0)+45, G34="EM60",EOMONTH(E34,0)+60, G34="EM90",EOMONTH(E34,0)+90, G34="OA15",E34+15, G34="OA30",E34+30, G34="OA60",E34+60)} -> 46133 | G34: =VLOOKUP(C34,Vendor_list!A:D,3,0) -> OA15 | H34: 26000 | I34: Medium | J34: Paid | K34: 46152 | L34: =IF(J34="Paid",K34,IF(J34="Open",F34,F34+INDEX(Vendor_list!$F$2:$F$16,MATCH(B34,Vendor_list!$B$2:$B$16,0))*Weekly_Cash_Flow_Summary!$B$9)) -> 46152
A35: AP-260034 | B35: =VLOOKUP(C35,Vendor_list!A:D,2,0) -> V00002 | C35: Coastal Line Logistics | D35: =VLOOKUP(C35,Vendor_list!A:D,4,0) -> C | E35: 46142 | F35: {=_xlfn.IFS(G35="EM15",EOMONTH(E35,0)+15, G35="EM30",EOMONTH(E35,0)+30, G35="EM45",EOMONTH(E35,0)+45, G35="EM60",EOMONTH(E35,0)+60, G35="EM90",EOMONTH(E35,0)+90, G35="OA15",E35+15, G35="OA30",E35+30, G35="OA60",E35+60)} -> 46232 | G35: =VLOOKUP(C35,Vendor_list!A:D,3,0) -> EM90 | H35: 69500 | I35: High | J35: Overdue | L35: =IF(J35="Paid",K35,IF(J35="Open",F35,F35+INDEX(Vendor_list!$F$2:$F$16,MATCH(B35,Vendor_list!$B$2:$B$16,0))*Weekly_Cash_Flow_Summary!$B$9)) -> 46234
A36: AP-260035 | B36: =VLOOKUP(C36,Vendor_list!A:D,2,0) -> V00013 | C36: Ashford Raw Materials Ltd. | D36: =VLOOKUP(C36,Vendor_list!A:D,4,0) -> B | E36: 46178 | F36: {=_xlfn.IFS(G36="EM15",EOMONTH(E36,0)+15, G36="EM30",EOMONTH(E36,0)+30, G36="EM45",EOMONTH(E36,0)+45, G36="EM60",EOMONTH(E36,0)+60, G36="EM90",EOMONTH(E36,0)+90, G36="OA15",E36+15, G36="OA30",E36+30, G36="OA60",E36+60)} -> 46208 | G36: =VLOOKUP(C36,Vendor_list!A:D,3,0) -> OA30 | H36: 59500 | I36: Low | J36: Paid | K36: 46228 | L36: =IF(J36="Paid",K36,IF(J36="Open",F36,F36+INDEX(Vendor_list!$F$2:$F$16,MATCH(B36,Vendor_list!$B$2:$B$16,0))*Weekly_Cash_Flow_Summary!$B$9)) -> 46228
A37: AP-260036 | B37: =VLOOKUP(C37,Vendor_list!A:D,2,0) -> V00011 | C37: Highcastle Equipment Co. | D37: =VLOOKUP(C37,Vendor_list!A:D,4,0) -> C | E37: 46203 | F37: {=_xlfn.IFS(G37="EM15",EOMONTH(E37,0)+15, G37="EM30",EOMONTH(E37,0)+30, G37="EM45",EOMONTH(E37,0)+45, G37="EM60",EOMONTH(E37,0)+60, G37="EM90",EOMONTH(E37,0)+90, G37="OA15",E37+15, G37="OA30",E37+30, G37="OA60",E37+60)} -> 46293 | G37: =VLOOKUP(C37,Vendor_list!A:D,3,0) -> EM90 | H37: 192000 | I37: High | J37: Open | L37: =IF(J37="Paid",K37,IF(J37="Open",F37,F37+INDEX(Vendor_list!$F$2:$F$16,MATCH(B37,Vendor_list!$B$2:$B$16,0))*Weekly_Cash_Flow_Summary!$B$9)) -> 46293
A38: AP-260037 | B38: =VLOOKUP(C38,Vendor_list!A:D,2,0) -> V00007 | C38: Northline Freight Services | D38: =VLOOKUP(C38,Vendor_list!A:D,4,0) -> A | E38: 46114 | F38: {=_xlfn.IFS(G38="EM15",EOMONTH(E38,0)+15, G38="EM30",EOMONTH(E38,0)+30, G38="EM45",EOMONTH(E38,0)+45, G38="EM60",EOMONTH(E38,0)+60, G38="EM90",EOMONTH(E38,0)+90, G38="OA15",E38+15, G38="OA30",E38+30, G38="OA60",E38+60)} -> 46129 | G38: =VLOOKUP(C38,Vendor_list!A:D,3,0) -> OA15 | H38: 128500 | I38: High | J38: Paid | K38: 46137 | L38: =IF(J38="Paid",K38,IF(J38="Open",F38,F38+INDEX(Vendor_list!$F$2:$F$16,MATCH(B38,Vendor_list!$B$2:$B$16,0))*Weekly_Cash_Flow_Summary!$B$9)) -> 46137
A39: AP-260038 | B39: =VLOOKUP(C39,Vendor_list!A:D,2,0) -> V00014 | C39: Kestrel Logistics Group | D39: =VLOOKUP(C39,Vendor_list!A:D,4,0) -> C | E39: 46186 | F39: {=_xlfn.IFS(G39="EM15",EOMONTH(E39,0)+15, G39="EM30",EOMONTH(E39,0)+30, G39="EM45",EOMONTH(E39,0)+45, G39="EM60",EOMONTH(E39,0)+60, G39="EM90",EOMONTH(E39,0)+90, G39="OA15",E39+15, G39="OA30",E39+30, G39="OA60",E39+60)} -> 46201 | G39: =VLOOKUP(C39,Vendor_list!A:D,3,0) -> OA15 | H39: 206500 | I39: Low | J39: Paid | K39: 46228 | L39: =IF(J39="Paid",K39,IF(J39="Open",F39,F39+INDEX(Vendor_list!$F$2:$F$16,MATCH(B39,Vendor_list!$B$2:$B$16,0))*Weekly_Cash_Flow_Summary!$B$9)) -> 46228
A40: AP-260039 | B40: =VLOOKUP(C40,Vendor_list!A:D,2,0) -> V00004 | C40: Redwood Packaging Co. | D40: =VLOOKUP(C40,Vendor_list!A:D,4,0) -> B | E40: 46172 | F40: {=_xlfn.IFS(G40="EM15",EOMONTH(E40,0)+15, G40="EM30",EOMONTH(E40,0)+30, G40="EM45",EOMONTH(E40,0)+45, G40="EM60",EOMONTH(E40,0)+60, G40="EM90",EOMONTH(E40,0)+90, G40="OA15",E40+15, G40="OA30",E40+30, G40="OA60",E40+60)} -> 46263 | G40: =VLOOKUP(C40,Vendor_list!A:D,3,0) -> EM90 | H40: 258500 | I40: Medium | J40: Open | L40: =IF(J40="Paid",K40,IF(J40="Open",F40,F40+INDEX(Vendor_list!$F$2:$F$16,MATCH(B40,Vendor_list!$B$2:$B$16,0))*Weekly_Cash_Flow_Summary!$B$9)) -> 46263
A41: AP-260040 | B41: =VLOOKUP(C41,Vendor_list!A:D,2,0) -> V00005 | C41: Summit Ridge Components | D41: =VLOOKUP(C41,Vendor_list!A:D,4,0) -> A | E41: 46220 | F41: {=_xlfn.IFS(G41="EM15",EOMONTH(E41,0)+15, G41="EM30",EOMONTH(E41,0)+30, G41="EM45",EOMONTH(E41,0)+45, G41="EM60",EOMONTH(E41,0)+60, G41="EM90",EOMONTH(E41,0)+90, G41="OA15",E41+15, G41="OA30",E41+30, G41="OA60",E41+60)} -> 46249 | G41: =VLOOKUP(C41,Vendor_list!A:D,3,0) -> EM15 | H41: 203000 | I41: High | J41: Open | L41: =IF(J41="Paid",K41,IF(J41="Open",F41,F41+INDEX(Vendor_list!$F$2:$F$16,MATCH(B41,Vendor_list!$B$2:$B$16,0))*Weekly_Cash_Flow_Summary!$B$9)) -> 46249
A42: AP-260041 | B42: =VLOOKUP(C42,Vendor_list!A:D,2,0) -> V00003 | C42: Amberfield Textiles | D42: =VLOOKUP(C42,Vendor_list!A:D,4,0) -> C | E42: 46141 | F42: {=_xlfn.IFS(G42="EM15",EOMONTH(E42,0)+15, G42="EM30",EOMONTH(E42,0)+30, G42="EM45",EOMONTH(E42,0)+45, G42="EM60",EOMONTH(E42,0)+60, G42="EM90",EOMONTH(E42,0)+90, G42="OA15",E42+15, G42="OA30",E42+30, G42="OA60",E42+60)} -> 46171 | G42: =VLOOKUP(C42,Vendor_list!A:D,3,0) -> OA30 | H42: 186500 | I42: Medium | J42: Paid | K42: 46183 | L42: =IF(J42="Paid",K42,IF(J42="Open",F42,F42+INDEX(Vendor_list!$F$2:$F$16,MATCH(B42,Vendor_list!$B$2:$B$16,0))*Weekly_Cash_Flow_Summary!$B$9)) -> 46183
A43: AP-260042 | B43: =VLOOKUP(C43,Vendor_list!A:D,2,0) -> V00008 | C43: Copperfield Industrial Supply | D43: =VLOOKUP(C43,Vendor_list!A:D,4,0) -> C | E43: 46119 | F43: {=_xlfn.IFS(G43="EM15",EOMONTH(E43,0)+15, G43="EM30",EOMONTH(E43,0)+30, G43="EM45",EOMONTH(E43,0)+45, G43="EM60",EOMONTH(E43,0)+60, G43="EM90",EOMONTH(E43,0)+90, G43="OA15",E43+15, G43="OA30",E43+30, G43="OA60",E43+60)} -> 46202 | G43: =VLOOKUP(C43,Vendor_list!A:D,3,0) -> EM60 | H43: 219000 | I43: Medium | J43: Paid | K43: 46213 | L43: =IF(J43="Paid",K43,IF(J43="Open",F43,F43+INDEX(Vendor_list!$F$2:$F$16,MATCH(B43,Vendor_list!$B$2:$B$16,0))*Weekly_Cash_Flow_Summary!$B$9)) -> 46213
A44: AP-260043 | B44: =VLOOKUP(C44,Vendor_list!A:D,2,0) -> V00005 | C44: Summit Ridge Components | D44: =VLOOKUP(C44,Vendor_list!A:D,4,0) -> A | E44: 46161 | F44: {=_xlfn.IFS(G44="EM15",EOMONTH(E44,0)+15, G44="EM30",EOMONTH(E44,0)+30, G44="EM45",EOMONTH(E44,0)+45, G44="EM60",EOMONTH(E44,0)+60, G44="EM90",EOMONTH(E44,0)+90, G44="OA15",E44+15, G44="OA30",E44+30, G44="OA60",E44+60)} -> 46188 | G44: =VLOOKUP(C44,Vendor_list!A:D,3,0) -> EM15 | H44: 178500 | I44: High | J44: Paid | K44: 46198 | L44: =IF(J44="Paid",K44,IF(J44="Open",F44,F44+INDEX(Vendor_list!$F$2:$F$16,MATCH(B44,Vendor_list!$B$2:$B$16,0))*Weekly_Cash_Flow_Summary!$B$9)) -> 46198
A45: AP-260044 | B45: =VLOOKUP(C45,Vendor_list!A:D,2,0) -> V00004 | C45: Redwood Packaging Co. | D45: =VLOOKUP(C45,Vendor_list!A:D,4,0) -> B | E45: 46142 | F45: {=_xlfn.IFS(G45="EM15",EOMONTH(E45,0)+15, G45="EM30",EOMONTH(E45,0)+30, G45="EM45",EOMONTH(E45,0)+45, G45="EM60",EOMONTH(E45,0)+60, G45="EM90",EOMONTH(E45,0)+90, G45="OA15",E45+15, G45="OA30",E45+30, G45="OA60",E45+60)} -> 46232 | G45: =VLOOKUP(C45,Vendor_list!A:D,3,0) -> EM90 | H45: 287500 | I45: Medium | J45: Overdue | L45: =IF(J45="Paid",K45,IF(J45="Open",F45,F45+INDEX(Vendor_list!$F$2:$F$16,MATCH(B45,Vendor_list!$B$2:$B$16,0))*Weekly_Cash_Flow_Summary!$B$9)) -> 46239
A46: AP-260045 | B46: =VLOOKUP(C46,Vendor_list!A:D,2,0) -> V00009 | C46: Bayridge Fabrication Inc. | D46: =VLOOKUP(C46,Vendor_list!A:D,4,0) -> B | E46: 46124 | F46: {=_xlfn.IFS(G46="EM15",EOMONTH(E46,0)+15, G46="EM30",EOMONTH(E46,0)+30, G46="EM45",EOMONTH(E46,0)+45, G46="EM60",EOMONTH(E46,0)+60, G46="EM90",EOMONTH(E46,0)+90, G46="OA15",E46+15, G46="OA30",E46+30, G46="OA60",E46+60)} -> 46184 | G46: =VLOOKUP(C46,Vendor_list!A:D,3,0) -> OA60 | H46: 191000 | I46: Medium | J46: Paid | K46: 46198 | L46: =IF(J46="Paid",K46,IF(J46="Open",F46,F46+INDEX(Vendor_list!$F$2:$F$16,MATCH(B46,Vendor_list!$B$2:$B$16,0))*Weekly_Cash_Flow_Summary!$B$9)) -> 46198
A47: AP-260046 | B47: =VLOOKUP(C47,Vendor_list!A:D,2,0) -> V00015 | C47: Marbleton Supply Chain Co. | D47: =VLOOKUP(C47,Vendor_list!A:D,4,0) -> C | E47: 46177 | F47: {=_xlfn.IFS(G47="EM15",EOMONTH(E47,0)+15, G47="EM30",EOMONTH(E47,0)+30, G47="EM45",EOMONTH(E47,0)+45, G47="EM60",EOMONTH(E47,0)+60, G47="EM90",EOMONTH(E47,0)+90, G47="OA15",E47+15, G47="OA30",E47+30, G47="OA60",E47+60)} -> 46237 | G47: =VLOOKUP(C47,Vendor_list!A:D,3,0) -> OA60 | H47: 38500 | I47: Low | J47: Open | L47: =IF(J47="Paid",K47,IF(J47="Open",F47,F47+INDEX(Vendor_list!$F$2:$F$16,MATCH(B47,Vendor_list!$B$2:$B$16,0))*Weekly_Cash_Flow_Summary!$B$9)) -> 46237
A48: AP-260047 | B48: =VLOOKUP(C48,Vendor_list!A:D,2,0) -> V00007 | C48: Northline Freight Services | D48: =VLOOKUP(C48,Vendor_list!A:D,4,0) -> A | E48: 46195 | F48: {=_xlfn.IFS(G48="EM15",EOMONTH(E48,0)+15, G48="EM30",EOMONTH(E48,0)+30, G48="EM45",EOMONTH(E48,0)+45, G48="EM60",EOMONTH(E48,0)+60, G48="EM90",EOMONTH(E48,0)+90, G48="OA15",E48+15, G48="OA30",E48+30, G48="OA60",E48+60)} -> 46210 | G48: =VLOOKUP(C48,Vendor_list!A:D,3,0) -> OA15 | H48: 172000 | I48: High | J48: Paid | K48: 46213 | L48: =IF(J48="Paid",K48,IF(J48="Open",F48,F48+INDEX(Vendor_list!$F$2:$F$16,MATCH(B48,Vendor_list!$B$2:$B$16,0))*Weekly_Cash_Flow_Summary!$B$9)) -> 46213
A49: AP-260048 | B49: =VLOOKUP(C49,Vendor_list!A:D,2,0) -> V00015 | C49: Marbleton Supply Chain Co. | D49: =VLOOKUP(C49,Vendor_list!A:D,4,0) -> C | E49: 46208 | F49: {=_xlfn.IFS(G49="EM15",EOMONTH(E49,0)+15, G49="EM30",EOMONTH(E49,0)+30, G49="EM45",EOMONTH(E49,0)+45, G49="EM60",EOMONTH(E49,0)+60, G49="EM90",EOMONTH(E49,0)+90, G49="OA15",E49+15, G49="OA30",E49+30, G49="OA60",E49+60)} -> 46268 | G49: =VLOOKUP(C49,Vendor_list!A:D,3,0) -> OA60 | H49: 132000 | I49: Low | J49: Open | L49: =IF(J49="Paid",K49,IF(J49="Open",F49,F49+INDEX(Vendor_list!$F$2:$F$16,MATCH(B49,Vendor_list!$B$2:$B$16,0))*Weekly_Cash_Flow_Summary!$B$9)) -> 46268
A50: AP-260049 | B50: =VLOOKUP(C50,Vendor_list!A:D,2,0) -> V00003 | C50: Amberfield Textiles | D50: =VLOOKUP(C50,Vendor_list!A:D,4,0) -> C | E50: 46167 | F50: {=_xlfn.IFS(G50="EM15",EOMONTH(E50,0)+15, G50="EM30",EOMONTH(E50,0)+30, G50="EM45",EOMONTH(E50,0)+45, G50="EM60",EOMONTH(E50,0)+60, G50="EM90",EOMONTH(E50,0)+90, G50="OA15",E50+15, G50="OA30",E50+30, G50="OA60",E50+60)} -> 46197 | G50: =VLOOKUP(C50,Vendor_list!A:D,3,0) -> OA30 | H50: 231000 | I50: Medium | J50: Paid | K50: 46213 | L50: =IF(J50="Paid",K50,IF(J50="Open",F50,F50+INDEX(Vendor_list!$F$2:$F$16,MATCH(B50,Vendor_list!$B$2:$B$16,0))*Weekly_Cash_Flow_Summary!$B$9)) -> 46213
A51: AP-260050 | B51: =VLOOKUP(C51,Vendor_list!A:D,2,0) -> V00010 | C51: Timberline Wholesale Goods | D51: =VLOOKUP(C51,Vendor_list!A:D,4,0) -> C | E51: 46137 | F51: {=_xlfn.IFS(G51="EM15",EOMONTH(E51,0)+15, G51="EM30",EOMONTH(E51,0)+30, G51="EM45",EOMONTH(E51,0)+45, G51="EM60",EOMONTH(E51,0)+60, G51="EM90",EOMONTH(E51,0)+90, G51="OA15",E51+15, G51="OA30",E51+30, G51="OA60",E51+60)} -> 46152 | G51: =VLOOKUP(C51,Vendor_list!A:D,3,0) -> OA15 | H51: 33000 | I51: Low | J51: Paid | K51: 46167 | L51: =IF(J51="Paid",K51,IF(J51="Open",F51,F51+INDEX(Vendor_list!$F$2:$F$16,MATCH(B51,Vendor_list!$B$2:$B$16,0))*Weekly_Cash_Flow_Summary!$B$9)) -> 46167
A52: AP-260051 | B52: =VLOOKUP(C52,Vendor_list!A:D,2,0) -> V00013 | C52: Ashford Raw Materials Ltd. | D52: =VLOOKUP(C52,Vendor_list!A:D,4,0) -> B | E52: 46142 | F52: {=_xlfn.IFS(G52="EM15",EOMONTH(E52,0)+15, G52="EM30",EOMONTH(E52,0)+30, G52="EM45",EOMONTH(E52,0)+45, G52="EM60",EOMONTH(E52,0)+60, G52="EM90",EOMONTH(E52,0)+90, G52="OA15",E52+15, G52="OA30",E52+30, G52="OA60",E52+60)} -> 46172 | G52: =VLOOKUP(C52,Vendor_list!A:D,3,0) -> OA30 | H52: 141500 | I52: Low | J52: Paid | K52: 46198 | L52: =IF(J52="Paid",K52,IF(J52="Open",F52,F52+INDEX(Vendor_list!$F$2:$F$16,MATCH(B52,Vendor_list!$B$2:$B$16,0))*Weekly_Cash_Flow_Summary!$B$9)) -> 46198
A53: AP-260052 | B53: =VLOOKUP(C53,Vendor_list!A:D,2,0) -> V00005 | C53: Summit Ridge Components | D53: =VLOOKUP(C53,Vendor_list!A:D,4,0) -> A | E53: 46210 | F53: {=_xlfn.IFS(G53="EM15",EOMONTH(E53,0)+15, G53="EM30",EOMONTH(E53,0)+30, G53="EM45",EOMONTH(E53,0)+45, G53="EM60",EOMONTH(E53,0)+60, G53="EM90",EOMONTH(E53,0)+90, G53="OA15",E53+15, G53="OA30",E53+30, G53="OA60",E53+60)} -> 46249 | G53: =VLOOKUP(C53,Vendor_list!A:D,3,0) -> EM15 | H53: 163000 | I53: High | J53: Open | L53: =IF(J53="Paid",K53,IF(J53="Open",F53,F53+INDEX(Vendor_list!$F$2:$F$16,MATCH(B53,Vendor_list!$B$2:$B$16,0))*Weekly_Cash_Flow_Summary!$B$9)) -> 46249
A54: AP-260053 | B54: =VLOOKUP(C54,Vendor_list!A:D,2,0) -> V00013 | C54: Ashford Raw Materials Ltd. | D54: =VLOOKUP(C54,Vendor_list!A:D,4,0) -> B | E54: 46139 | F54: {=_xlfn.IFS(G54="EM15",EOMONTH(E54,0)+15, G54="EM30",EOMONTH(E54,0)+30, G54="EM45",EOMONTH(E54,0)+45, G54="EM60",EOMONTH(E54,0)+60, G54="EM90",EOMONTH(E54,0)+90, G54="OA15",E54+15, G54="OA30",E54+30, G54="OA60",E54+60)} -> 46169 | G54: =VLOOKUP(C54,Vendor_list!A:D,3,0) -> OA30 | H54: 57500 | I54: Low | J54: Paid | K54: 46198 | L54: =IF(J54="Paid",K54,IF(J54="Open",F54,F54+INDEX(Vendor_list!$F$2:$F$16,MATCH(B54,Vendor_list!$B$2:$B$16,0))*Weekly_Cash_Flow_Summary!$B$9)) -> 46198
A55: AP-260054 | B55: =VLOOKUP(C55,Vendor_list!A:D,2,0) -> V00014 | C55: Kestrel Logistics Group | D55: =VLOOKUP(C55,Vendor_list!A:D,4,0) -> C | E55: 46165 | F55: {=_xlfn.IFS(G55="EM15",EOMONTH(E55,0)+15, G55="EM30",EOMONTH(E55,0)+30, G55="EM45",EOMONTH(E55,0)+45, G55="EM60",EOMONTH(E55,0)+60, G55="EM90",EOMONTH(E55,0)+90, G55="OA15",E55+15, G55="OA30",E55+30, G55="OA60",E55+60)} -> 46180 | G55: =VLOOKUP(C55,Vendor_list!A:D,3,0) -> OA15 | H55: 177500 | I55: Low | J55: Paid | K55: 46198 | L55: =IF(J55="Paid",K55,IF(J55="Open",F55,F55+INDEX(Vendor_list!$F$2:$F$16,MATCH(B55,Vendor_list!$B$2:$B$16,0))*Weekly_Cash_Flow_Summary!$B$9)) -> 46198
A56: AP-260055 | B56: =VLOOKUP(C56,Vendor_list!A:D,2,0) -> V00011 | C56: Highcastle Equipment Co. | D56: =VLOOKUP(C56,Vendor_list!A:D,4,0) -> C | E56: 46134 | F56: {=_xlfn.IFS(G56="EM15",EOMONTH(E56,0)+15, G56="EM30",EOMONTH(E56,0)+30, G56="EM45",EOMONTH(E56,0)+45, G56="EM60",EOMONTH(E56,0)+60, G56="EM90",EOMONTH(E56,0)+90, G56="OA15",E56+15, G56="OA30",E56+30, G56="OA60",E56+60)} -> 46232 | G56: =VLOOKUP(C56,Vendor_list!A:D,3,0) -> EM90 | H56: 200000 | I56: High | J56: Overdue | L56: =IF(J56="Paid",K56,IF(J56="Open",F56,F56+INDEX(Vendor_list!$F$2:$F$16,MATCH(B56,Vendor_list!$B$2:$B$16,0))*Weekly_Cash_Flow_Summary!$B$9)) -> 46234
A57: AP-260056 | B57: =VLOOKUP(C57,Vendor_list!A:D,2,0) -> V00015 | C57: Marbleton Supply Chain Co. | D57: =VLOOKUP(C57,Vendor_list!A:D,4,0) -> C | E57: 46152 | F57: {=_xlfn.IFS(G57="EM15",EOMONTH(E57,0)+15, G57="EM30",EOMONTH(E57,0)+30, G57="EM45",EOMONTH(E57,0)+45, G57="EM60",EOMONTH(E57,0)+60, G57="EM90",EOMONTH(E57,0)+90, G57="OA15",E57+15, G57="OA30",E57+30, G57="OA60",E57+60)} -> 46212 | G57: =VLOOKUP(C57,Vendor_list!A:D,3,0) -> OA60 | H57: 120000 | I57: Low | J57: Overdue | L57: =IF(J57="Paid",K57,IF(J57="Open",F57,F57+INDEX(Vendor_list!$F$2:$F$16,MATCH(B57,Vendor_list!$B$2:$B$16,0))*Weekly_Cash_Flow_Summary!$B$9)) -> 46227
A58: AP-260057 | B58: =VLOOKUP(C58,Vendor_list!A:D,2,0) -> V00003 | C58: Amberfield Textiles | D58: =VLOOKUP(C58,Vendor_list!A:D,4,0) -> C | E58: 46155 | F58: {=_xlfn.IFS(G58="EM15",EOMONTH(E58,0)+15, G58="EM30",EOMONTH(E58,0)+30, G58="EM45",EOMONTH(E58,0)+45, G58="EM60",EOMONTH(E58,0)+60, G58="EM90",EOMONTH(E58,0)+90, G58="OA15",E58+15, G58="OA30",E58+30, G58="OA60",E58+60)} -> 46185 | G58: =VLOOKUP(C58,Vendor_list!A:D,3,0) -> OA30 | H58: 131000 | I58: Medium | J58: Paid | K58: 46198 | L58: =IF(J58="Paid",K58,IF(J58="Open",F58,F58+INDEX(Vendor_list!$F$2:$F$16,MATCH(B58,Vendor_list!$B$2:$B$16,0))*Weekly_Cash_Flow_Summary!$B$9)) -> 46198
A59: AP-260058 | B59: =VLOOKUP(C59,Vendor_list!A:D,2,0) -> V00011 | C59: Highcastle Equipment Co. | D59: =VLOOKUP(C59,Vendor_list!A:D,4,0) -> C | E59: 46219 | F59: {=_xlfn.IFS(G59="EM15",EOMONTH(E59,0)+15, G59="EM30",EOMONTH(E59,0)+30, G59="EM45",EOMONTH(E59,0)+45, G59="EM60",EOMONTH(E59,0)+60, G59="EM90",EOMONTH(E59,0)+90, G59="OA15",E59+15, G59="OA30",E59+30, G59="OA60",E59+60)} -> 46324 | G59: =VLOOKUP(C59,Vendor_list!A:D,3,0) -> EM90 | H59: 243500 | I59: High | J59: Open | L59: =IF(J59="Paid",K59,IF(J59="Open",F59,F59+INDEX(Vendor_list!$F$2:$F$16,MATCH(B59,Vendor_list!$B$2:$B$16,0))*Weekly_Cash_Flow_Summary!$B$9)) -> 46324
A60: AP-260059 | B60: =VLOOKUP(C60,Vendor_list!A:D,2,0) -> V00013 | C60: Ashford Raw Materials Ltd. | D60: =VLOOKUP(C60,Vendor_list!A:D,4,0) -> B | E60: 46114 | F60: {=_xlfn.IFS(G60="EM15",EOMONTH(E60,0)+15, G60="EM30",EOMONTH(E60,0)+30, G60="EM45",EOMONTH(E60,0)+45, G60="EM60",EOMONTH(E60,0)+60, G60="EM90",EOMONTH(E60,0)+90, G60="OA15",E60+15, G60="OA30",E60+30, G60="OA60",E60+60)} -> 46144 | G60: =VLOOKUP(C60,Vendor_list!A:D,3,0) -> OA30 | H60: 262500 | I60: Low | J60: Overdue | L60: =IF(J60="Paid",K60,IF(J60="Open",F60,F60+INDEX(Vendor_list!$F$2:$F$16,MATCH(B60,Vendor_list!$B$2:$B$16,0))*Weekly_Cash_Flow_Summary!$B$9)) -> 46159
A61: AP-260060 | B61: =VLOOKUP(C61,Vendor_list!A:D,2,0) -> V00002 | C61: Coastal Line Logistics | D61: =VLOOKUP(C61,Vendor_list!A:D,4,0) -> C | E61: 46126 | F61: {=_xlfn.IFS(G61="EM15",EOMONTH(E61,0)+15, G61="EM30",EOMONTH(E61,0)+30, G61="EM45",EOMONTH(E61,0)+45, G61="EM60",EOMONTH(E61,0)+60, G61="EM90",EOMONTH(E61,0)+90, G61="OA15",E61+15, G61="OA30",E61+30, G61="OA60",E61+60)} -> 46232 | G61: =VLOOKUP(C61,Vendor_list!A:D,3,0) -> EM90 | H61: 216500 | I61: High | J61: Overdue | L61: =IF(J61="Paid",K61,IF(J61="Open",F61,F61+INDEX(Vendor_list!$F$2:$F$16,MATCH(B61,Vendor_list!$B$2:$B$16,0))*Weekly_Cash_Flow_Summary!$B$9)) -> 46234
A62: AP-260061 | B62: =VLOOKUP(C62,Vendor_list!A:D,2,0) -> V00002 | C62: Coastal Line Logistics | D62: =VLOOKUP(C62,Vendor_list!A:D,4,0) -> C | E62: 46218 | F62: {=_xlfn.IFS(G62="EM15",EOMONTH(E62,0)+15, G62="EM30",EOMONTH(E62,0)+30, G62="EM45",EOMONTH(E62,0)+45, G62="EM60",EOMONTH(E62,0)+60, G62="EM90",EOMONTH(E62,0)+90, G62="OA15",E62+15, G62="OA30",E62+30, G62="OA60",E62+60)} -> 46324 | G62: =VLOOKUP(C62,Vendor_list!A:D,3,0) -> EM90 | H62: 285000 | I62: High | J62: Open | L62: =IF(J62="Paid",K62,IF(J62="Open",F62,F62+INDEX(Vendor_list!$F$2:$F$16,MATCH(B62,Vendor_list!$B$2:$B$16,0))*Weekly_Cash_Flow_Summary!$B$9)) -> 46324
A63: AP-260062 | B63: =VLOOKUP(C63,Vendor_list!A:D,2,0) -> V00013 | C63: Ashford Raw Materials Ltd. | D63: =VLOOKUP(C63,Vendor_list!A:D,4,0) -> B | E63: 46232 | F63: {=_xlfn.IFS(G63="EM15",EOMONTH(E63,0)+15, G63="EM30",EOMONTH(E63,0)+30, G63="EM45",EOMONTH(E63,0)+45, G63="EM60",EOMONTH(E63,0)+60, G63="EM90",EOMONTH(E63,0)+90, G63="OA15",E63+15, G63="OA30",E63+30, G63="OA60",E63+60)} -> 46262 | G63: =VLOOKUP(C63,Vendor_list!A:D,3,0) -> OA30 | H63: 86000 | I63: Low | J63: Open | L63: =IF(J63="Paid",K63,IF(J63="Open",F63,F63+INDEX(Vendor_list!$F$2:$F$16,MATCH(B63,Vendor_list!$B$2:$B$16,0))*Weekly_Cash_Flow_Summary!$B$9)) -> 46262
A64: AP-260063 | B64: =VLOOKUP(C64,Vendor_list!A:D,2,0) -> V00012 | C64: Starling Print & Packaging | D64: =VLOOKUP(C64,Vendor_list!A:D,4,0) -> B | E64: 46165 | F64: {=_xlfn.IFS(G64="EM15",EOMONTH(E64,0)+15, G64="EM30",EOMONTH(E64,0)+30, G64="EM45",EOMONTH(E64,0)+45, G64="EM60",EOMONTH(E64,0)+60, G64="EM90",EOMONTH(E64,0)+90, G64="OA15",E64+15, G64="OA30",E64+30, G64="OA60",E64+60)} -> 46180 | G64: =VLOOKUP(C64,Vendor_list!A:D,3,0) -> OA15 | H64: 268000 | I64: Low | J64: Paid | K64: 46198 | L64: =IF(J64="Paid",K64,IF(J64="Open",F64,F64+INDEX(Vendor_list!$F$2:$F$16,MATCH(B64,Vendor_list!$B$2:$B$16,0))*Weekly_Cash_Flow_Summary!$B$9)) -> 46198
A65: AP-260064 | B65: =VLOOKUP(C65,Vendor_list!A:D,2,0) -> V00008 | C65: Copperfield Industrial Supply | D65: =VLOOKUP(C65,Vendor_list!A:D,4,0) -> C | E65: 46152 | F65: {=_xlfn.IFS(G65="EM15",EOMONTH(E65,0)+15, G65="EM30",EOMONTH(E65,0)+30, G65="EM45",EOMONTH(E65,0)+45, G65="EM60",EOMONTH(E65,0)+60, G65="EM90",EOMONTH(E65,0)+90, G65="OA15",E65+15, G65="OA30",E65+30, G65="OA60",E65+60)} -> 46233 | G65: =VLOOKUP(C65,Vendor_list!A:D,3,0) -> EM60 | H65: 163000 | I65: Medium | J65: Open | L65: =IF(J65="Paid",K65,IF(J65="Open",F65,F65+INDEX(Vendor_list!$F$2:$F$16,MATCH(B65,Vendor_list!$B$2:$B$16,0))*Weekly_Cash_Flow_Summary!$B$9)) -> 46233
A66: AP-260065 | B66: =VLOOKUP(C66,Vendor_list!A:D,2,0) -> V00004 | C66: Redwood Packaging Co. | D66: =VLOOKUP(C66,Vendor_list!A:D,4,0) -> B | E66: 46154 | F66: {=_xlfn.IFS(G66="EM15",EOMONTH(E66,0)+15, G66="EM30",EOMONTH(E66,0)+30, G66="EM45",EOMONTH(E66,0)+45, G66="EM60",EOMONTH(E66,0)+60, G66="EM90",EOMONTH(E66,0)+90, G66="OA15",E66+15, G66="OA30",E66+30, G66="OA60",E66+60)} -> 46263 | G66: =VLOOKUP(C66,Vendor_list!A:D,3,0) -> EM90 | H66: 62000 | I66: Medium | J66: Open | L66: =IF(J66="Paid",K66,IF(J66="Open",F66,F66+INDEX(Vendor_list!$F$2:$F$16,MATCH(B66,Vendor_list!$B$2:$B$16,0))*Weekly_Cash_Flow_Summary!$B$9)) -> 46263
A67: AP-260066 | B67: =VLOOKUP(C67,Vendor_list!A:D,2,0) -> V00013 | C67: Ashford Raw Materials Ltd. | D67: =VLOOKUP(C67,Vendor_list!A:D,4,0) -> B | E67: 46159 | F67: {=_xlfn.IFS(G67="EM15",EOMONTH(E67,0)+15, G67="EM30",EOMONTH(E67,0)+30, G67="EM45",EOMONTH(E67,0)+45, G67="EM60",EOMONTH(E67,0)+60, G67="EM90",EOMONTH(E67,0)+90, G67="OA15",E67+15, G67="OA30",E67+30, G67="OA60",E67+60)} -> 46189 | G67: =VLOOKUP(C67,Vendor_list!A:D,3,0) -> OA30 | H67: 162500 | I67: Low | J67: Paid | K67: 46213 | L67: =IF(J67="Paid",K67,IF(J67="Open",F67,F67+INDEX(Vendor_list!$F$2:$F$16,MATCH(B67,Vendor_list!$B$2:$B$16,0))*Weekly_Cash_Flow_Summary!$B$9)) -> 46213
A68: AP-260067 | B68: =VLOOKUP(C68,Vendor_list!A:D,2,0) -> V00007 | C68: Northline Freight Services | D68: =VLOOKUP(C68,Vendor_list!A:D,4,0) -> A | E68: 46192 | F68: {=_xlfn.IFS(G68="EM15",EOMONTH(E68,0)+15, G68="EM30",EOMONTH(E68,0)+30, G68="EM45",EOMONTH(E68,0)+45, G68="EM60",EOMONTH(E68,0)+60, G68="EM90",EOMONTH(E68,0)+90, G68="OA15",E68+15, G68="OA30",E68+30, G68="OA60",E68+60)} -> 46207 | G68: =VLOOKUP(C68,Vendor_list!A:D,3,0) -> OA15 | H68: 245500 | I68: High | J68: Paid | K68: 46213 | L68: =IF(J68="Paid",K68,IF(J68="Open",F68,F68+INDEX(Vendor_list!$F$2:$F$16,MATCH(B68,Vendor_list!$B$2:$B$16,0))*Weekly_Cash_Flow_Summary!$B$9)) -> 46213
A69: AP-260068 | B69: =VLOOKUP(C69,Vendor_list!A:D,2,0) -> V00008 | C69: Copperfield Industrial Supply | D69: =VLOOKUP(C69,Vendor_list!A:D,4,0) -> C | E69: 46138 | F69: {=_xlfn.IFS(G69="EM15",EOMONTH(E69,0)+15, G69="EM30",EOMONTH(E69,0)+30, G69="EM45",EOMONTH(E69,0)+45, G69="EM60",EOMONTH(E69,0)+60, G69="EM90",EOMONTH(E69,0)+90, G69="OA15",E69+15, G69="OA30",E69+30, G69="OA60",E69+60)} -> 46202 | G69: =VLOOKUP(C69,Vendor_list!A:D,3,0) -> EM60 | H69: 16000 | I69: Medium | J69: Paid | K69: 46213 | L69: =IF(J69="Paid",K69,IF(J69="Open",F69,F69+INDEX(Vendor_list!$F$2:$F$16,MATCH(B69,Vendor_list!$B$2:$B$16,0))*Weekly_Cash_Flow_Summary!$B$9)) -> 46213
A70: AP-260069 | B70: =VLOOKUP(C70,Vendor_list!A:D,2,0) -> V00005 | C70: Summit Ridge Components | D70: =VLOOKUP(C70,Vendor_list!A:D,4,0) -> A | E70: 46143 | F70: {=_xlfn.IFS(G70="EM15",EOMONTH(E70,0)+15, G70="EM30",EOMONTH(E70,0)+30, G70="EM45",EOMONTH(E70,0)+45, G70="EM60",EOMONTH(E70,0)+60, G70="EM90",EOMONTH(E70,0)+90, G70="OA15",E70+15, G70="OA30",E70+30, G70="OA60",E70+60)} -> 46188 | G70: =VLOOKUP(C70,Vendor_list!A:D,3,0) -> EM15 | H70: 186000 | I70: High | J70: Paid | K70: 46198 | L70: =IF(J70="Paid",K70,IF(J70="Open",F70,F70+INDEX(Vendor_list!$F$2:$F$16,MATCH(B70,Vendor_list!$B$2:$B$16,0))*Weekly_Cash_Flow_Summary!$B$9)) -> 46198
A71: AP-260070 | B71: =VLOOKUP(C71,Vendor_list!A:D,2,0) -> V00008 | C71: Copperfield Industrial Supply | D71: =VLOOKUP(C71,Vendor_list!A:D,4,0) -> C | E71: 46172 | F71: {=_xlfn.IFS(G71="EM15",EOMONTH(E71,0)+15, G71="EM30",EOMONTH(E71,0)+30, G71="EM45",EOMONTH(E71,0)+45, G71="EM60",EOMONTH(E71,0)+60, G71="EM90",EOMONTH(E71,0)+90, G71="OA15",E71+15, G71="OA30",E71+30, G71="OA60",E71+60)} -> 46233 | G71: =VLOOKUP(C71,Vendor_list!A:D,3,0) -> EM60 | H71: 219500 | I71: Medium | J71: Open | L71: =IF(J71="Paid",K71,IF(J71="Open",F71,F71+INDEX(Vendor_list!$F$2:$F$16,MATCH(B71,Vendor_list!$B$2:$B$16,0))*Weekly_Cash_Flow_Summary!$B$9)) -> 46233
A72: AP-260071 | B72: =VLOOKUP(C72,Vendor_list!A:D,2,0) -> V00013 | C72: Ashford Raw Materials Ltd. | D72: =VLOOKUP(C72,Vendor_list!A:D,4,0) -> B | E72: 46135 | F72: {=_xlfn.IFS(G72="EM15",EOMONTH(E72,0)+15, G72="EM30",EOMONTH(E72,0)+30, G72="EM45",EOMONTH(E72,0)+45, G72="EM60",EOMONTH(E72,0)+60, G72="EM90",EOMONTH(E72,0)+90, G72="OA15",E72+15, G72="OA30",E72+30, G72="OA60",E72+60)} -> 46165 | G72: =VLOOKUP(C72,Vendor_list!A:D,3,0) -> OA30 | H72: 110000 | I72: Low | J72: Paid | K72: 46183 | L72: =IF(J72="Paid",K72,IF(J72="Open",F72,F72+INDEX(Vendor_list!$F$2:$F$16,MATCH(B72,Vendor_list!$B$2:$B$16,0))*Weekly_Cash_Flow_Summary!$B$9)) -> 46183
A73: AP-260072 | B73: =VLOOKUP(C73,Vendor_list!A:D,2,0) -> V00008 | C73: Copperfield Industrial Supply | D73: =VLOOKUP(C73,Vendor_list!A:D,4,0) -> C | E73: 46220 | F73: {=_xlfn.IFS(G73="EM15",EOMONTH(E73,0)+15, G73="EM30",EOMONTH(E73,0)+30, G73="EM45",EOMONTH(E73,0)+45, G73="EM60",EOMONTH(E73,0)+60, G73="EM90",EOMONTH(E73,0)+90, G73="OA15",E73+15, G73="OA30",E73+30, G73="OA60",E73+60)} -> 46294 | G73: =VLOOKUP(C73,Vendor_list!A:D,3,0) -> EM60 | H73: 224000 | I73: Medium | J73: Open | L73: =IF(J73="Paid",K73,IF(J73="Open",F73,F73+INDEX(Vendor_list!$F$2:$F$16,MATCH(B73,Vendor_list!$B$2:$B$16,0))*Weekly_Cash_Flow_Summary!$B$9)) -> 46294
A74: AP-260073 | B74: =VLOOKUP(C74,Vendor_list!A:D,2,0) -> V00015 | C74: Marbleton Supply Chain Co. | D74: =VLOOKUP(C74,Vendor_list!A:D,4,0) -> C | E74: 46134 | F74: {=_xlfn.IFS(G74="EM15",EOMONTH(E74,0)+15, G74="EM30",EOMONTH(E74,0)+30, G74="EM45",EOMONTH(E74,0)+45, G74="EM60",EOMONTH(E74,0)+60, G74="EM90",EOMONTH(E74,0)+90, G74="OA15",E74+15, G74="OA30",E74+30, G74="OA60",E74+60)} -> 46194 | G74: =VLOOKUP(C74,Vendor_list!A:D,3,0) -> OA60 | H74: 217000 | I74: Low | J74: Paid | K74: 46213 | L74: =IF(J74="Paid",K74,IF(J74="Open",F74,F74+INDEX(Vendor_list!$F$2:$F$16,MATCH(B74,Vendor_list!$B$2:$B$16,0))*Weekly_Cash_Flow_Summary!$B$9)) -> 46213
A75: AP-260074 | B75: =VLOOKUP(C75,Vendor_list!A:D,2,0) -> V00010 | C75: Timberline Wholesale Goods | D75: =VLOOKUP(C75,Vendor_list!A:D,4,0) -> C | E75: 46141 | F75: {=_xlfn.IFS(G75="EM15",EOMONTH(E75,0)+15, G75="EM30",EOMONTH(E75,0)+30, G75="EM45",EOMONTH(E75,0)+45, G75="EM60",EOMONTH(E75,0)+60, G75="EM90",EOMONTH(E75,0)+90, G75="OA15",E75+15, G75="OA30",E75+30, G75="OA60",E75+60)} -> 46156 | G75: =VLOOKUP(C75,Vendor_list!A:D,3,0) -> OA15 | H75: 33500 | I75: Low | J75: Paid | K75: 46183 | L75: =IF(J75="Paid",K75,IF(J75="Open",F75,F75+INDEX(Vendor_list!$F$2:$F$16,MATCH(B75,Vendor_list!$B$2:$B$16,0))*Weekly_Cash_Flow_Summary!$B$9)) -> 46183
A76: AP-260075 | B76: =VLOOKUP(C76,Vendor_list!A:D,2,0) -> V00013 | C76: Ashford Raw Materials Ltd. | D76: =VLOOKUP(C76,Vendor_list!A:D,4,0) -> B | E76: 46152 | F76: {=_xlfn.IFS(G76="EM15",EOMONTH(E76,0)+15, G76="EM30",EOMONTH(E76,0)+30, G76="EM45",EOMONTH(E76,0)+45, G76="EM60",EOMONTH(E76,0)+60, G76="EM90",EOMONTH(E76,0)+90, G76="OA15",E76+15, G76="OA30",E76+30, G76="OA60",E76+60)} -> 46182 | G76: =VLOOKUP(C76,Vendor_list!A:D,3,0) -> OA30 | H76: 207000 | I76: Low | J76: Overdue | L76: =IF(J76="Paid",K76,IF(J76="Open",F76,F76+INDEX(Vendor_list!$F$2:$F$16,MATCH(B76,Vendor_list!$B$2:$B$16,0))*Weekly_Cash_Flow_Summary!$B$9)) -> 46197
A77: AP-260076 | B77: =VLOOKUP(C77,Vendor_list!A:D,2,0) -> V00011 | C77: Highcastle Equipment Co. | D77: =VLOOKUP(C77,Vendor_list!A:D,4,0) -> C | E77: 46183 | F77: {=_xlfn.IFS(G77="EM15",EOMONTH(E77,0)+15, G77="EM30",EOMONTH(E77,0)+30, G77="EM45",EOMONTH(E77,0)+45, G77="EM60",EOMONTH(E77,0)+60, G77="EM90",EOMONTH(E77,0)+90, G77="OA15",E77+15, G77="OA30",E77+30, G77="OA60",E77+60)} -> 46293 | G77: =VLOOKUP(C77,Vendor_list!A:D,3,0) -> EM90 | H77: 225000 | I77: High | J77: Open | L77: =IF(J77="Paid",K77,IF(J77="Open",F77,F77+INDEX(Vendor_list!$F$2:$F$16,MATCH(B77,Vendor_list!$B$2:$B$16,0))*Weekly_Cash_Flow_Summary!$B$9)) -> 46293
A78: AP-260077 | B78: =VLOOKUP(C78,Vendor_list!A:D,2,0) -> V00006 | C78: Vantage Point Materials | D78: =VLOOKUP(C78,Vendor_list!A:D,4,0) -> B | E78: 46133 | F78: {=_xlfn.IFS(G78="EM15",EOMONTH(E78,0)+15, G78="EM30",EOMONTH(E78,0)+30, G78="EM45",EOMONTH(E78,0)+45, G78="EM60",EOMONTH(E78,0)+60, G78="EM90",EOMONTH(E78,0)+90, G78="OA15",E78+15, G78="OA30",E78+30, G78="OA60",E78+60)} -> 46148 | G78: =VLOOKUP(C78,Vendor_list!A:D,3,0) -> OA15 | H78: 204000 | I78: Medium | J78: Paid | K78: 46167 | L78: =IF(J78="Paid",K78,IF(J78="Open",F78,F78+INDEX(Vendor_list!$F$2:$F$16,MATCH(B78,Vendor_list!$B$2:$B$16,0))*Weekly_Cash_Flow_Summary!$B$9)) -> 46167
A79: AP-260078 | B79: =VLOOKUP(C79,Vendor_list!A:D,2,0) -> V00014 | C79: Kestrel Logistics Group | D79: =VLOOKUP(C79,Vendor_list!A:D,4,0) -> C | E79: 46169 | F79: {=_xlfn.IFS(G79="EM15",EOMONTH(E79,0)+15, G79="EM30",EOMONTH(E79,0)+30, G79="EM45",EOMONTH(E79,0)+45, G79="EM60",EOMONTH(E79,0)+60, G79="EM90",EOMONTH(E79,0)+90, G79="OA15",E79+15, G79="OA30",E79+30, G79="OA60",E79+60)} -> 46184 | G79: =VLOOKUP(C79,Vendor_list!A:D,3,0) -> OA15 | H79: 221000 | I79: Low | J79: Paid | K79: 46213 | L79: =IF(J79="Paid",K79,IF(J79="Open",F79,F79+INDEX(Vendor_list!$F$2:$F$16,MATCH(B79,Vendor_list!$B$2:$B$16,0))*Weekly_Cash_Flow_Summary!$B$9)) -> 46213
A80: AP-260079 | B80: =VLOOKUP(C80,Vendor_list!A:D,2,0) -> V00015 | C80: Marbleton Supply Chain Co. | D80: =VLOOKUP(C80,Vendor_list!A:D,4,0) -> C | E80: 46139 | F80: {=_xlfn.IFS(G80="EM15",EOMONTH(E80,0)+15, G80="EM30",EOMONTH(E80,0)+30, G80="EM45",EOMONTH(E80,0)+45, G80="EM60",EOMONTH(E80,0)+60, G80="EM90",EOMONTH(E80,0)+90, G80="OA15",E80+15, G80="OA30",E80+30, G80="OA60",E80+60)} -> 46199 | G80: =VLOOKUP(C80,Vendor_list!A:D,3,0) -> OA60 | H80: 226000 | I80: Low | J80: Overdue | L80: =IF(J80="Paid",K80,IF(J80="Open",F80,F80+INDEX(Vendor_list!$F$2:$F$16,MATCH(B80,Vendor_list!$B$2:$B$16,0))*Weekly_Cash_Flow_Summary!$B$9)) -> 46214
A81: AP-260080 | B81: =VLOOKUP(C81,Vendor_list!A:D,2,0) -> V00014 | C81: Kestrel Logistics Group | D81: =VLOOKUP(C81,Vendor_list!A:D,4,0) -> C | E81: 46151 | F81: {=_xlfn.IFS(G81="EM15",EOMONTH(E81,0)+15, G81="EM30",EOMONTH(E81,0)+30, G81="EM45",EOMONTH(E81,0)+45, G81="EM60",EOMONTH(E81,0)+60, G81="EM90",EOMONTH(E81,0)+90, G81="OA15",E81+15, G81="OA30",E81+30, G81="OA60",E81+60)} -> 46166 | G81: =VLOOKUP(C81,Vendor_list!A:D,3,0) -> OA15 | H81: 189500 | I81: Low | J81: Paid | K81: 46183 | L81: =IF(J81="Paid",K81,IF(J81="Open",F81,F81+INDEX(Vendor_list!$F$2:$F$16,MATCH(B81,Vendor_list!$B$2:$B$16,0))*Weekly_Cash_Flow_Summary!$B$9)) -> 46183
A82: AP-260081 | B82: =VLOOKUP(C82,Vendor_list!A:D,2,0) -> V00012 | C82: Starling Print & Packaging | D82: =VLOOKUP(C82,Vendor_list!A:D,4,0) -> B | E82: 46194 | F82: {=_xlfn.IFS(G82="EM15",EOMONTH(E82,0)+15, G82="EM30",EOMONTH(E82,0)+30, G82="EM45",EOMONTH(E82,0)+45, G82="EM60",EOMONTH(E82,0)+60, G82="EM90",EOMONTH(E82,0)+90, G82="OA15",E82+15, G82="OA30",E82+30, G82="OA60",E82+60)} -> 46209 | G82: =VLOOKUP(C82,Vendor_list!A:D,3,0) -> OA15 | H82: 98500 | I82: Low | J82: Paid | K82: 46228 | L82: =IF(J82="Paid",K82,IF(J82="Open",F82,F82+INDEX(Vendor_list!$F$2:$F$16,MATCH(B82,Vendor_list!$B$2:$B$16,0))*Weekly_Cash_Flow_Summary!$B$9)) -> 46228
A83: AP-260082 | B83: =VLOOKUP(C83,Vendor_list!A:D,2,0) -> V00006 | C83: Vantage Point Materials | D83: =VLOOKUP(C83,Vendor_list!A:D,4,0) -> B | E83: 46129 | F83: {=_xlfn.IFS(G83="EM15",EOMONTH(E83,0)+15, G83="EM30",EOMONTH(E83,0)+30, G83="EM45",EOMONTH(E83,0)+45, G83="EM60",EOMONTH(E83,0)+60, G83="EM90",EOMONTH(E83,0)+90, G83="OA15",E83+15, G83="OA30",E83+30, G83="OA60",E83+60)} -> 46144 | G83: =VLOOKUP(C83,Vendor_list!A:D,3,0) -> OA15 | H83: 210500 | I83: Medium | J83: Paid | K83: 46152 | L83: =IF(J83="Paid",K83,IF(J83="Open",F83,F83+INDEX(Vendor_list!$F$2:$F$16,MATCH(B83,Vendor_list!$B$2:$B$16,0))*Weekly_Cash_Flow_Summary!$B$9)) -> 46152
A84: AP-260083 | B84: =VLOOKUP(C84,Vendor_list!A:D,2,0) -> V00009 | C84: Bayridge Fabrication Inc. | D84: =VLOOKUP(C84,Vendor_list!A:D,4,0) -> B | E84: 46218 | F84: {=_xlfn.IFS(G84="EM15",EOMONTH(E84,0)+15, G84="EM30",EOMONTH(E84,0)+30, G84="EM45",EOMONTH(E84,0)+45, G84="EM60",EOMONTH(E84,0)+60, G84="EM90",EOMONTH(E84,0)+90, G84="OA15",E84+15, G84="OA30",E84+30, G84="OA60",E84+60)} -> 46278 | G84: =VLOOKUP(C84,Vendor_list!A:D,3,0) -> OA60 | H84: 173000 | I84: Medium | J84: Open | L84: =IF(J84="Paid",K84,IF(J84="Open",F84,F84+INDEX(Vendor_list!$F$2:$F$16,MATCH(B84,Vendor_list!$B$2:$B$16,0))*Weekly_Cash_Flow_Summary!$B$9)) -> 46278
A85: AP-260084 | B85: =VLOOKUP(C85,Vendor_list!A:D,2,0) -> V00008 | C85: Copperfield Industrial Supply | D85: =VLOOKUP(C85,Vendor_list!A:D,4,0) -> C | E85: 46202 | F85: {=_xlfn.IFS(G85="EM15",EOMONTH(E85,0)+15, G85="EM30",EOMONTH(E85,0)+30, G85="EM45",EOMONTH(E85,0)+45, G85="EM60",EOMONTH(E85,0)+60, G85="EM90",EOMONTH(E85,0)+90, G85="OA15",E85+15, G85="OA30",E85+30, G85="OA60",E85+60)} -> 46263 | G85: =VLOOKUP(C85,Vendor_list!A:D,3,0) -> EM60 | H85: 275000 | I85: Medium | J85: Open | L85: =IF(J85="Paid",K85,IF(J85="Open",F85,F85+INDEX(Vendor_list!$F$2:$F$16,MATCH(B85,Vendor_list!$B$2:$B$16,0))*Weekly_Cash_Flow_Summary!$B$9)) -> 46263
A86: AP-260085 | B86: =VLOOKUP(C86,Vendor_list!A:D,2,0) -> V00011 | C86: Highcastle Equipment Co. | D86: =VLOOKUP(C86,Vendor_list!A:D,4,0) -> C | E86: 46204 | F86: {=_xlfn.IFS(G86="EM15",EOMONTH(E86,0)+15, G86="EM30",EOMONTH(E86,0)+30, G86="EM45",EOMONTH(E86,0)+45, G86="EM60",EOMONTH(E86,0)+60, G86="EM90",EOMONTH(E86,0)+90, G86="OA15",E86+15, G86="OA30",E86+30, G86="OA60",E86+60)} -> 46324 | G86: =VLOOKUP(C86,Vendor_list!A:D,3,0) -> EM90 | H86: 185000 | I86: High | J86: Open | L86: =IF(J86="Paid",K86,IF(J86="Open",F86,F86+INDEX(Vendor_list!$F$2:$F$16,MATCH(B86,Vendor_list!$B$2:$B$16,0))*Weekly_Cash_Flow_Summary!$B$9)) -> 46324
A87: AP-260086 | B87: =VLOOKUP(C87,Vendor_list!A:D,2,0) -> V00003 | C87: Amberfield Textiles | D87: =VLOOKUP(C87,Vendor_list!A:D,4,0) -> C | E87: 46166 | F87: {=_xlfn.IFS(G87="EM15",EOMONTH(E87,0)+15, G87="EM30",EOMONTH(E87,0)+30, G87="EM45",EOMONTH(E87,0)+45, G87="EM60",EOMONTH(E87,0)+60, G87="EM90",EOMONTH(E87,0)+90, G87="OA15",E87+15, G87="OA30",E87+30, G87="OA60",E87+60)} -> 46196 | G87: =VLOOKUP(C87,Vendor_list!A:D,3,0) -> OA30 | H87: 228500 | I87: Medium | J87: Overdue | L87: =IF(J87="Paid",K87,IF(J87="Open",F87,F87+INDEX(Vendor_list!$F$2:$F$16,MATCH(B87,Vendor_list!$B$2:$B$16,0))*Weekly_Cash_Flow_Summary!$B$9)) -> 46203
A88: AP-260087 | B88: =VLOOKUP(C88,Vendor_list!A:D,2,0) -> V00014 | C88: Kestrel Logistics Group | D88: =VLOOKUP(C88,Vendor_list!A:D,4,0) -> C | E88: 46218 | F88: {=_xlfn.IFS(G88="EM15",EOMONTH(E88,0)+15, G88="EM30",EOMONTH(E88,0)+30, G88="EM45",EOMONTH(E88,0)+45, G88="EM60",EOMONTH(E88,0)+60, G88="EM90",EOMONTH(E88,0)+90, G88="OA15",E88+15, G88="OA30",E88+30, G88="OA60",E88+60)} -> 46233 | G88: =VLOOKUP(C88,Vendor_list!A:D,3,0) -> OA15 | H88: 235000 | I88: Low | J88: Open | L88: =IF(J88="Paid",K88,IF(J88="Open",F88,F88+INDEX(Vendor_list!$F$2:$F$16,MATCH(B88,Vendor_list!$B$2:$B$16,0))*Weekly_Cash_Flow_Summary!$B$9)) -> 46233
A89: AP-260088 | B89: =VLOOKUP(C89,Vendor_list!A:D,2,0) -> V00001 | C89: Granite Peak Manufacturing | D89: =VLOOKUP(C89,Vendor_list!A:D,4,0) -> A | E89: 46173 | F89: {=_xlfn.IFS(G89="EM15",EOMONTH(E89,0)+15, G89="EM30",EOMONTH(E89,0)+30, G89="EM45",EOMONTH(E89,0)+45, G89="EM60",EOMONTH(E89,0)+60, G89="EM90",EOMONTH(E89,0)+90, G89="OA15",E89+15, G89="OA30",E89+30, G89="OA60",E89+60)} -> 46203 | G89: =VLOOKUP(C89,Vendor_list!A:D,3,0) -> OA30 | H89: 123000 | I89: High | J89: Paid | K89: 46213 | L89: =IF(J89="Paid",K89,IF(J89="Open",F89,F89+INDEX(Vendor_list!$F$2:$F$16,MATCH(B89,Vendor_list!$B$2:$B$16,0))*Weekly_Cash_Flow_Summary!$B$9)) -> 46213
A90: AP-260089 | B90: =VLOOKUP(C90,Vendor_list!A:D,2,0) -> V00008 | C90: Copperfield Industrial Supply | D90: =VLOOKUP(C90,Vendor_list!A:D,4,0) -> C | E90: 46187 | F90: {=_xlfn.IFS(G90="EM15",EOMONTH(E90,0)+15, G90="EM30",EOMONTH(E90,0)+30, G90="EM45",EOMONTH(E90,0)+45, G90="EM60",EOMONTH(E90,0)+60, G90="EM90",EOMONTH(E90,0)+90, G90="OA15",E90+15, G90="OA30",E90+30, G90="OA60",E90+60)} -> 46263 | G90: =VLOOKUP(C90,Vendor_list!A:D,3,0) -> EM60 | H90: 190000 | I90: Medium | J90: Open | L90: =IF(J90="Paid",K90,IF(J90="Open",F90,F90+INDEX(Vendor_list!$F$2:$F$16,MATCH(B90,Vendor_list!$B$2:$B$16,0))*Weekly_Cash_Flow_Summary!$B$9)) -> 46263
A91: AP-260090 | B91: =VLOOKUP(C91,Vendor_list!A:D,2,0) -> V00009 | C91: Bayridge Fabrication Inc. | D91: =VLOOKUP(C91,Vendor_list!A:D,4,0) -> B | E91: 46190 | F91: {=_xlfn.IFS(G91="EM15",EOMONTH(E91,0)+15, G91="EM30",EOMONTH(E91,0)+30, G91="EM45",EOMONTH(E91,0)+45, G91="EM60",EOMONTH(E91,0)+60, G91="EM90",EOMONTH(E91,0)+90, G91="OA15",E91+15, G91="OA30",E91+30, G91="OA60",E91+60)} -> 46250 | G91: =VLOOKUP(C91,Vendor_list!A:D,3,0) -> OA60 | H91: 82000 | I91: Medium | J91: Open | L91: =IF(J91="Paid",K91,IF(J91="Open",F91,F91+INDEX(Vendor_list!$F$2:$F$16,MATCH(B91,Vendor_list!$B$2:$B$16,0))*Weekly_Cash_Flow_Summary!$B$9)) -> 46250
A92: AP-260091 | B92: =VLOOKUP(C92,Vendor_list!A:D,2,0) -> V00001 | C92: Granite Peak Manufacturing | D92: =VLOOKUP(C92,Vendor_list!A:D,4,0) -> A | E92: 46207 | F92: {=_xlfn.IFS(G92="EM15",EOMONTH(E92,0)+15, G92="EM30",EOMONTH(E92,0)+30, G92="EM45",EOMONTH(E92,0)+45, G92="EM60",EOMONTH(E92,0)+60, G92="EM90",EOMONTH(E92,0)+90, G92="OA15",E92+15, G92="OA30",E92+30, G92="OA60",E92+60)} -> 46237 | G92: =VLOOKUP(C92,Vendor_list!A:D,3,0) -> OA30 | H92: 24000 | I92: High | J92: Open | L92: =IF(J92="Paid",K92,IF(J92="Open",F92,F92+INDEX(Vendor_list!$F$2:$F$16,MATCH(B92,Vendor_list!$B$2:$B$16,0))*Weekly_Cash_Flow_Summary!$B$9)) -> 46237
A93: AP-260092 | B93: =VLOOKUP(C93,Vendor_list!A:D,2,0) -> V00005 | C93: Summit Ridge Components | D93: =VLOOKUP(C93,Vendor_list!A:D,4,0) -> A | E93: 46126 | F93: {=_xlfn.IFS(G93="EM15",EOMONTH(E93,0)+15, G93="EM30",EOMONTH(E93,0)+30, G93="EM45",EOMONTH(E93,0)+45, G93="EM60",EOMONTH(E93,0)+60, G93="EM90",EOMONTH(E93,0)+90, G93="OA15",E93+15, G93="OA30",E93+30, G93="OA60",E93+60)} -> 46157 | G93: =VLOOKUP(C93,Vendor_list!A:D,3,0) -> EM15 | H93: 112000 | I93: High | J93: Paid | K93: 46167 | L93: =IF(J93="Paid",K93,IF(J93="Open",F93,F93+INDEX(Vendor_list!$F$2:$F$16,MATCH(B93,Vendor_list!$B$2:$B$16,0))*Weekly_Cash_Flow_Summary!$B$9)) -> 46167
A94: AP-260093 | B94: =VLOOKUP(C94,Vendor_list!A:D,2,0) -> V00014 | C94: Kestrel Logistics Group | D94: =VLOOKUP(C94,Vendor_list!A:D,4,0) -> C | E94: 46164 | F94: {=_xlfn.IFS(G94="EM15",EOMONTH(E94,0)+15, G94="EM30",EOMONTH(E94,0)+30, G94="EM45",EOMONTH(E94,0)+45, G94="EM60",EOMONTH(E94,0)+60, G94="EM90",EOMONTH(E94,0)+90, G94="OA15",E94+15, G94="OA30",E94+30, G94="OA60",E94+60)} -> 46179 | G94: =VLOOKUP(C94,Vendor_list!A:D,3,0) -> OA15 | H94: 251000 | I94: Low | J94: Paid | K94: 46198 | L94: =IF(J94="Paid",K94,IF(J94="Open",F94,F94+INDEX(Vendor_list!$F$2:$F$16,MATCH(B94,Vendor_list!$B$2:$B$16,0))*Weekly_Cash_Flow_Summary!$B$9)) -> 46198
A95: AP-260094 | B95: =VLOOKUP(C95,Vendor_list!A:D,2,0) -> V00011 | C95: Highcastle Equipment Co. | D95: =VLOOKUP(C95,Vendor_list!A:D,4,0) -> C | E95: 46217 | F95: {=_xlfn.IFS(G95="EM15",EOMONTH(E95,0)+15, G95="EM30",EOMONTH(E95,0)+30, G95="EM45",EOMONTH(E95,0)+45, G95="EM60",EOMONTH(E95,0)+60, G95="EM90",EOMONTH(E95,0)+90, G95="OA15",E95+15, G95="OA30",E95+30, G95="OA60",E95+60)} -> 46324 | G95: =VLOOKUP(C95,Vendor_list!A:D,3,0) -> EM90 | H95: 174500 | I95: High | J95: Open | L95: =IF(J95="Paid",K95,IF(J95="Open",F95,F95+INDEX(Vendor_list!$F$2:$F$16,MATCH(B95,Vendor_list!$B$2:$B$16,0))*Weekly_Cash_Flow_Summary!$B$9)) -> 46324
A96: AP-260095 | B96: =VLOOKUP(C96,Vendor_list!A:D,2,0) -> V00008 | C96: Copperfield Industrial Supply | D96: =VLOOKUP(C96,Vendor_list!A:D,4,0) -> C | E96: 46197 | F96: {=_xlfn.IFS(G96="EM15",EOMONTH(E96,0)+15, G96="EM30",EOMONTH(E96,0)+30, G96="EM45",EOMONTH(E96,0)+45, G96="EM60",EOMONTH(E96,0)+60, G96="EM90",EOMONTH(E96,0)+90, G96="OA15",E96+15, G96="OA30",E96+30, G96="OA60",E96+60)} -> 46263 | G96: =VLOOKUP(C96,Vendor_list!A:D,3,0) -> EM60 | H96: 123000 | I96: Medium | J96: Open | L96: =IF(J96="Paid",K96,IF(J96="Open",F96,F96+INDEX(Vendor_list!$F$2:$F$16,MATCH(B96,Vendor_list!$B$2:$B$16,0))*Weekly_Cash_Flow_Summary!$B$9)) -> 46263
A97: AP-260096 | B97: =VLOOKUP(C97,Vendor_list!A:D,2,0) -> V00014 | C97: Kestrel Logistics Group | D97: =VLOOKUP(C97,Vendor_list!A:D,4,0) -> C | E97: 46227 | F97: {=_xlfn.IFS(G97="EM15",EOMONTH(E97,0)+15, G97="EM30",EOMONTH(E97,0)+30, G97="EM45",EOMONTH(E97,0)+45, G97="EM60",EOMONTH(E97,0)+60, G97="EM90",EOMONTH(E97,0)+90, G97="OA15",E97+15, G97="OA30",E97+30, G97="OA60",E97+60)} -> 46242 | G97: =VLOOKUP(C97,Vendor_list!A:D,3,0) -> OA15 | H97: 183500 | I97: Low | J97: Open | L97: =IF(J97="Paid",K97,IF(J97="Open",F97,F97+INDEX(Vendor_list!$F$2:$F$16,MATCH(B97,Vendor_list!$B$2:$B$16,0))*Weekly_Cash_Flow_Summary!$B$9)) -> 46242
A98: AP-260097 | B98: =VLOOKUP(C98,Vendor_list!A:D,2,0) -> V00003 | C98: Amberfield Textiles | D98: =VLOOKUP(C98,Vendor_list!A:D,4,0) -> C | E98: 46123 | F98: {=_xlfn.IFS(G98="EM15",EOMONTH(E98,0)+15, G98="EM30",EOMONTH(E98,0)+30, G98="EM45",EOMONTH(E98,0)+45, G98="EM60",EOMONTH(E98,0)+60, G98="EM90",EOMONTH(E98,0)+90, G98="OA15",E98+15, G98="OA30",E98+30, G98="OA60",E98+60)} -> 46153 | G98: =VLOOKUP(C98,Vendor_list!A:D,3,0) -> OA30 | H98: 252000 | I98: Medium | J98: Overdue | L98: =IF(J98="Paid",K98,IF(J98="Open",F98,F98+INDEX(Vendor_list!$F$2:$F$16,MATCH(B98,Vendor_list!$B$2:$B$16,0))*Weekly_Cash_Flow_Summary!$B$9)) -> 46160
A99: AP-260098 | B99: =VLOOKUP(C99,Vendor_list!A:D,2,0) -> V00003 | C99: Amberfield Textiles | D99: =VLOOKUP(C99,Vendor_list!A:D,4,0) -> C | E99: 46145 | F99: {=_xlfn.IFS(G99="EM15",EOMONTH(E99,0)+15, G99="EM30",EOMONTH(E99,0)+30, G99="EM45",EOMONTH(E99,0)+45, G99="EM60",EOMONTH(E99,0)+60, G99="EM90",EOMONTH(E99,0)+90, G99="OA15",E99+15, G99="OA30",E99+30, G99="OA60",E99+60)} -> 46175 | G99: =VLOOKUP(C99,Vendor_list!A:D,3,0) -> OA30 | H99: 265500 | I99: Medium | J99: Paid | K99: 46183 | L99: =IF(J99="Paid",K99,IF(J99="Open",F99,F99+INDEX(Vendor_list!$F$2:$F$16,MATCH(B99,Vendor_list!$B$2:$B$16,0))*Weekly_Cash_Flow_Summary!$B$9)) -> 46183
A100: AP-260099 | B100: =VLOOKUP(C100,Vendor_list!A:D,2,0) -> V00002 | C100: Coastal Line Logistics | D100: =VLOOKUP(C100,Vendor_list!A:D,4,0) -> C | E100: 46120 | F100: {=_xlfn.IFS(G100="EM15",EOMONTH(E100,0)+15, G100="EM30",EOMONTH(E100,0)+30, G100="EM45",EOMONTH(E100,0)+45, G100="EM60",EOMONTH(E100,0)+60, G100="EM90",EOMONTH(E100,0)+90, G100="OA15",E100+15, G100="OA30",E100+30, G100="OA60",E100+60)} -> 46232 | G100: =VLOOKUP(C100,Vendor_list!A:D,3,0) -> EM90 | H100: 122000 | I100: High | J100: Overdue | L100: =IF(J100="Paid",K100,IF(J100="Open",F100,F100+INDEX(Vendor_list!$F$2:$F$16,MATCH(B100,Vendor_list!$B$2:$B$16,0))*Weekly_Cash_Flow_Summary!$B$9)) -> 46234
...

Sheet Customer_list
A1: Customer_Name | B1: Customer_Code | C1: Payment_Terms | D1: Department | E1: Payment Habit | F1: Credit Limit | G1: Collection_Probability | H1: Typical_Delay_Days | J1: Habit | K1: Base_Probability | L1: Typical_Delay_Days
A2: Silverline Retail Group | B2: C00001 | C2: EM15 | D2: C | E2: Good | F2: 1150000 | G2: =INDEX($K$2:$K$4,MATCH(E2,$J$2:$J$4,0)) -> 0.97 | H2: =INDEX($L$2:$L$4,MATCH(E2,$J$2:$J$4,0)) -> 3 | J2: Good | K2: 0.97 | L2: 3
A3: Northgate Commerce Co. | B3: C00002 | C3: OA60 | D3: B | E3: Average | F3: 350000 | G3: =INDEX($K$2:$K$4,MATCH(E3,$J$2:$J$4,0)) -> 0.9 | H3: =INDEX($L$2:$L$4,MATCH(E3,$J$2:$J$4,0)) -> 10 | J3: Average | K3: 0.9 | L3: 10
A4: BluePeak Distributors | B4: C00003 | C4: EM60 | D4: A | E4: Good | F4: 550000 | G4: =INDEX($K$2:$K$4,MATCH(E4,$J$2:$J$4,0)) -> 0.97 | H4: =INDEX($L$2:$L$4,MATCH(E4,$J$2:$J$4,0)) -> 3 | J4: Poor | K4: 0.75 | L4: 25
A5: Harborview Trading Ltd. | B5: C00004 | C5: EM60 | D5: B | E5: Average | F5: 550000 | G5: =INDEX($K$2:$K$4,MATCH(E5,$J$2:$J$4,0)) -> 0.9 | H5: =INDEX($L$2:$L$4,MATCH(E5,$J$2:$J$4,0)) -> 10
A6: Crestwood Merchandise Inc. | B6: C00005 | C6: OA30 | D6: C | E6: Poor | F6: 250000 | G6: =INDEX($K$2:$K$4,MATCH(E6,$J$2:$J$4,0)) -> 0.75 | H6: =INDEX($L$2:$L$4,MATCH(E6,$J$2:$J$4,0)) -> 25
A7: Meadowbrook Supply Co. | B7: C00006 | C7: EM60 | D7: B | E7: Average | F7: 500000 | G7: =INDEX($K$2:$K$4,MATCH(E7,$J$2:$J$4,0)) -> 0.9 | H7: =INDEX($L$2:$L$4,MATCH(E7,$J$2:$J$4,0)) -> 10
A8: Ironstone Enterprises | B8: C00007 | C8: EM30 | D8: A | E8: Good | F8: 650000 | G8: =INDEX($K$2:$K$4,MATCH(E8,$J$2:$J$4,0)) -> 0.97 | H8: =INDEX($L$2:$L$4,MATCH(E8,$J$2:$J$4,0)) -> 3
A9: Sunridge Retail Partners | B9: C00008 | C9: OA30 | D9: B | E9: Average | F9: 350000 | G9: =INDEX($K$2:$K$4,MATCH(E9,$J$2:$J$4,0)) -> 0.9 | H9: =INDEX($L$2:$L$4,MATCH(E9,$J$2:$J$4,0)) -> 10
A10: Westfall Commercial Group | B10: C00009 | C10: EM30 | D10: A | E10: Average | F10: 350000 | G10: =INDEX($K$2:$K$4,MATCH(E10,$J$2:$J$4,0)) -> 0.9 | H10: =INDEX($L$2:$L$4,MATCH(E10,$J$2:$J$4,0)) -> 10
A11: Oakhaven Trading Co. | B11: C00010 | C11: OA30 | D11: A | E11: Good | F11: 1100000 | G11: =INDEX($K$2:$K$4,MATCH(E11,$J$2:$J$4,0)) -> 0.97 | H11: =INDEX($L$2:$L$4,MATCH(E11,$J$2:$J$4,0)) -> 3
A12: Riverton Wholesale Ltd. | B12: C00011 | C12: OA15 | D12: B | E12: Poor | F12: 300000 | G12: =INDEX($K$2:$K$4,MATCH(E12,$J$2:$J$4,0)) -> 0.75 | H12: =INDEX($L$2:$L$4,MATCH(E12,$J$2:$J$4,0)) -> 25
A13: Goldenbridge Retailers | B13: C00012 | C13: OA30 | D13: B | E13: Average | F13: 300000 | G13: =INDEX($K$2:$K$4,MATCH(E13,$J$2:$J$4,0)) -> 0.9 | H13: =INDEX($L$2:$L$4,MATCH(E13,$J$2:$J$4,0)) -> 10
A14: Pinehill Distribution Inc. | B14: C00013 | C14: OA30 | D14: B | E14: Poor | F14: 100000 | G14: =INDEX($K$2:$K$4,MATCH(E14,$J$2:$J$4,0)) -> 0.75 | H14: =INDEX($L$2:$L$4,MATCH(E14,$J$2:$J$4,0)) -> 25
A15: Clearwater Commerce Co. | B15: C00014 | C15: EM45 | D15: A | E15: Good | F15: 600000 | G15: =INDEX($K$2:$K$4,MATCH(E15,$J$2:$J$4,0)) -> 0.97 | H15: =INDEX($L$2:$L$4,MATCH(E15,$J$2:$J$4,0)) -> 3
A16: Brightstone Supply Group | B16: C00015 | C16: EM45 | D16: B | E16: Poor | F16: 200000 | G16: =INDEX($K$2:$K$4,MATCH(E16,$J$2:$J$4,0)) -> 0.75 | H16: =INDEX($L$2:$L$4,MATCH(E16,$J$2:$J$4,0)) -> 25
... A21: Willowmere Commercial Ltd. | B21: C00020 | C21: EM60 | D21: C | E21: Good | F21: 1100000 | G21: =INDEX($K$2:$K$4,MATCH(E21,$J$2:$J$4,0)) -> 0.97 | H21: =INDEX($L$2:$L$4,MATCH(E21,$J$2:$J$4,0)) -> 3

Sheet Vendor_list
A1: Vendor_Name | B1: Vendor_Code | C1: Payment_Terms | D1: Department | E1: Priority | F1: Typical_Delay_Days | H1: Priority | I1: Typical_Delay_Days
A2: Granite Peak Manufacturing | B2: V00001 | C2: OA30 | D2: A | E2: High | F2: =INDEX($I$2:$I$4,MATCH(E2,$H$2:$H$4,0)) -> 2 | H2: High | I2: 2
A3: Coastal Line Logistics | B3: V00002 | C3: EM90 | D3: C | E3: High | F3: =INDEX($I$2:$I$4,MATCH(E3,$H$2:$H$4,0)) -> 2 | H3: Medium | I3: 7
A4: Amberfield Textiles | B4: V00003 | C4: OA30 | D4: C | E4: Medium | F4: =INDEX($I$2:$I$4,MATCH(E4,$H$2:$H$4,0)) -> 7 | H4: Low | I4: 15
A5: Redwood Packaging Co. | B5: V00004 | C5: EM90 | D5: B | E5: Medium | F5: =INDEX($I$2:$I$4,MATCH(E5,$H$2:$H$4,0)) -> 7
A6: Summit Ridge Components | B6: V00005 | C6: EM15 | D6: A | E6: High | F6: =INDEX($I$2:$I$4,MATCH(E6,$H$2:$H$4,0)) -> 2
A7: Vantage Point Materials | B7: V00006 | C7: OA15 | D7: B | E7: Medium | F7: =INDEX($I$2:$I$4,MATCH(E7,$H$2:$H$4,0)) -> 7
A8: Northline Freight Services | B8: V00007 | C8: OA15 | D8: A | E8: High | F8: =INDEX($I$2:$I$4,MATCH(E8,$H$2:$H$4,0)) -> 2
A9: Copperfield Industrial Supply | B9: V00008 | C9: EM60 | D9: C | E9: Medium | F9: =INDEX($I$2:$I$4,MATCH(E9,$H$2:$H$4,0)) -> 7
A10: Bayridge Fabrication Inc. | B10: V00009 | C10: OA60 | D10: B | E10: Medium | F10: =INDEX($I$2:$I$4,MATCH(E10,$H$2:$H$4,0)) -> 7
A11: Timberline Wholesale Goods | B11: V00010 | C11: OA15 | D11: C | E11: Low | F11: =INDEX($I$2:$I$4,MATCH(E11,$H$2:$H$4,0)) -> 15
A12: Highcastle Equipment Co. | B12: V00011 | C12: EM90 | D12: C | E12: High | F12: =INDEX($I$2:$I$4,MATCH(E12,$H$2:$H$4,0)) -> 2
A13: Starling Print & Packaging | B13: V00012 | C13: OA15 | D13: B | E13: Low | F13: =INDEX($I$2:$I$4,MATCH(E13,$H$2:$H$4,0)) -> 15
A14: Ashford Raw Materials Ltd. | B14: V00013 | C14: OA30 | D14: B | E14: Low | F14: =INDEX($I$2:$I$4,MATCH(E14,$H$2:$H$4,0)) -> 15
A15: Kestrel Logistics Group | B15: V00014 | C15: OA15 | D15: C | E15: Low | F15: =INDEX($I$2:$I$4,MATCH(E15,$H$2:$H$4,0)) -> 15
A16: Marbleton Supply Chain Co. | B16: V00015 | C16: OA60 | D16: C | E16: Low | F16: =INDEX($I$2:$I$4,MATCH(E16,$H$2:$H$4,0)) -> 15
